Workbook
Name PIVOT: Data!#REF!
Name _AMO_SingleObject_328283544_ROM_F0.SEC2.Tabulate_1.SEC1.FTR.TXT1: #REF!
Name _AMO_SingleObject_328283544_ROM_F0.SEC2.Tabulate_1.SEC1.HDR.TXT1: #REF!
Name _AMO_SingleObject_328283544_ROM_F0.SEC2.Tabulate_1.SEC1.FTR.TXT2: #REF!
Name _AMO_SingleObject_328283544_ROM_F0.SEC2.Tabulate_1.SEC1.HDR.TXT2: #REF!
Name PIVOT2: #REF!
Name _AMO_SingleObject_328283544_ROM_F0.SEC2.Tabulate_1.SEC1.BDY.Cross_tabular_summary_report_Table_1: #REF!

Sheet Profile
A1: 2022 Hospital Discharge Summary Report
A4: Profile Characteristics (Individual Hospital Information will appear only if one hospital is selected)
A6: OSHPD Facility No. | B6: =IF($F$21=1,Pivot!B11,"") -> #REF!
A7: Hospital Name | B7: =IF($F$21=1,VLOOKUP($B$6,Data!A1:EP445,4,FALSE),IF(A1="(All)","",)) -> #REF!
A8: County | B8: =IF($F$21=1,VLOOKUP($B$6,Data!A1:EP445,3,FALSE),IF(Pivot!A3="(All)","",)) -> #REF!
A9: Address | B9: =IF($F$21=1,VLOOKUP($B$6,Data!A1:EP445,5,FALSE),"") -> #REF!
A10: City | B10: =IF($F$21=1,VLOOKUP($B$6,Data!A1:EP445,6,FALSE),"") -> #REF!
A11: ZIP Code | B11: =IF($F$21=1,VLOOKUP($B$6,Data!A1:EP445,7,FALSE),"") -> #REF!
A12: Type of Control | B12: =IF($F$21=1,VLOOKUP($B$6,Data!A1:EP445,8,FALSE),IF(Pivot!A2="(All)"," ",)) -> #REF!
A13: Teaching/Rural | B13: =IF($F$21=1,VLOOKUP($B$6,Data!A1:EP445,9,FALSE),IF(Pivot!A5="(All)","",)) -> #REF!
A14: Licensed Bed Size | B14: =IF($F$21=1,VLOOKUP($B$6,Data!A1:EP445,10,FALSE),IF(Pivot!A4="(All)","",)) -> #REF!
A15: Senate District | B15: =IF($F$21=1,VLOOKUP($B$6,Data!A1:EP445,11,FALSE),IF(Pivot!A6="(All)","",)) -> #REF!
A16: Assembly District | B16: =IF($F$21=1,VLOOKUP($B$6,Data!A1:EP445,12,FALSE),IF(Pivot!A7="(All)","",)) -> #REF!
A17: MSSA Designation | B17: =IF($F$21=1,VLOOKUP($B$6,Data!A1:EP445,14,FALSE),IF(Pivot!B1="(All)","",)) -> #REF!
A18: MSSA Name | B18: =IF($F$21=1,VLOOKUP($B$6,Data!A1:EP445,13,FALSE),IF(Pivot!B2="(All)","", )) -> #REF! | K18: Source: 2022 California Patient Discharge Data
A20: TYPE OF CARE | B20: # | C20: % | E20: DISCHARGES/DAYS | F20: # | I20: EXPECTED PAYER SOURCE | J20: # | K20: %
A21: Acute | B21: =GETPIVOTDATA("Sum of TOC_Acute",Pivot!$A$8) -> #REF! | C21: =B21/$B$27 -> #REF! | E21: Number of Hospital Reports | F21: =GETPIVOTDATA("Count of oshpd_id",Pivot!$A$8) -> #REF! | I21: Medi-Cal | J21: =GETPIVOTDATA("Sum of Payer_Medi_Cal",Pivot!$A$8) -> #REF! | K21: =J21/$J$31 -> #REF!
A22: Chemical Dependency | B22: =GETPIVOTDATA("Sum of TOC_Chem_Dep",Pivot!$A$8) -> #REF! | C22: =B22/$B$27 -> #REF! | E22: Number of Discharges | F22: =B27 -> #REF! | I22: Medicare | J22: =GETPIVOTDATA("Sum of Payer_Medicare",Pivot!$A$8) -> #REF! | K22: =J22/$J$31 -> #REF!
A23: Physical Rehabilitation | B23: =GETPIVOTDATA("Sum of TOC_Rehab",Pivot!$A$8) -> #REF! | C23: =B23/$B$27 -> #REF! | E23: Number of Discharge Days | F23: =GETPIVOTDATA("Sum of Dsch_Days",Pivot!$A$8) -> #REF! | I23: Private Coverage | J23: =GETPIVOTDATA("Sum of Payer_Priv_Coverage",Pivot!$A$8) -> #REF! | K23: =J23/$J$31 -> #REF!
A24: Psychiatric | B24: =GETPIVOTDATA("Sum of TOC_Psych",Pivot!$A$8) -> #REF! | C24: =B24/$B$27 -> #REF! | E24: Average Length of Stay (Days) | F24: =F23/F22 -> #REF! | I24: Self Pay | J24: =GETPIVOTDATA("Sum of Payer_Self_Pay",Pivot!$A$8) -> #REF! | K24: =J24/$J$31 -> #REF!
A25: Skilled Nursing/Intermediate Care | B25: =GETPIVOTDATA("Sum of TOC_SN_IC",Pivot!$A$8) -> #REF! | C25: =B25/$B$27 -> #REF! | I25: Workers' Compensation | J25: =GETPIVOTDATA("Sum of Payer_Workers_Comp",Pivot!$A$8) -> #REF! | K25: =J25/$J$31 -> #REF!
A26: Unknown/Blank/Invalid | B26: =GETPIVOTDATA("Sum of TOC_Unknown",Pivot!$A$8) -> #REF! | C26: =B26/$B$27 -> #REF! | I26: County Indigent Programs | J26: =GETPIVOTDATA("Sum of Payer_County_Indigent_Prog",Pivot!$A$8) -> #REF! | K26: =J26/$J$31 -> #REF!
B27: =SUM(B21:B26) -> #REF! | C27: =SUM(C21:C26) -> #REF! | E27: DNR ORDERS | F27: # | G27: % | I27: Other Government | J27: =GETPIVOTDATA("Sum of Payer_Other_Government",Pivot!$A$8) -> #REF! | K27: =J27/$J$31 -> #REF!
E28: Yes | F28: =GETPIVOTDATA("Sum of DNR_Yes",Pivot!$A$8) -> #REF! | G28: =F28/$F$31 -> #REF! | I28: Other Indigent | J28: =GETPIVOTDATA("Sum of Payer_Other_Indigent",Pivot!$A$8) -> #REF! | K28: =J28/$J$31 -> #REF!
E29: No | F29: =GETPIVOTDATA("Sum of DNR_No",Pivot!$A$8) -> #REF! | G29: =F29/$F$31 -> #REF! | I29: Other Payer | J29: =GETPIVOTDATA("Sum of Payer_Other_Payer",Pivot!$A$8) -> #REF! | K29: =J29/$J$31 -> #REF!
E30: Invalid | F30: =GETPIVOTDATA("Sum of DNR_Unknown",Pivot!$A$8) -> #REF! | G30: =F30/$F$31 -> #REF! | I30: Unknown/Blank/Invalid | J30: =GETPIVOTDATA("Sum of Payer_Unknown",Pivot!$A$8) -> #REF! | K30: =J30/$J$31 -> #REF!
F31: =SUM(F28:F30) -> #REF! | G31: =SUM(G28:G30) -> #REF! | J31: =SUM(J21:J30) -> #REF! | K31: =SUM(K21:K30) -> #REF!
A35: AGE GROUPS (at discharge) | B35: # | C35: % | E35: RACE | F35: # | G35: % | I35: PATIENT ZIP CODE GROUP | J35: # | K35: %
A36: 0 - 9 | B36: =GETPIVOTDATA("Sum of Age_0_09",Pivot!$A$9) -> 527704 | C36: =B36/$B$46 -> #REF! | E36: American Indian/Alaska Native | F36: =GETPIVOTDATA("Sum of racegrp_aman",Pivot!$A$9) -> 14414 | G36: =F36/$F$44 -> 0.0040000877 | I36: California Resident | J36: =GETPIVOTDATA("Sum of Zip_CA_Resident",Pivot!$A$9) -> 3442534 | K36: =J36/J$41 -> 0.9553516
A37: 10 - 19 | B37: =GETPIVOTDATA("Sum of Age_10_19",Pivot!$A$8) -> #REF! | C37: =B37/$B$46 -> #REF! | E37: Asian | F37: =GETPIVOTDATA("Sum of RaceGrp_Asian",Pivot!$A$9) -> 335529 | G37: =F37/$F$44 -> 0.093114016 | I37: Homeless* | J37: =GETPIVOTDATA("Sum of Zip_Homeless",Pivot!$A$9) -> 116580 | K37: =J37/J$41 -> 0.032352589
A38: 20 - 29 | B38: =GETPIVOTDATA("Sum of Age_20_29",Pivot!$A$8) -> #REF! | C38: =B38/$B$46 -> #REF! | E38: Black or African American | F38: =GETPIVOTDATA("Sum of RaceGrp_Black",Pivot!$A$9) -> 304186 | G38: =F38/$F$44 -> 0.084415893 | I38: Out of State | J38: =GETPIVOTDATA("Sum of Zip_Out_of_State",Pivot!$A$9) -> 33829 | K38: =J38/J$41 -> 0.0093880232
A39: 30 - 39 | B39: =GETPIVOTDATA("Sum of Age_30_39",Pivot!$A$8) -> #REF! | C39: =B39/$B$46 -> #REF! | E39: Multiracial | F39: =GETPIVOTDATA("Sum of racegrp_multirace",Pivot!$A$9) -> 66333 | G39: =F39/$F$44 -> 0.01840834 | I39: Does Not Reside in US | J39: =GETPIVOTDATA("Sum of Zip_Foreign",Pivot!$A$9) -> 4595 | K39: =J39/J$41 -> 0.0012751771
A40: 40 - 49 | B40: =GETPIVOTDATA("Sum of Age_40_49",Pivot!$A$8) -> #REF! | C40: =B40/$B$46 -> #REF! | E40: Native Hawaiian or Other Pacific Islander | F40: =GETPIVOTDATA("Sum of racegrp_nhpi",Pivot!$A$9) -> 22343 | G40: =F40/$F$44 -> 0.0062004967 | I40: Unknown/Blank/Invalid | J40: =GETPIVOTDATA("Sum of Zip_Unk_Inv_Bl",Pivot!$A$9) -> 5883 | K40: =J40/J$41 -> 0.0016326152
A41: 50 - 59 | B41: =GETPIVOTDATA("Sum of Age_50_59",Pivot!$A$8) -> #REF! | C41: =B41/$B$46 -> #REF! | E41: White | F41: =GETPIVOTDATA("Sum of RaceGrp_White",Pivot!$A$9) -> 1996646 | G41: =F41/$F$44 -> 0.55409734 | J41: =SUM(J36:J40) -> 3603421 | K41: =SUM(K36:K40) -> 1
A42: 60 - 69 | B42: =GETPIVOTDATA("Sum of Age_60_69",Pivot!$A$8) -> #REF! | C42: =B42/$B$46 -> #REF! | E42: Other Race | F42: =GETPIVOTDATA("Sum of RaceGrp_Other",Pivot!$A$9) -> 788243 | G42: =F42/$F$44 -> 0.21874852
A43: 70 - 79 | B43: =GETPIVOTDATA("Sum of Age_70_79",Pivot!$A$8) -> #REF! | C43: =B43/$B$46 -> #REF! | E43: Unknown/Blank/Invalid/Masked | F43: =GETPIVOTDATA("Sum of racegrp_unknown",Pivot!$A$9) -> 75727 | G43: =F43/$F$44 -> 0.021015307 | I43: * For definition, please see 'Instructions & Footnotes' tab
A44: 80+ | B44: =GETPIVOTDATA("Sum of Age_80_",Pivot!$A$8) -> #REF! | C44: =B44/$B$46 -> #REF! | F44: =SUM(F36:F43) -> 3603421 | G44: =SUM(G36:G43) -> 1
A45: Unknown/Blank/Invalid/Masked | B45: =GETPIVOTDATA("Sum of Age_Other_Unknown",Pivot!$A$9) -> 1225 | C45: =B45/$B$46 -> #REF!
B46: =SUM(B36:B45) -> #REF! | C46: =SUM(C36:C45) -> #REF!
E47: ETHNICITY | F47: # | G47: % | I47: SEX | J47: # | K47: %
E48: Hispanic or Latino | F48: =GETPIVOTDATA("Sum of eth_Hispanic",Pivot!$A$9) -> 1238948 | G48: =F48/$J$51 -> #REF! | I48: Female | J48: =GETPIVOTDATA("Sum of Sex_Female",Pivot!$A$8) -> #REF! | K48: =J48/$J$51 -> #REF!
E49: Non-Hispanic or Latino | F49: =GETPIVOTDATA("Sum of eth_NonHispanic",Pivot!$A$9) -> 2288091 | G49: =F49/$J$51 -> #REF! | I49: Male | J49: =GETPIVOTDATA("Sum of Sex_Male",Pivot!$A$8) -> #REF! | K49: =J49/$J$51 -> #REF!
E50: Unknown/Blank/Invalid/Masked | F50: =GETPIVOTDATA("Sum of eth_Other_Unknown",Pivot!$A$9) -> 76382 | G50: =F50/$J$51 -> #REF! | I50: Unknown/Blank/Invalid | J50: =GETPIVOTDATA("Sum of Sex_Other_Unknown",Pivot!$A$9) -> 472 | K50: =J50/$J$51 -> #REF!
F51: =SUM(F48:F50) -> 3603421 | G51: =SUM(G48:G50) -> #REF! | J51: =SUM(J48:J50) -> #REF! | K51: =SUM(K48:K50) -> #REF!
A54: ADMISSION SOURCE - POINT OF ORIGIN | B54: # | C54: % | E54: ADMISSION SOURCE - ROUTE | F54: # | G54: % | I54: DISPOSITION | J54: # | K54: %
A55: Non-Health Care Facility | B55: =GETPIVOTDATA("Sum of Admt_Non_HCF",Pivot!$A$9) -> 2566436 | C55: =B55/$B$67 -> 0.71222208 | E55: Your Emergency Department | F55: =GETPIVOTDATA("Sum of Route_Your_ER",Pivot!$A$8) -> #REF! | G55: =F55/$F$59 -> #REF! | I55: Routine (home) | J55: =GETPIVOTDATA("Sum of Disp_Routine",Pivot!$A$8) -> #REF! | K55: =J55/$J$72 -> #REF!
A56: Clinic or Physician's Office | B56: =GETPIVOTDATA("Sum of Admt_Clinic_Dr",Pivot!$A$9) -> 158427 | C56: =B56/$B$67 -> 0.04396572 | E56: Another Emergency Department | F56: =GETPIVOTDATA("Sum of Route_Another_ER",Pivot!$A$9) -> 163407 | G56: =F56/$F$59 -> #REF! | I56: Home Health Service | J56: =GETPIVOTDATA("Sum of Disp_Home_Health_Service",Pivot!$A$8) -> #REF! | K56: =J56/$J$72 -> #REF!
A57: Hospital (different facility) | B57: =GETPIVOTDATA("Sum of Admt_Hosp_Dif",Pivot!$A$9) -> 315895 | C57: =B57/$B$67 -> 0.087665305 | E57: Not Admitted from Emergency Department | F57: =GETPIVOTDATA("Sum of Route_No_ER",Pivot!$A$9) -> 1423846 | G57: =F57/$F$59 -> #REF! | I57: Acute Care | J57: =GETPIVOTDATA("Sum of Disp_Acute_Care",Pivot!$A$8) -> #REF! | K57: =J57/$J$72 -> #REF!
A58: Skilled Nursing/Intermediate Care/Assisted Living Facility | B58: =GETPIVOTDATA("Sum of Admt_SNF_ICF_ALF",Pivot!$A$9) -> 69430 | C58: =B58/$B$67 -> 0.019267801 | E58: Information Not Available/Unknown | F58: =GETPIVOTDATA("Sum of Route_NA",Pivot!$A$9) -> 1145 | G58: =F58/$F$59 -> #REF! | I58: Skilled Nursing | J58: =GETPIVOTDATA("Sum of Disp_SN_IC_Care",Pivot!$A$8) -> #REF! | K58: =J58/$J$72 -> #REF!
A59: Another Health Care Facility | B59: =GETPIVOTDATA("Sum of Admt_Another_HCF",Pivot!$A$9) -> 24078 | C59: =B59/$B$67 -> 0.0066819836 | F59: =SUM(F55:F58) -> #REF! | G59: =F59/$F$59 -> #REF! | I59: Residential Care Facility | J59: =GETPIVOTDATA("Sum of Disp_Residential_Care",Pivot!$A$8) -> #REF! | K59: =J59/$J$72 -> #REF!
A60: Court/Law Enforcement | B60: =GETPIVOTDATA("Sum of Admt_Court_LE",Pivot!$A$9) -> 13183 | C60: =B60/$B$67 -> 0.0036584679 | I60: Court/Law Enforcement | J60: =GETPIVOTDATA("Sum of Disp_Prison_Jail",Pivot!$A$8) -> #REF! | K60: =J60/$J$72 -> #REF!
A61: One Distinct Unit to Another Distinct Unit, Same Hospital | B61: =GETPIVOTDATA("Sum of Admt_DistinctPartXfer",Pivot!$A$9) -> 36380 | C61: =B61/$B$67 -> 0.010095962 | E61: ADMISSION TYPE | F61: # | G61: % | I61: Against Medical Advice | J61: =GETPIVOTDATA("Sum of Disp_Against_Medical_Advice",Pivot!$A$8) -> #REF! | K61: =J61/$J$72 -> #REF!
A62: Ambulatory Surgery Center | B62: =GETPIVOTDATA("Sum of Admt_Amb_Surgery",Pivot!$A$9) -> 2653 | C62: =B62/$B$67 -> 0.00073624481 | E62: Emergency | F62: =GETPIVOTDATA("Sum of Adm_Emergency",Pivot!$A$9) -> 1439899 | G62: =F62/$F$68 -> 0.39959222 | I62: Children's or Cancer Center | J62: =GETPIVOTDATA("Sum of disp_Childrens_or_cancer",Pivot!$A$8) -> #REF! | K62: =J62/$J$72 -> #REF!
A63: Hospice Facility | B63: =GETPIVOTDATA("Sum of Admt_HospiceFacility",Pivot!$A$9) -> 402 | C63: =B63/$B$67 -> 0.00011156065 | E63: Urgent | F63: =GETPIVOTDATA("Sum of Adm_Urgent",Pivot!$A$9) -> 1128054 | G63: =F63/$F$68 -> 0.31305085 | I63: Hospice Care | J63: =GETPIVOTDATA("Sum of disp_hospice_care",Pivot!$A$8) -> #REF! | K63: =J63/$J$72 -> #REF!
A64: Disaster Care Site | B64: =GETPIVOTDATA("Sum of Admt_Disaster_Care_Site",Pivot!$A$9) -> 44 | C64: =B64/$B$67 -> 1.2210619e-05 | E64: Elective | F64: =GETPIVOTDATA("Sum of Adm_Elective",Pivot!$A$9) -> 560584 | G64: =F64/$F$68 -> 0.15556994 | I64: Psychiatric Care | J64: =GETPIVOTDATA("Sum of disp_psychiatric_care",Pivot!$A$8) -> #REF! | K64: =J64/$J$72 -> #REF!
A65: Newborn Admit Type* | B65: =GETPIVOTDATA("Sum of Admt_Newborn",Pivot!$A$9) -> 411598 | C65: =B65/$B$67 -> 0.11422423 | E65: Newborn | F65: =GETPIVOTDATA("Sum of Adm_Newborn",Pivot!$A$9) -> 411598 | G65: =F65/$F$68 -> 0.11422423 | I65: Critical Access Hospital | J65: =GETPIVOTDATA("Sum of disp_cah",Pivot!$A$8) -> #REF! | K65: =J65/$J$72 -> #REF!
A66: Information Not Available/Unknown/Masked | B66: =GETPIVOTDATA("Sum of Admt_NA",Pivot!$A$9) -> 4895 | C66: =B66/$B$67 -> 0.0013584313 | E66: Trauma | F66: =GETPIVOTDATA("Sum of Adm_Trauma",Pivot!$A$9) -> 61941 | G66: =F66/$F$68 -> 0.017189499 | I66: Died | J66: =GETPIVOTDATA("Sum of Disp_Died",Pivot!$A$8) -> #REF! | K66: =J66/$J$72 -> #REF!
B67: =SUM(B55:B66) -> 3603421 | C67: =SUM(C55:C66) -> 1 | E67: Information Not Available/Unknown/Masked | F67: =GETPIVOTDATA("Sum of Adm_NA",Pivot!$A$9) -> 1345 | G67: =F67/$F$68 -> 0.00037325641 | I67: Inpatient Rehabilitation | J67: =GETPIVOTDATA("Sum of Disp_Rehab",Pivot!$A$8) -> #REF! | K67: =J67/$J$72 -> #REF!
F68: =SUM(F62:F67) -> 3603421 | G68: =SUM(G62:G67) -> 1 | I68: Other | J68: =GETPIVOTDATA("Sum of disp_Other",Pivot!$A$9) -> 940 | K68: =J68/$J$72 -> #REF!
I69: Disaster Care Site | J69: =GETPIVOTDATA("Sum of Disp_Disaster_Care_Site",Pivot!$A$8) -> #REF! | K69: =J69/$J$72 -> #REF!
I70: Not Defined Elsewhere | J70: =GETPIVOTDATA("Sum of disp_not_defined_elsewhere",Pivot!$A$8) -> #REF! | K70: =J70/$J$72 -> #REF!
A71: * Please see note on 'Instructions & Footnotes' tab | I71: Blank/Invalid | J71: =GETPIVOTDATA("Sum of disp_Invalid_Blank",Pivot!$A$9) -> 210 | K71: =J71/$J$72 -> #REF!
J72: =SUM(J55:J71) -> #REF! | K72: =SUM(K55:K70) -> #REF!
A74: PRINCIPAL DIAGNOSIS GROUP | B74: # | C74: % | I74: PRINCIPAL PROCEDURE GROUP | J74: # | K74: %
A75: Certain conditions originating in the perinatal period | B75: =GETPIVOTDATA("Sum of dx_Certain_Perinatal_Conditions",Pivot!$A$9) -> 429242 | C75: =B75/B$96 -> 0.11912069 | I75: Miscellaneous diagnostic and therapeutic procedures | J75: =GETPIVOTDATA("Sum of PR_Diagnostic_Therapeutic",Pivot!$A$9) -> 626698 | K75: =J75/J$92 -> 0.17391751
A76: Complications of pregnancy; childbirth; and the puerperium | B76: =GETPIVOTDATA("Sum of dx_Pregnancy_Childbirth",Pivot!$A$9) -> 446985 | C76: =B76/B$96 -> 0.12404462 | I76: Obstetrical procedures | J76: =GETPIVOTDATA("Sum of PR_Obstetrical",Pivot!$A$9) -> 408052 | K76: =J76/J$92 -> 0.11324017
A77: Congenital anomalies | B77: =GETPIVOTDATA("Sum of DX_Congenital",Pivot!$A$9) -> 12160 | C77: =B77/B$96 -> 0.003374571 | I77: Operations on the cardiovascular system | J77: =GETPIVOTDATA("Sum of PR_Cardiovascular_System",Pivot!$A$9) -> 291709 | K77: =J77/J$92 -> 0.08095335
A78: Diseases of the blood and blood-forming organs | B78: =GETPIVOTDATA("Sum of dx_Diseases_of_the_Blood",Pivot!$A$9) -> 28568 | C78: =B78/B$96 -> 0.0079280217 | I78: Operations on the digestive system | J78: =GETPIVOTDATA("Sum of PR_Digestive_System",Pivot!$A$9) -> 316157 | K78: =J78/J$92 -> 0.087738013
A79: Diseases of the circulatory system | B79: =GETPIVOTDATA("Sum of DX_Circulatory",Pivot!$A$9) -> 445811 | C79: =B79/B$96 -> 0.12371882 | I79: Operations on the ear | J79: =GETPIVOTDATA("Sum of PR_Ear",Pivot!$A$9) -> 2436 | K79: =J79/J$92 -> 0.00067602426
A80: Diseases of the digestive system | B80: =GETPIVOTDATA("Sum of DX_Digestive",Pivot!$A$9) -> 326053 | C80: =B80/B$96 -> 0.090484293 | I80: Operations on the endocrine system | J80: =GETPIVOTDATA("Sum of PR_Endocrine_System",Pivot!$A$9) -> 4485 | K80: =J80/J$92 -> 0.0012446506
A81: Diseases of the Ear and Mastoid Process | B81: =GETPIVOTDATA("Sum of dx_Ear",Pivot!$A$9) -> 3822 | C81: =B81/B$96 -> 0.0010606587 | I81: Operations on the eye | J81: =GETPIVOTDATA("Sum of PR_Eye",Pivot!$A$9) -> 1814 | K81: =J81/J$92 -> 0.00050341051
A82: Diseases of the Eye and Adnexa | B82: =GETPIVOTDATA("Sum of dx_Eye",Pivot!$A$9) -> 3940 | C82: =B82/B$96 -> 0.0010934054 | I82: Operations on the genital organs | J82: =GETPIVOTDATA("Sum of PR_Reproductive_System",Pivot!$A$9) -> 70272 | K82: =J82/J$92 -> 0.019501468
A83: Diseases of the genitourinary system | B83: =GETPIVOTDATA("Sum of DX_Genitourinary",Pivot!$A$9) -> 143043 | C83: =B83/B$96 -> 0.039696444 | I83: Operations on the hemic and lymphatic system | J83: =GETPIVOTDATA("Sum of PR_Hemic_Lymph_System",Pivot!$A$9) -> 13871 | K83: =J83/J$92 -> 0.0038493976
A84: Diseases of the musculoskeletal system and connective tissue | B84: =GETPIVOTDATA("Sum of dx_Musculoskeletal",Pivot!$A$9) -> 126705 | C84: =B84/B$96 -> 0.035162419 | I84: Operations on the integumentary system | J84: =GETPIVOTDATA("Sum of PR_Integumentary_System",Pivot!$A$9) -> 69245 | K84: =J84/J$92 -> 0.019216461
A85: Diseases of the nervous system and sense organs | B85: =GETPIVOTDATA("Sum of dx_Nervous_System",Pivot!$A$9) -> 97546 | C85: =B85/B$96 -> 0.027070387 | I85: Operations on the musculoskeletal system | J85: =GETPIVOTDATA("Sum of PR_Musculoskeletal_System",Pivot!$A$9) -> 217292 | K85: =J85/J$92 -> 0.060301586
A86: Diseases of the respiratory system | B86: =GETPIVOTDATA("Sum of DX_Respiratory",Pivot!$A$9) -> 181164 | C86: =B86/B$96 -> 0.050275558 | I86: Operations on the nervous system | J86: =GETPIVOTDATA("Sum of PR_Nervous_System",Pivot!$A$9) -> 55790 | K86: =J86/J$92 -> 0.01548251
A87: Diseases of the skin and subcutaneous tissue | B87: =GETPIVOTDATA("Sum of DX_Skin",Pivot!$A$9) -> 47959 | C87: =B87/B$96 -> 0.013309297 | I87: Operations on the nose; mouth; and pharynx | J87: =GETPIVOTDATA("Sum of PR_Nose_Mouth_Pharynx",Pivot!$A$9) -> 13290 | K87: =J87/J$92 -> 0.0036881619
A88: Endocrine; nutritional; and metabolic diseases and immunity disorders | B88: =GETPIVOTDATA("Sum of DX_Endocrine",Pivot!$A$9) -> 146130 | C88: =B88/B$96 -> 0.04055313 | I88: Operations on the respiratory system | J88: =GETPIVOTDATA("Sum of PR_Respiratory_System",Pivot!$A$9) -> 67298 | K88: =J88/J$92 -> 0.018676141
A89: Factors influencing health status | B89: =GETPIVOTDATA("Sum of dx_Factors_Influencing_Health",Pivot!$A$9) -> 40643 | C89: =B89/B$96 -> 0.011279004 | I89: Operations on the urinary system | J89: =GETPIVOTDATA("Sum of PR_Urinary_System",Pivot!$A$9) -> 52302 | K89: =J89/J$92 -> 0.01451454
A90: Infectious and parasitic diseases | B90: =GETPIVOTDATA("Sum of dx_Infectious",Pivot!$A$9) -> 392664 | C90: =B90/B$96 -> 0.10896978 | I90: No procedure group assigned | J90: =GETPIVOTDATA("Sum of PR_No_Group_Assigned",Pivot!$A$9) -> 68739 | K90: =J90/J$92 -> 0.019076039
A91: Injury and poisoning | B91: =GETPIVOTDATA("Sum of DX_Injury_Poisoning",Pivot!$A$9) -> 291701 | C91: =B91/B$96 -> 0.080951129 | I91: No Principal Procedure Reported | J91: =GETPIVOTDATA("Sum of PR_None",Pivot!$A$9) -> 1323971 | K91: =J91/J$92 -> 0.36742057
A92: Mental Illness | B92: =GETPIVOTDATA("Sum of dx_MentalHealth",Pivot!$A$9) -> 253338 | C92: =B92/B$96 -> 0.070304858 | J92: =SUM(J75:J91) -> 3603421 | K92: =SUM(K75:K91) -> 1
A93: Neoplasms | B93: =GETPIVOTDATA("Sum of DX_Neoplasms",Pivot!$A$9) -> 128086 | C93: =B93/B$96 -> 0.035545666
A94: Symptoms; signs; and ill-defined conditions and factors influencing health status | B94: =GETPIVOTDATA("Sum of dx_Symptoms_Signs_NEC",Pivot!$A$9) -> 57219 | C94: =B94/B$96 -> 0.015879077
A95: Unknown/Blank/Invalid/Masked | B95: =GETPIVOTDATA("Sum of dx_Other_Unknown",Pivot!$A$9) -> 642 | C95: =B95/B$96 -> 0.00017816403
B96: =SUM(B75:B95) -> 3603421 | C96: =SUM(C75:C95) -> 1

Sheet Pivot
D3: Make your selection here
D146: This Excel pivot table uses the California Patient Discharge Database for January 1, 2022 to December 31, 2022. It is a fast and simple way to aggregate and display data.
D149: Select your variables above using the pulldown arrows. You can choose a specific hospital or county, or create a custom aggregation. To get Statewide totals, select "All" for all fields. When done, click on the "PROFILE" worksheet to see your results.
D153: Note: Avoid changing the worksheets as they contain many links, formulas and custom formats.
D156: **No adjustments have been made to the data for any hospitals with reporting modifications, non-compliances, data anomalies, or shortened report periods due to facility openings, closures, or consolidations. The data is aggregated at the facility level. Therefore, it does not contain individually identifiable health information.

Sheet Data
A1: oshpd_id9 | B1: OSHPD_ID | C1: COUNTY | D1: FACILITY_NAME | E1: ADDRESS | F1: CITY | G1: DBA_ZIP_CODE | H1: CONTROL_TYPE_DESC | I1: teach_rural | J1: licensed_bed_size | K1: senate_district_desc | L1: assembly_district_desc | M1: mssa_name | N1: mssa_designation | O1: TOC_Acute | P1: TOC_SN_IC | Q1: TOC_Psych | R1: TOC_Chem_Dep | S1: TOC_Rehab | T1: TOC_Unknown | U1: Sex_Male | V1: Sex_Female | W1: Sex_Other_Unknown | X1: Age_0_09 | Y1: Age_10_19 | Z1: Age_20_29 | AA1: Age_30_39 | AB1: Age_40_49 | AC1: Age_50_59 | AD1: Age_60_69 | AE1: Age_70_79 | AF1: Age_80_ | AG1: Age_Other_Unknown | AH1: eth_Hispanic | AI1: eth_NonHispanic | AJ1: eth_Other_Unknown | AK1: racegrp_aman | AL1: racegrp_asian | AM1: racegrp_nhpi | AN1: racegrp_black | AO1: racegrp_white | AP1: racegrp_unknown | AQ1: racegrp_other | AR1: racegrp_multirace | AS1: Admt_Non_HCF | AT1: Admt_Clinic_Dr | AU1: Admt_Hosp_Dif | AV1: Admt_SNF_ICF_ALF | AW1: Admt_Another_HCF | AX1: Admt_DistinctPartXfer | AY1: Admt_Amb_Surgery | AZ1: Admt_HospiceFacility | BA1: Admt_Court_LE | BB1: Admt_NA | BC1: Admt_Newborn | BD1: admt_disaster_care_site | BE1: Route_Your_ER | BF1: Route_Another_ER | BG1: Route_No_ER | BH1: Route_NA | BI1: dsch_days | BJ1: Adm_Emergency | BK1: Adm_Urgent | BL1: Adm_Elective | BM1: Adm_Newborn | BN1: Adm_Trauma | BO1: Adm_NA | BP1: disp_Routine | BQ1: disp_Acute_Care | BR1: disp_Rehab | BS1: disp_SN_IC_Care | BT1: disp_Residential_Care | BU1: disp_Prison_Jail | BV1: disp_Against_Medical_Advice | BW1: disp_Died | BX1: disp_Home_Health_Service | BY1: disp_Disaster_Care_Site | BZ1: disp_Childrens_or_Cancer | CA1: disp_Hospice_Care | CB1: disp_Psychiatric_Care | CC1: disp_CAH | CD1: disp_Not_Defined_Elsewhere | CE1: disp_Other | CF1: disp_Invalid_Blank | CG1: DNR_Yes | CH1: DNR_No | CI1: DNR_Unknown | CJ1: Payer_Medicare | CK1: Payer_Medi_Cal | CL1: Payer_Priv_Coverage | CM1: Payer_Workers_Comp | CN1: Payer_County_Indigent_Prog | CO1: Payer_Other_Government | CP1: Payer_Other_Indigent | CQ1: Payer_Self_Pay | CR1: Payer_Other_Payer | CS1: Payer_Unknown | CT1: dx_Infectious | CU1: dx_Neoplasms | CV1: dx_Diseases_of_the_Blood | CW1: dx_Endocrine | CX1: dx_MentalHealth | CY1: dx_Nervous_System | CZ1: dx_Eye | DA1: dx_Ear | DB1: dx_Circulatory | DC1: dx_Respiratory | DD1: dx_Digestive | DE1: dx_Skin | DF1: dx_Musculoskeletal | DG1: dx_Genitourinary | DH1: dx_Pregnancy_Childbirth | DI1: dx_Certain_Perinatal_Conditions | DJ1: dx_Congenital | DK1: dx_Symptoms_Signs_NEC | DL1: dx_Injury_Poisoning | DM1: dx_Factors_Influencing_Health | DN1: dx_Other_Unknown | DO1: PR_Diagnostic_Therapeutic | DP1: PR_Obstetrical | DQ1: PR_Cardiovascular_System | DR1: PR_Digestive_System | DS1: PR_Ear | DT1: PR_Endocrine_System | DU1: PR_Eye | DV1: PR_Reproductive_System | DW1: PR_Hemic_Lymph_System | DX1: PR_Integumentary_System | DY1: PR_Musculoskeletal_System | DZ1: PR_Nervous_System | EA1: PR_Nose_Mouth_Pharynx | EB1: PR_Respiratory_System | EC1: PR_Urinary_System | ED1: PR_None | EE1: PR_No_Group_Assigned | EF1: Zip_Unk_Inv_Bl | EG1: Zip_Homeless | EH1: Zip_Foreign | EI1: Zip_Out_of_State | EJ1: Zip_CA_Resident
A2: 106010735 | B2: 010735 | C2: ALAMEDA | D2: ALAMEDA HOSPITAL | E2: 2070 CLINTON AVE | F2: ALAMEDA | G2: 94501 | H2: City or County | I2: NA | J2: 100-149 | K2: District 9 | L2: District 18 | M2: Alameda/Jack London Square/Oakland Inner Harbor | N2: Urban | O2: 2646 | P2: 130 | S2: 1 | T2: 1 | U2: 1409 | V2: 1368 | W2: 1 | Z2: 104 | AA2: 187 | AB2: 296 | AC2: 408 | AD2: 590 | AE2: 570 | AF2: 619 | AG2: 4 | AH2: 487 | AI2: 2230 | AJ2: 61 | AL2: 480 | AM2: 19 | AN2: 727 | AO2: 943 | AP2: 30 | AQ2: 513 | AR2: 66 | AS2: 1823 | AT2: 5 | AU2: 461 | AV2: 380 | AW2: 12 | AX2: 94 | BB2: 3 | BE2: 2116 | BF2: 327 | BG2: 335 | BI2: 85839 | BJ2: 2119 | BK2: 379 | BL2: 279 | BO2: 1 | BP2: 1166 | BQ2: 204 | BR2: 60 | BS2: 574 | BV2: 119 | BW2: 102 | BX2: 500 | CA2: 46 | CB2: 6 | CD2: 1 | CG2: 109 | CH2: 2669 | CJ2: 1478 | CK2: 973 | CL2: 204 | CM2: 1 | CN2: 48 | CO2: 19 | CQ2: 55 | CT2: 460 | CU2: 49 | CV2: 52 | CW2: 138 | CX2: 79 | CY2: 181 | CZ2: 4 | DA2: 6 | DB2: 470 | DC2: 272 | DD2: 343 | DE2: 73 | DF2: 135 | DG2: 151 | DK2: 128 | DL2: 217 | DM2: 17 | DN2: 3 | DO2: 321 | DQ2: 221 | DR2: 168 | DU2: 1 | DV2: 19 | DX2: 39 | DY2: 123 | DZ2: 28 | EA2: 3 | EB2: 78 | EC2: 11 | ED2: 1743 | EE2: 23 | EF2: 1 | EG2: 141 | EI2: 27 | EJ2: 2609
A3: 106010739 | B3: 010739 | C3: ALAMEDA | D3: ALTA BATES SUMMIT MEDICAL CENTER-ALTA BATES CAMPUS | E3: 2450 ASHBY AVE | F3: BERKELEY | G3: 94705 | H3: Non-profit Corporation (incl. Church-related) | I3: NA | J3: 300-499 | K3: District 9 | L3: District 15 | M3: Albany/Berkeley East and North/Claremont/Cragmont/Forest Park/Rockridge/Temescal/Thousand Oaks | N3: Urban | O3: 15007 | U3: 5171 | V3: 9836 | X3: 4314 | Y3: 188 | Z3: 1720 | AA3: 3212 | AB3: 931 | AC3: 788 | AD3: 1104 | AE3: 1436 | AF3: 1314 | AH3: 4211 | AI3: 10314 | AJ3: 482 | AK3: 44 | AL3: 1873 | AM3: 389 | AN3: 3099 | AO3: 5072 | AP3: 320 | AQ3: 3941 | AR3: 269 | AS3: 9681 | AT3: 107 | AU3: 829 | AV3: 150 | AW3: 20 | AX3: 3 | AY3: 3 | AZ3: 1 | BB3: 1 | BC3: 4212 | BE3: 4758 | BF3: 547 | BG3: 9702 | BI3: 60441 | BJ3: 3534 | BK3: 4666 | BL3: 2595 | BM3: 4212 | BP3: 11358 | BQ3: 274 | BR3: 118 | BS3: 922 | BT3: 40 | BU3: 2 | BV3: 260 | BW3: 189 | BX3: 1590 | BZ3: 22 | CA3: 122 | CB3: 101 | CD3: 9 | CG3: 645 | CH3: 14362 | CJ3: 3074 | CK3: 6095 | CL3: 5174 | CM3: 12 | CO3: 396 | CQ3: 247 | CR3: 9 | CT3: 1322 | CU3: 241 | CV3: 139 | CW3: 269 | CX3: 128 | CY3: 222 | CZ3: 11 | DA3: 15 | DB3: 773 | DC3: 277 | DD3: 801 | DE3: 161 | DF3: 562 | DG3: 317 | DH3: 4719 | DI3: 4309 | DJ3: 6 | DK3: 136 | DL3: 584 | DM3: 15 | DO3: 1265 | DP3: 4209 | DQ3: 401 | DR3: 698 | DS3: 3 | DT3: 5 | DU3: 4 | DV3: 227 | DW3: 17 | DX3: 189 | DY3: 663 | DZ3: 247 | EA3: 33 | EB3: 167 | EC3: 122 | ED3: 6484 | EE3: 273 | EF3: 32 | EG3: 381 | EH3: 6 | EI3: 69 | EJ3: 14519
A4: 106010776 | B4: 010776 | C4: ALAMEDA | D4: UCSF BENIOFF CHILDREN'S HOSPITAL OAKLAND | E4: 747 52ND ST | F4: OAKLAND | G4: 94609 | H4: Non-profit Corporation (incl. Church-related) | I4: Teaching | J4: 150-199 | K4: District 9 | L4: District 15 | M4: Oakland West Central | N4: Urban | O4: 7240 | S4: 92 | U4: 3962 | V4: 3369 | W4: 1 | X4: 4770 | Y4: 2379 | Z4: 179 | AG4: 4 | AH4: 3194 | AI4: 4075 | AJ4: 63 | AK4: 29 | AL4: 604 | AM4: 96 | AN4: 1053 | AO4: 1437 | AP4: 66 | AQ4: 3617 | AR4: 430 | AS4: 4553 | AT4: 869 | AU4: 1766 | AW4: 84 | AX4: 58 | AY4: 1 | BB4: 1 | BE4: 5028 | BF4: 123 | BG4: 2181 | BI4: 41285 | BJ4: 3862 | BK4: 1711 | BL4: 1536 | BN4: 218 | BO4: 5 | BP4: 7059 | BQ4: 79 | BR4: 72 | BS4: 1 | BT4: 2 | BU4: 1 | BV4: 15 | BW4: 47 | BX4: 6 | BZ4: 5 | CA4: 5 | CB4: 40 | CG4: 24 | CH4: 7308 | CJ4: 18 | CK4: 3274 | CL4: 1919 | CO4: 2030 | CQ4: 82 | CR4: 9 | CT4: 630 | CU4: 202 | CV4: 253 | CW4: 326 | CX4: 79 | CY4: 568 | CZ4: 24 | DA4: 23 | DB4: 65 | DC4: 1353 | DD4: 757 | DE4: 149 | DF4: 294 | DG4: 209 | DI4: 410 | DJ4: 405 | DK4: 243 | DL4: 924 | DM4: 416 | DN4: 2 | DO4: 1311 | DQ4: 209 | DR4: 693 | DS4: 30 | DT4: 14 | DU4: 16 | DV4: 62 | DW4: 60 | DX4: 154 | DY4: 518 | DZ4: 338 | EA4: 199 | EB4: 94 | EC4: 31 | ED4: 3415 | EE4: 188 | EG4: 22 | EH4: 1 | EI4: 72 | EJ4: 7237
A5: 106010844 | B5: 010844 | C5: ALAMEDA | D5: ALTA BATES SUMMIT MEDICAL CENTER-HERRICK CAMPUS | E5: 2001 DWIGHT WAY | F5: BERKELEY | G5: 94704 | H5: Non-profit Corporation (incl. Church-related) | I5: Teaching | J5: 50-99 | K5: District 9 | L5: District 15 | M5: Berkeley South and West/Emeryville/Oakland Northwest | N5: Urban | Q5: 1609 | U5: 629 | V5: 980 | Y5: 532 | Z5: 324 | AA5: 241 | AB5: 159 | AC5: 120 | AD5: 140 | AE5: 60 | AF5: 33 | AH5: 194 | AI5: 1350 | AJ5: 65 | AK5: 11 | AL5: 153 | AM5: 21 | AN5: 323 | AO5: 800 | AP5: 43 | AQ5: 193 | AR5: 65 | AS5: 429 | AT5: 9 | AU5: 1076 | AV5: 3 | AW5: 12 | AX5: 80 | BF5: 953 | BG5: 656 | BI5: 16229 | BJ5: 6 | BK5: 1593 | BL5: 10 | BP5: 1384 | BQ5: 38 | BR5: 5 | BS5: 25 | BT5: 100 | BU5: 6 | BV5: 29 | BX5: 1 | BZ5: 1 | CB5: 8 | CD5: 12 | CG5: 1 | CH5: 1608 | CJ5: 312 | CK5: 637 | CL5: 600 | CM5: 2 | CO5: 23 | CQ5: 34 | CR5: 1 | CT5: 1 | CX5: 1600 | DN5: 8 | DO5: 302 | DQ5: 1 | DR5: 2 | DX5: 2 | DY5: 1 | EA5: 1 | ED5: 1265 | EE5: 35 | EF5: 5 | EG5: 270 | EI5: 17 | EJ5: 1317
A6: 106010846 | B6: 010846 | C6: ALAMEDA | D6: HIGHLAND HOSPITAL | E6: 1411 E 31ST ST | F6: OAKLAND | G6: 94602 | H6: City or County | I6: Teaching | J6: 200-299 | K6: District 9 | L6: District 18 | M6: Oakland West Central | N6: Urban | O6: 14681 | P6: 87 | Q6: 2479 | S6: 566 | T6: 11 | U6: 9475 | V6: 8345 | W6: 4 | X6: 1439 | Y6: 302 | Z6: 2413 | AA6: 2851 | AB6: 2151 | AC6: 2719 | AD6: 3083 | AE6: 1758 | AF6: 1104 | AG6: 4 | AH6: 5291 | AI6: 12348 | AJ6: 185 | AK6: 61 | AL6: 1914 | AM6: 186 | AN6: 6297 | AO6: 3048 | AP6: 120 | AQ6: 5733 | AR6: 465 | AS6: 12615 | AT6: 637 | AU6: 1380 | AV6: 358 | AW6: 198 | AX6: 906 | AY6: 10 | BA6: 105 | BB6: 227 | BC6: 1388 | BE6: 10805 | BF6: 26 | BG6: 6979 | BH6: 14 | BI6: 133268 | BJ6: 8981 | BK6: 4053 | BL6: 1919 | BM6: 1388 | BN6: 1460 | BO6: 23 | BP6: 11568 | BQ6: 822 | BR6: 333 | BS6: 1586 | BU6: 325 | BV6: 725 | BW6: 399 | BX6: 1338 | BZ6: 28 | CA6: 121 | CB6: 221 | CD6: 358 | CG6: 668 | CH6: 17155 | CI6: 1 | CJ6: 4991 | CK6: 11147 | CL6: 895 | CM6: 58 | CN6: 238 | CO6: 152 | CQ6: 343 | CT6: 1502 | CU6: 552 | CV6: 115 | CW6: 770 | CX6: 2950 | CY6: 477 | CZ6: 32 | DA6: 14 | DB6: 1681 | DC6: 736 | DD6: 1393 | DE6: 291 | DF6: 374 | DG6: 592 | DH6: 1634 | DI6: 1438 | DJ6: 8 | DK6: 332 | DL6: 2680 | DM6: 249 | DN6: 4 | DO6: 2731 | DP6: 1476 | DQ6: 1211 | DR6: 1087 | DS6: 20 | DT6: 18 | DU6: 16 | DV6: 154 | DW6: 46 | DX6: 614 | DY6: 914 | DZ6: 400 | EA6: 85 | EB6: 291 | EC6: 209 | ED6: 8098 | EE6: 454 | EF6: 1 | EG6: 1937 | EH6: 3 | EI6: 95 | EJ6: 15788
A7: 106010887 | B7: 010887 | C7: ALAMEDA | D7: KINDRED HOSPITAL - SAN FRANCISCO BAY AREA | E7: 2800 BENEDICT DR | F7: SAN LEANDRO | G7: 94577 | H7: Investor - Limited Liability Company | I7: Teaching | J7: 50-99 | K7: District 9 | L7: District 18 | M7: Castro Valley Central and North/Oak Knoll/San Leandro Northeast/Sheffield Village/Union City East | N7: Urban | O7: 331 | U7: 209 | V7: 122 | AA7: 28 | AB7: 40 | AC7: 91 | AD7: 70 | AE7: 67 | AF7: 26 | AG7: 9 | AH7: 66 | AI7: 224 | AJ7: 41 | AL7: 53 | AN7: 63 | AO7: 99 | AP7: 7 | AQ7: 109 | AU7: 331 | BG7: 331 | BI7: 23259 | BL7: 331 | BP7: 10 | BQ7: 117 | BR7: 19 | BS7: 103 | BT7: 1 | BV7: 5 | BW7: 34 | BX7: 41 | CA7: 1 | CG7: 16 | CH7: 315 | CJ7: 77 | CK7: 163 | CL7: 83 | CM7: 2 | CO7: 6 | CT7: 11 | CU7: 1 | CW7: 2 | CY7: 1 | DB7: 5 | DC7: 230 | DD7: 10 | DE7: 15 | DF7: 13 | DG7: 10 | DL7: 22 | DM7: 11 | DO7: 145 | DQ7: 33 | DR7: 19 | DS7: 1 | DX7: 13 | DY7: 10 | EA7: 2 | EB7: 3 | EC7: 1 | ED7: 100 | EE7: 4 | EF7: 1 | EG7: 8 | EI7: 2 | EJ7: 320
A8: 106010937 | B8: 010937 | C8: ALAMEDA | D8: ALTA BATES SUMMIT MEDICAL CENTER | E8: 350 HAWTHORNE AVE | F8: OAKLAND | G8: 94609 | H8: Non-profit Corporation (incl. Church-related) | I8: Teaching | J8: 300-499 | K8: District 9 | L8: District 18 | M8: Dimond/Montclair/Oakland East/Oakmore/Piedmont/Piedmont Pines/Trestle Glen | N8: Urban | O8: 9656 | S8: 724 | U8: 5219 | V8: 5161 | Y8: 30 | Z8: 256 | AA8: 650 | AB8: 845 | AC8: 1437 | AD8: 2316 | AE8: 2470 | AF8: 2376 | AH8: 1129 | AI8: 9091 | AJ8: 160 | AK8: 23 | AL8: 1664 | AM8: 226 | AN8: 3786 | AO8: 3300 | AP8: 118 | AQ8: 1192 | AR8: 71 | AS8: 8563 | AT8: 129 | AU8: 1170 | AV8: 364 | AW8: 12 | AX8: 127 | AY8: 14 | AZ8: 1 | BE8: 7612 | BF8: 288 | BG8: 2480 | BI8: 63533 | BJ8: 5688 | BK8: 2611 | BL8: 2081 | BP8: 4267 | BQ8: 297 | BR8: 253 | BS8: 1517 | BT8: 73 | BU8: 1 | BV8: 266 | BW8: 382 | BX8: 3053 | BZ8: 1 | CA8: 261 | CB8: 8 | CD8: 1 | CG8: 1059 | CH8: 9321 | CJ8: 5512 | CK8: 2415 | CL8: 2131 | CM8: 24 | CO8: 141 | CQ8: 142 | CR8: 15 | CT8: 1825 | CU8: 617 | CV8: 213 | CW8: 688 | CX8: 116 | CY8: 376 | CZ8: 15 | DA8: 10 | DB8: 2828 | DC8: 492 | DD8: 989 | DE8: 89 | DF8: 372 | DG8: 513 | DH8: 14 | DJ8: 15 | DK8: 198 | DL8: 812 | DM8: 198 | DO8: 1555 | DQ8: 1740 | DR8: 1227 | DS8: 3 | DT8: 23 | DV8: 82 | DW8: 81 | DX8: 293 | DY8: 509 | DZ8: 98 | EA8: 22 | EB8: 332 | EC8: 134 | ED8: 4016 | EE8: 265 | EF8: 4 | EG8: 549 | EH8: 6 | EI8: 76 | EJ8: 9745
A9: 106010967 | B9: 010967 | C9: ALAMEDA | D9: ST. ROSE HOSPITAL | E9: 27200 CALAROGA AVE | F9: HAYWARD | G9: 94545 | H9: Non-profit Corporation (incl. Church-related) | I9: Teaching | J9: 150-199 | K9: District 10 | L9: District 20 | M9: San Leandro West/San Lorenzo West/Hayward West | N9: Urban | O9: 4209 | U9: 2084 | V9: 2125 | X9: 315 | Y9: 52 | Z9: 331 | AA9: 368 | AB9: 361 | AC9: 534 | AD9: 878 | AE9: 690 | AF9: 680 | AH9: 1346 | AI9: 2835 | AJ9: 28 | AL9: 879 | AM9: 140 | AN9: 612 | AO9: 1048 | AP9: 39 | AQ9: 1451 | AR9: 40 | AS9: 3206 | AT9: 37 | AU9: 152 | AV9: 489 | AW9: 3 | AZ9: 2 | BA9: 4 | BB9: 1 | BC9: 315 | BE9: 3260 | BF9: 51 | BG9: 898 | BI9: 17227 | BJ9: 3274 | BK9: 272 | BL9: 348 | BM9: 315 | BP9: 2424 | BQ9: 171 | BR9: 11 | BS9: 640 | BT9: 75 | BV9: 123 | BW9: 163 | BX9: 530 | BZ9: 5 | CA9: 50 | CB9: 17 | CG9: 277 | CH9: 3932 | CJ9: 1615 | CK9: 2125 | CL9: 348 | CM9: 6 | CO9: 14 | CP9: 26 | CQ9: 75 | CT9: 586 | CU9: 54 | CV9: 35 | CW9: 243 | CX9: 83 | CY9: 105 | CZ9: 3 | DA9: 9 | DB9: 794 | DC9: 283 | DD9: 514 | DE9: 57 | DF9: 209 | DG9: 248 | DH9: 352 | DI9: 315 | DK9: 115 | DL9: 197 | DM9: 6 | DN9: 1 | DO9: 728 | DP9: 309 | DQ9: 579 | DR9: 480 | DV9: 41 | DW9: 7 | DX9: 52 | DY9: 255 | DZ9: 13 | EA9: 12 | EB9: 45 | EC9: 25 | ED9: 1587 | EE9: 76 | EF9: 5 | EG9: 126 | EH9: 1 | EI9: 11 | EJ9: 4066
A10: 106010987 | B10: 010987 | C10: ALAMEDA | D10: WASHINGTON HOSPITAL - FREMONT | E10: 2000 MOWRY AVE | F10: FREMONT | G10: 94538 | H10: District | I10: Teaching | J10: 300-499 | K10: District 10 | L10: District 20 | M10: Fremont East/Niles/Union City Central | N10: Urban | O10: 11205 | P10: 302 | U10: 4981 | V10: 6526 | X10: 1639 | Y10: 46 | Z10: 433 | AA10: 1464 | AB10: 649 | AC10: 1000 | AD10: 1763 | AE10: 2008 | AF10: 2505 | AH10: 1483 | AI10: 9855 | AJ10: 169 | AK10: 13 | AL10: 5295 | AM10: 105 | AN10: 543 | AO10: 3352 | AP10: 152 | AQ10: 1818 | AR10: 229 | AS10: 7405 | AT10: 2109 | AV10: 399 | AW10: 68 | AZ10: 74 | BA10: 2 | BC10: 1450 | BE10: 7807 | BF10: 48 | BG10: 3652 | BI10: 58714 | BJ10: 7749 | BK10: 1400 | BL10: 906 | BM10: 1450 | BN10: 2 | BP10: 6596 | BQ10: 153 | BR10: 69 | BS10: 1460 | BW10: 408 | BX10: 2622 | BZ10: 6 | CA10: 160 | CB10: 22 | CC10: 3 | CD10: 5 | CE10: 2 | CF10: 1 | CG10: 1173 | CH10: 10334 | CJ10: 4961 | CK10: 2104 | CL10: 4170 | CM10: 56 | CO10: 57 | CQ10: 71 | CS10: 88 | CT10: 1386 | CU10: 342 | CV10: 47 | CW10: 474 | CX10: 95 | CY10: 178 | CZ10: 8 | DA10: 20 | DB10: 1821 | DC10: 770 | DD10: 1076 | DE10: 252 | DF10: 419 | DG10: 607 | DH10: 1532 | DI10: 1537 | DJ10: 9 | DK10: 55 | DL10: 837 | DM10: 38 | DN10: 4 | DO10: 2949 | DP10: 1433 | DQ10: 1218 | DR10: 850 | DS10: 6 | DT10: 18 | DV10: 95 | DW10: 26 | DX10: 220 | DY10: 743 | DZ10: 181 | EA10: 19 | EB10: 247 | EC10: 143 | ED10: 3108 | EE10: 251 | EF10: 11 | EG10: 149 | EH10: 30 | EI10: 59 | EJ10: 11258
A11: 106013687 | B11: 013687 | C11: ALAMEDA | D11: MPI CHEMICAL DEPENDENCY RECOVERY HOSPITAL | E11: 3012 SUMMIT ST | F11: OAKLAND | G11: 94609 | H11: Non-profit Corporation (incl. Church-related) | I11: Teaching | J11: 1-49 | K11: District 9 | L11: District 18 | M11: Dimond/Montclair/Oakland East/Oakmore/Piedmont/Piedmont Pines/Trestle Glen | N11: Urban | R11: 343 | U11: 221 | V11: 122 | Z11: 64 | AA11: 102 | AB11: 55 | AC11: 76 | AD11: 32 | AG11: 14 | AH11: 45 | AI11: 279 | AJ11: 19 | AL11: 17 | AN11: 40 | AO11: 227 | AP11: 29 | AQ11: 30 | AS11: 322 | AU11: 18 | AV11: 1 | AW11: 2 | BF11: 12 | BG11: 331 | BI11: 3747 | BK11: 17 | BL11: 326 | BP11: 304 | BQ11: 6 | BS11: 2 | BT11: 6 | BV11: 20 | BW11: 1 | CB11: 3 | CD11: 1 | CG11: 2 | CH11: 341 | CJ11: 4 | CK11: 1 | CL11: 304 | CO11: 27 | CQ11: 7 | CX11: 341 | DN11: 2 | DO11: 309 | ED11: 33 | EE11: 1 | EF11: 1 | EG11: 18 | EI11: 4 | EJ11: 320
A12: 106014034 | B12: 014034 | C12: ALAMEDA | D12: FREMONT HOSPITAL | E12: 39001 SUNDALE DR | F12: FREMONT | G12: 94538 | H12: Investor - Corporation | I12: Teaching | J12: 100-149 | K12: District 10 | L12: District 25 | M12: Centerville/Fremont West/Irvington/Newark East Central | N12: Urban | Q12: 5412 | U12: 2169 | V12: 3241 | W12: 2 | Y12: 2631 | Z12: 1118 | AA12: 706 | AB12: 461 | AC12: 312 | AD12: 135 | AE12: 47 | AG12: 2 | AH12: 828 | AI12: 4584 | AL12: 472 | AN12: 206 | AO12: 1455 | AP12: 29 | AQ12: 3250 | AS12: 63 | AU12: 4629 | AW12: 720 | BF12: 4631 | BG12: 781 | BI12: 42792 | BK12: 5412 | BP12: 5122 | BQ12: 14 | BT12: 64 | BU12: 1 | BV12: 205 | CE12: 6 | CH12: 5412 | CJ12: 516 | CK12: 1304 | CL12: 2575 | CM12: 1 | CO12: 1016 | CX12: 5404 | DN12: 8 | DO12: 776 | ED12: 4636 | EF12: 35 | EG12: 548 | EI12: 17 | EJ12: 4812
A13: 106014050 | B13: 014050 | C13: ALAMEDA | D13: STANFORD HEALTH CARE TRI-VALLEY | E13: 5555 W LAS POSITAS BLVD | F13: PLEASANTON | G13: 94588 | H13: Non-profit Corporation (incl. Church-related) | I13: Teaching | J13: 150-199 | K13: District 7 | L13: District 16 | M13: Dublin/Pleasanton/Santa Rita/Sunol | N13: Urban | O13: 8050 | U13: 3449 | V13: 4600 | W13: 1 | X13: 1353 | Y13: 34 | Z13: 400 | AA13: 1305 | AB13: 486 | AC13: 701 | AD13: 1014 | AE13: 1329 | AF13: 1428 | AH13: 993 | AI13: 6986 | AJ13: 71 | AK13: 31 | AL13: 1550 | AM13: 41 | AN13: 319 | AO13: 3673 | AP13: 48 | AQ13: 2213 | AR13: 175 | AS13: 6147 | AT13: 162 | AU13: 225 | AV13: 163 | AW13: 7 | AX13: 1 | AY13: 6 | AZ13: 3 | BA13: 33 | BC13: 1303 | BE13: 4280 | BF13: 34 | BG13: 3736 | BI13: 35608 | BJ13: 4441 | BK13: 256 | BL13: 2050 | BM13: 1303 | BP13: 4978 | BQ13: 173 | BR13: 40 | BS13: 986 | BU13: 36 | BW13: 244 | BX13: 1430 | BZ13: 1 | CA13: 149 | CB13: 9 | CE13: 4 | CG13: 491 | CH13: 7559 | CJ13: 3120 | CK13: 788 | CL13: 3193 | CM13: 34 | CO13: 96 | CQ13: 179 | CR13: 640 | CT13: 917 | CU13: 223 | CV13: 42 | CW13: 393 | CX13: 86 | CY13: 118 | CZ13: 4 | DA13: 6 | DB13: 1185 | DC13: 379 | DD13: 742 | DE13: 66 | DF13: 312 | DG13: 283 | DH13: 1376 | DI13: 1347 | DJ13: 11 | DK13: 59 | DL13: 492 | DM13: 9 | DO13: 875 | DP13: 1268 | DQ13: 932 | DR13: 741 | DT13: 1 | DV13: 56 | DW13: 23 | DX13: 102 | DY13: 472 | DZ13: 82 | EA13: 11 | EB13: 219 | EC13: 99 | ED13: 3008 | EE13: 161 | EG13: 90 | EH13: 5 | EI13: 64 | EJ13: 7891
A14: 106014132 | B14: 014132 | C14: ALAMEDA | D14: KAISER FOUNDATION HOSPITAL - FREMONT | E14: 39400 PASEO PADRE PKWY | F14: FREMONT | G14: 94538 | H14: Non-profit Corporation (incl. Church-related) | I14: Teaching | J14: 100-149 | K14: District 10 | L14: District 25 | M14: Fremont East/Niles/Union City Central | N14: Urban | O14: 4364 | Q14: 272 | U14: 2337 | V14: 2299 | Y14: 24 | Z14: 138 | AA14: 210 | AB14: 308 | AC14: 564 | AD14: 865 | AE14: 1052 | AF14: 1472 | AG14: 3 | AH14: 607 | AI14: 4023 | AJ14: 6 | AL14: 1385 | AM14: 33 | AN14: 330 | AO14: 2234 | AP14: 29 | AQ14: 625 | AS14: 3723 | AT14: 117 | AU14: 427 | AV14: 200 | AW14: 166 | AX14: 1 | AY14: 1 | BB14: 1 | BE14: 4064 | BF14: 243 | BG14: 329 | BI14: 23540 | BJ14: 565 | BK14: 3986 | BL14: 85 | BP14: 1977 | BQ14: 285 | BR14: 29 | BS14: 524 | BT14: 1 | BV14: 48 | BW14: 216 | BX14: 1346 | CA14: 172 | CB14: 29 | CD14: 3 | CE14: 6 | CG14: 869 | CH14: 3767 | CJ14: 2957 | CK14: 218 | CL14: 1391 | CM14: 16 | CO14: 2 | CQ14: 52 | CT14: 1292 | CU14: 106 | CV14: 49 | CW14: 236 | CX14: 331 | CY14: 106 | CZ14: 1 | DA14: 5 | DB14: 886 | DC14: 274 | DD14: 510 | DE14: 69 | DF14: 51 | DG14: 233 | DH14: 15 | DJ14: 1 | DK14: 135 | DL14: 322 | DM14: 14 | DO14: 1222 | DQ14: 318 | DR14: 538 | DS14: 2 | DT14: 6 | DV14: 19 | DW14: 11 | DX14: 106 | DY14: 200 | DZ14: 42 | EA14: 20 | EB14: 89 | EC14: 185 | ED14: 1675 | EE14: 203 | EG14: 55 | EI14: 15 | EJ14: 4566
A15: 106014207 | B15: 014207 | C15: ALAMEDA | D15: TELECARE HERITAGE PSYCHIATRIC HEALTH FACILITY | E15: 2633 E 27TH ST | F15: OAKLAND | G15: 94601 | H15: Investor - Corporation | I15: Teaching | J15: 1-49 | K15: District 9 | L15: District 18 | M15: Oakland West Central | N15: Urban | Q15: 1149 | U15: 523 | V15: 626 | Y15: 115 | Z15: 388 | AA15: 239 | AB15: 164 | AC15: 122 | AD15: 86 | AE15: 32 | AG15: 3 | AH15: 218 | AI15: 863 | AJ15: 68 | AL15: 86 | AN15: 164 | AO15: 517 | AP15: 33 | AQ15: 349 | AS15: 807 | AU15: 314 | AW15: 25 | BB15: 3 | BG15: 1149 | BI15: 6275 | BK15: 1149 | BP15: 1024 | BQ15: 16 | BS15: 2 | BT15: 57 | BU15: 2 | BV15: 48 | CH15: 1149 | CJ15: 202 | CK15: 47 | CL15: 885 | CQ15: 1 | CR15: 14 | CX15: 1149 | ED15: 1149 | EF15: 4 | EG15: 3 | EJ15: 1142
A16: 106014226 | B16: 014226 | C16: ALAMEDA | D16: TELECARE WILLOW ROCK CENTER | E16: 2050 FAIRMONT DR | F16: SAN LEANDRO | G16: 94578 | H16: Investor - Corporation | I16: Teaching | J16: 1-49 | K16: District 10 | L16: District 20 | M16: Castro Valley Central and North/Oak Knoll/San Leandro Northeast/Sheffield Village/Union City East | N16: Urban | Q16: 447 | U16: 168 | V16: 279 | Y16: 447 | AH16: 135 | AI16: 281 | AJ16: 31 | AL16: 14 | AN16: 80 | AO16: 148 | AP16: 16 | AQ16: 189 | AS16: 334 | AT16: 3 | AU16: 102 | AW16: 4 | BA16: 2 | BB16: 2 | BG16: 447 | BI16: 2385 | BK16: 447 | BP16: 431 | BQ16: 1 | BT16: 2 | BU16: 1 | BV16: 6 | CA16: 6 | CH16: 447 | CK16: 5 | CL16: 229 | CN16: 208 | CP16: 1 | CR16: 4 | CX16: 447 | ED16: 447 | EJ16: 447
A17: 106014233 | B17: 014233 | C17: ALAMEDA | D17: EDEN MEDICAL CENTER | E17: 20103 LAKE CHABOT RD | F17: CASTRO VALLEY | G17: 94546 | H17: Non-profit Corporation (incl. Church-related) | I17: Teaching | J17: 100-149 | K17: District 10 | L17: District 20 | M17: Castro Valley Central and North/Oak Knoll/San Leandro Northeast/Sheffield Village/Union City East | N17: Urban | O17: 9600 | U17: 4361 | V17: 5239 | X17: 1194 | Y17: 106 | Z17: 713 | AA17: 1269 | AB17: 652 | AC17: 961 | AD17: 1469 | AE17: 1551 | AF17: 1685 | AH17: 2424 | AI17: 7017 | AJ17: 159 | AK17: 29 | AL17: 1478 | AM17: 517 | AN17: 1429 | AO17: 4083 | AP17: 120 | AQ17: 1797 | AR17: 147 | AS17: 7659 | AT17: 71 | AU17: 200 | AV17: 449 | AW17: 20 | AY17: 3 | BA17: 5 | BC17: 1193 | BE17: 6574 | BF17: 77 | BG17: 2949 | BI17: 44615 | BJ17: 4183 | BK17: 1950 | BL17: 1016 | BM17: 1193 | BN17: 1258 | BP17: 5042 | BQ17: 413 | BR17: 162 | BS17: 1522 | BT17: 69 | BU17: 16 | BV17: 188 | BW17: 339 | BX17: 1544 | BZ17: 1 | CA17: 258 | CB17: 43 | CD17: 3 | CG17: 725 | CH17: 8875 | CJ17: 3597 | CK17: 2374 | CL17: 3229 | CM17: 62 | CO17: 150 | CQ17: 171 | CR17: 17 | CT17: 1264 | CU17: 259 | CV17: 114 | CW17: 358 | CX17: 106 | CY17: 269 | CZ17: 13 | DA17: 9 | DB17: 1208 | DC17: 357 | DD17: 739 | DE17: 120 | DF17: 291 | DG17: 357 | DH17: 1253 | DI17: 1194 | DJ17: 3 | DK17: 140 | DL17: 1523 | DM17: 23 | DO17: 1233 | DP17: 1185 | DQ17: 526 | DR17: 713 | DS17: 5 | DT17: 6 | DU17: 12 | DV17: 116 | DW17: 36 | DX17: 313 | DY17: 729 | DZ17: 217 | EA17: 21 | EB17: 232 | EC17: 123 | ED17: 3958 | EE17: 175 | EF17: 10 | EG17: 254 | EH17: 6 | EI17: 52 | EJ17: 9278
A18: 106014326 | B18: 014326 | C18: ALAMEDA | D18: KAISER FOUNDATION HOSPITAL - OAKLAND/RICHMOND | E18: 275 W MACARTHUR BLVD | F18: OAKLAND | G18: 94611 | H18: Non-profit Corporation (incl. Church-related) | I18: Teaching | J18: 300-499 | K18: District 9 | L18: District 15 | M18: Dimond/Montclair/Oakland East/Oakmore/Piedmont/Piedmont Pines/Trestle Glen | N18: Urban | O18: 23461 | U18: 10314 | V18: 13146 | W18: 1 | X18: 3847 | Y18: 903 | Z18: 1138 | AA18: 2870 | AB18: 1660 | AC18: 2190 | AD18: 3306 | AE18: 3946 | AF18: 3599 | AG18: 2 | AH18: 3946 | AI18: 19069 | AJ18: 446 | AK18: 83 | AL18: 3753 | AM18: 125 | AN18: 5756 | AO18: 8395 | AP18: 554 | AQ18: 4425 | AR18: 370 | AS18: 18889 | AT18: 145 | AU18: 1421 | AV18: 320 | AW18: 47 | AX18: 3 | AY18: 2 | BB18: 66 | BC18: 2563 | BD18: 5 | BE18: 12023 | BF18: 1042 | BG18: 10396 | BI18: 104645 | BJ18: 2664 | BK18: 14312 | BL18: 3916 | BM18: 2563 | BO18: 6 | BP18: 16734 | BQ18: 449 | BR18: 117 | BS18: 1817 | BT18: 6 | BV18: 260 | BW18: 689 | BX18: 2979 | BZ18: 2 | CA18: 296 | CB18: 49 | CC18: 2 | CD18: 38 | CE18: 23 | CG18: 2257 | CH18: 21204 | CJ18: 9437 | CK18: 2618 | CL18: 10950 | CM18: 18 | CO18: 125 | CQ18: 312 | CS18: 1 | CT18: 2823 | CU18: 1513 | CV18: 309 | CW18: 863 | CX18: 314 | CY18: 641 | CZ18: 32 | DA18: 30 | DB18: 3080 | DC18: 1385 | DD18: 1990 | DE18: 233 | DF18: 1317 | DG18: 658 | DH18: 2816 | DI18: 2684 | DJ18: 205 | DK18: 553 | DL18: 1374 | DM18: 641 | DO18: 6449 | DP18: 2567 | DQ18: 1542 | DR18: 2011 | DS18: 28 | DT18: 31 | DU18: 7 | DV18: 582 | DW18: 158 | DX18: 404 | DY18: 1702 | DZ18: 697 | EA18: 174 | EB18: 793 | EC18: 510 | ED18: 5204 | EE18: 602 | EF18: 23 | EG18: 239 | EI18: 61 | EJ18: 23138
A19: 106014337 | B19: 014337 | C19: ALAMEDA | D19: KAISER FOUNDATION HOSPITAL - SAN LEANDRO | E19: 2500 MERCED ST | F19: SAN LEANDRO | G19: 94577 | H19: Non-profit Corporation (incl. Church-related) | I19: Teaching | J19: 200-299 | K19: District 9 | L19: District 18 | M19: San Leandro West/San Lorenzo West/Hayward West | N19: Urban | O19: 15533 | U19: 5890 | V19: 9643 | X19: 3916 | Y19: 82 | Z19: 1372 | AA19: 3085 | AB19: 799 | AC19: 1023 | AD19: 1606 | AE19: 1819 | AF19: 1824 | AG19: 7 | AH19: 4116 | AI19: 11221 | AJ19: 196 | AK19: 72 | AL19: 4702 | AM19: 285 | AN19: 2025 | AO19: 4166 | AP19: 188 | AQ19: 3528 | AR19: 567 | AS19: 10460 | AT19: 153 | AU19: 498 | AV19: 344 | AW19: 255 | AX19: 1 | AZ19: 1 | BB19: 1 | BC19: 3819 | BD19: 1 | BE19: 6179 | BF19: 270 | BG19: 9084 | BI19: 53205 | BJ19: 602 | BK19: 9659 | BL19: 1453 | BM19: 3819 | BP19: 11024 | BQ19: 295 | BR19: 24 | BS19: 1036 | BV19: 76 | BW19: 361 | BX19: 2482 | CA19: 205 | CB19: 21 | CD19: 6 | CE19: 3 | CG19: 1222 | CH19: 14311 | CJ19: 4597 | CK19: 1247 | CL19: 9542 | CM19: 5 | CO19: 9 | CQ19: 133 | CT19: 2093 | CU19: 259 | CV19: 101 | CW19: 346 | CX19: 173 | CY19: 191 | CZ19: 4 | DA19: 6 | DB19: 1285 | DC19: 442 | DD19: 982 | DE19: 136 | DF19: 282 | DG19: 411 | DH19: 4047 | DI19: 3910 | DJ19: 6 | DK19: 152 | DL19: 656 | DM19: 49 | DN19: 2 | DO19: 4898 | DP19: 3797 | DQ19: 571 | DR19: 1123 | DS19: 6 | DT19: 1 | DU19: 3 | DV19: 879 | DW19: 17 | DX19: 206 | DY19: 715 | DZ19: 52 | EA19: 69 | EB19: 175 | EC19: 299 | ED19: 2412 | EE19: 310 | EF19: 3 | EG19: 69 | EI19: 26 | EJ19: 15435
A20: 106034002 | B20: 034002 | C20: AMADOR | D20: SUTTER AMADOR HOSPITAL | E20: 200 MISSION BLVD | F20: JACKSON | G20: 95642 | H20: Non-profit Corporation (incl. Church-related) | I20: Small/Rural | J20: 50-99 | K20: District 8 | L20: District 5 | M20: Ione/Jackson/Pine Grove/Sutter Creek | N20: Rural | O20: 2416 | U20: 1031 | V20: 1385 | X20: 239 | Y20: 16 | Z20: 147 | AA20: 185 | AB20: 107 | AC20: 209 | AD20: 423 | AE20: 535 | AF20: 555 | AH20: 213 | AI20: 2131 | AJ20: 72 | AK20: 32 | AL20: 11 | AN20: 18 | AO20: 2172 | AP20: 44 | AQ20: 98 | AR20: 41 | AS20: 2040 | AT20: 20 | AU20: 26 | AV20: 50 | AW20: 1 | AX20: 1 | AZ20: 1 | BA20: 45 | BB20: 1 | BC20: 231 | BE20: 1820 | BF20: 3 | BG20: 593 | BI20: 10181 | BJ20: 1391 | BK20: 517 | BL20: 277 | BM20: 231 | BP20: 1259 | BQ20: 135 | BR20: 8 | BS20: 284 | BT20: 4 | BU20: 49 | BV20: 52 | BW20: 57 | BX20: 494 | CA20: 66 | CB20: 3 | CC20: 1 | CD20: 4 | CG20: 230 | CH20: 2186 | CJ20: 1325 | CK20: 577 | CL20: 363 | CM20: 5 | CO20: 117 | CQ20: 29 | CT20: 563 | CU20: 17 | CV20: 17 | CW20: 83 | CX20: 37 | CY20: 60 | CZ20: 1 | DA20: 3 | DB20: 325 | DC20: 140 | DD20: 248 | DE20: 35 | DF20: 96 | DG20: 61 | DH20: 249 | DI20: 239 | DK20: 41 | DL20: 199 | DM20: 2 | DO20: 315 | DP20: 232 | DQ20: 62 | DR20: 182 | DU20: 1 | DV20: 6 | DW20: 3 | DX20: 31 | DY20: 200 | DZ20: 8 | EA20: 2 | EB20: 27 | EC20: 4 | ED20: 1228 | EE20: 115 | EF20: 3 | EG20: 26 | EH20: 2 | EI20: 15 | EJ20: 2370
A21: 106040802 | B21: 040802 | C21: BUTTE | D21: ORCHARD HOSPITAL | E21: 240 SPRUCE ST | F21: GRIDLEY | G21: 95948 | H21: Non-profit Corporation (incl. Church-related) | I21: Small/Rural | J21: 100-149 | K21: District 4 | L21: District 3 | M21: Biggs/East Biggs/Gridley | N21: Rural | O21: 327 | P21: 186 | U21: 263 | V21: 250 | AA21: 11 | AB21: 32 | AC21: 72 | AD21: 93 | AE21: 117 | AF21: 179 | AG21: 9 | AH21: 83 | AI21: 426 | AJ21: 4 | AO21: 421 | AP21: 19 | AQ21: 73 | AS21: 298 | AT21: 2 | AU21: 97 | AV21: 21 | AW21: 2 | AX21: 93 | BE21: 311 | BG21: 202 | BI21: 3660 | BK21: 329 | BL21: 184 | BP21: 249 | BQ21: 31 | BR21: 2 | BS21: 125 | BV21: 20 | BW21: 23 | BX21: 42 | BZ21: 1 | CA21: 9 | CC21: 11 | CG21: 431 | CH21: 82 | CJ21: 342 | CK21: 124 | CL21: 41 | CO21: 4 | CQ21: 2 | CT21: 104 | CU21: 13 | CW21: 39 | CX21: 14 | CY21: 21 | DA21: 1 | DB21: 85 | DC21: 69 | DD21: 22 | DE21: 18 | DF21: 29 | DG21: 17 | DK21: 18 | DL21: 54 | DM21: 9 | DO21: 21 | DQ21: 13 | DR21: 1 | DX21: 4 | DY21: 7 | ED21: 460 | EE21: 7 | EG21: 18 | EI21: 2 | EJ21: 493
A22: 106040937 | B22: 040937 | C22: BUTTE | D22: OROVILLE HOSPITAL | E22: 2767 OLIVE HWY | F22: OROVILLE | G22: 95966 | H22: Non-profit Corporation (incl. Church-related) | I22: Small/Rural | J22: 100-149 | K22: District 4 | L22: District 3 | M22: Oroville/Palermo/Thermalito | N22: Rural | O22: 11763 | P22: 419 | U22: 5761 | V22: 6421 | X22: 562 | Y22: 202 | Z22: 741 | AA22: 1067 | AB22: 1201 | AC22: 1834 | AD22: 2674 | AE22: 2192 | AF22: 1709 | AH22: 924 | AI22: 10778 | AJ22: 480 | AK22: 283 | AL22: 491 | AN22: 345 | AO22: 9813 | AP22: 156 | AQ22: 1022 | AR22: 72 | AS22: 11091 | AT22: 2 | AU22: 10 | AV22: 131 | AW22: 19 | AX22: 416 | AY22: 37 | BA22: 18 | BB22: 1 | BC22: 457 | BE22: 10054 | BG22: 2128 | BI22: 64812 | BJ22: 57 | BK22: 10412 | BL22: 1256 | BM22: 457 | BP22: 8468 | BQ22: 222 | BR22: 2 | BS22: 1140 | BT22: 77 | BU22: 65 | BV22: 1062 | BW22: 270 | BX22: 802 | CA22: 51 | CB22: 14 | CE22: 9 | CG22: 465 | CH22: 11717 | CJ22: 5634 | CK22: 4893 | CL22: 1094 | CM22: 32 | CN22: 1 | CO22: 364 | CP22: 6 | CQ22: 157 | CR22: 1 | CT22: 3276 | CU22: 239 | CV22: 40 | CW22: 387 | CX22: 223 | CY22: 477 | CZ22: 11 | DA22: 23 | DB22: 1615 | DC22: 375 | DD22: 1180 | DE22: 112 | DF22: 496 | DG22: 582 | DH22: 573 | DI22: 481 | DJ22: 11 | DK22: 597 | DL22: 1395 | DM22: 87 | DN22: 2 | DO22: 740 | DP22: 475 | DQ22: 348 | DR22: 1030 | DS22: 14 | DT22: 27 | DU22: 7 | DV22: 208 | DW22: 15 | DX22: 260 | DY22: 553 | DZ22: 35 | EA22: 53 | EB22: 312 | EC22: 244 | ED22: 7533 | EE22: 328 | EF22: 1 | EG22: 292 | EI22: 79 | EJ22: 11810
A23: 106040962 | B23: 040962 | C23: BUTTE | D23: ENLOE MEDICAL CENTER- ESPLANADE | E23: 1531 ESPLANADE | F23: CHICO | G23: 95926 | H23: Non-profit Corporation (incl. Church-related) | I23: Small/Rural | J23: 200-299 | K23: District 4 | L23: District 3 | M23: Chapmantown/Chico | N23: Urban | O23: 18730 | Q23: 417 | S23: 497 | U23: 9049 | V23: 10594 | W23: 1 | X23: 2267 | Y23: 244 | Z23: 1482 | AA23: 1699 | AB23: 1135 | AC23: 1805 | AD23: 3348 | AE23: 3917 | AF23: 3747 | AH23: 2870 | AI23: 16106 | AJ23: 668 | AK23: 268 | AL23: 359 | AM23: 38 | AN23: 339 | AO23: 15007 | AP23: 366 | AQ23: 3061 | AR23: 206 | AS23: 16005 | AT23: 470 | AU23: 516 | AV23: 213 | AW23: 46 | AX23: 439 | AY23: 2 | BA23: 2 | BB23: 28 | BC23: 1923 | BE23: 13154 | BF23: 39 | BG23: 6451 | BI23: 86169 | BJ23: 12742 | BK23: 419 | BL23: 4203 | BM23: 1923 | BN23: 346 | BO23: 11 | BP23: 13103 | BQ23: 360 | BR23: 460 | BS23: 1867 | BT23: 105 | BU23: 3 | BW23: 558 | BX23: 2825 | CA23: 344 | CB23: 19 | CG23: 2174 | CH23: 17470 | CJ23: 9330 | CK23: 4476 | CL23: 5483 | CM23: 46 | CO23: 41 | CQ23: 268 | CT23: 1904 | CU23: 507 | CV23: 134 | CW23: 939 | CX23: 592 | CY23: 429 | CZ23: 16 | DA23: 14 | DB23: 3164 | DC23: 1343 | DD23: 1954 | DE23: 257 | DF23: 794 | DG23: 1072 | DH23: 2019 | DI23: 2010 | DJ23: 13 | DK23: 352 | DL23: 1965 | DM23: 166 | DO23: 1425 | DP23: 1907 | DQ23: 1607 | DR23: 1926 | DS23: 16 | DT23: 1 | DU23: 1 | DV23: 219 | DW23: 38 | DX23: 343 | DY23: 1446 | DZ23: 187 | EA23: 188 | EB23: 447 | EC23: 393 | ED23: 9288 | EE23: 212 | EF23: 3 | EG23: 402 | EH23: 3 | EI23: 99 | EJ23: 19137
A24: 106044006 | B24: 044006 | C24: BUTTE | D24: BUTTE COUNTY MENTAL HEALTH SERVICES | E24: 592 RIO LINDO AVE | F24: CHICO | G24: 95926 | H24: City or County | I24: Small/Rural | J24: 1-49 | K24: District 4 | L24: District 3 | M24: Chapmantown/Chico | N24: Urban | Q24: 273 | U24: 126 | V24: 147 | Y24: 13 | Z24: 69 | AA24: 72 | AB24: 57 | AC24: 46 | AD24: 12 | AG24: 4 | AH24: 53 | AI24: 208 | AJ24: 12 | AK24: 16 | AN24: 24 | AO24: 182 | AP24: 14 | AQ24: 37 | AS24: 72 | AT24: 54 | AU24: 131 | BA24: 16 | BF24: 132 | BG24: 141 | BI24: 1635 | BJ24: 1 | BK24: 271 | BL24: 1 | BP24: 257 | BT24: 8 | BU24: 5 | BV24: 2 | CD24: 1 | CH24: 273 | CJ24: 44 | CK24: 208 | CL24: 1 | CQ24: 20 | CX24: 271 | DN24: 2 | ED24: 273 | EG24: 6 | EI24: 1 | EJ24: 266
A25: 106050932 | B25: 050932 | C25: CALAVERAS | D25: MARK TWAIN MEDICAL CENTER | E25: 768 MOUNTAIN RANCH RD | F25: SAN ANDREAS | G25: 95249 | H25: Non-profit Corporation (incl. Church-related) | I25: Small/Rural | J25: 1-49 | K25: District 8 | L25: District 5 | M25: Angels Camp/Arnold/Copperopolis/Mountain Ranch/Murphys/San Andreas/Valley Springs/West Point | N25: Rural | O25: 767 | U25: 356 | V25: 411 | Z25: 16 | AA25: 37 | AB25: 36 | AC25: 92 | AD25: 185 | AE25: 204 | AF25: 193 | AG25: 4 | AH25: 37 | AI25: 725 | AJ25: 5 | AO25: 724 | AP25: 23 | AQ25: 20 | AS25: 763 | AU25: 1 | AX25: 3 | BE25: 727 | BF25: 1 | BG25: 39 | BI25: 2870 | BJ25: 722 | BL25: 45 | BP25: 318 | BQ25: 59 | BR25: 10 | BS25: 158 | BT25: 2 | BV25: 29 | BW25: 26 | BX25: 146 | CA25: 9 | CB25: 5 | CD25: 5 | CG25: 12 | CH25: 755 | CJ25: 528 | CK25: 129 | CL25: 79 | CM25: 2 | CO25: 17 | CP25: 2 | CQ25: 10 | CT25: 169 | CU25: 9 | CV25: 3 | CW25: 40 | CX25: 37 | CY25: 16 | DB25: 124 | DC25: 87 | DD25: 93 | DE25: 38 | DF25: 28 | DG25: 40 | DK25: 13 | DL25: 67 | DM25: 3 | DO25: 145 | DQ25: 56 | DR25: 48 | DV25: 1 | DW25: 1 | DX25: 17 | DY25: 51 | DZ25: 7 | EB25: 4 | ED25: 433 | EE25: 4 | EG25: 6 | EI25: 12 | EJ25: 749
A26: 106060870 | B26: 060870 | C26: COLUSA | D26: COLUSA MEDICAL CENTER | E26: 199 E WEBSTER ST | F26: COLUSA | G26: 95932 | H26: Investor - Limited Liability Company | I26: Small/Rural | J26: 1-49 | K26: District 4 | L26: District 3 | M26: Colusa | N26: Rural | O26: 538 | P26: 255 | U26: 364 | V26: 429 | Z26: 15 | AA26: 30 | AB26: 55 | AC26: 86 | AD26: 164 | AE26: 197 | AF26: 245 | AG26: 1 | AH26: 140 | AI26: 653 | AL26: 16 | AN26: 12 | AO26: 697 | AP26: 22 | AR26: 46 | AS26: 465 | AT26: 1 | AU26: 176 | AV26: 1 | AW26: 1 | AX26: 149 | BE26: 441 | BF26: 56 | BG26: 296 | BI26: 7822 | BJ26: 40 | BK26: 741 | BL26: 12 | BP26: 355 | BQ26: 64 | BS26: 275 | BV26: 34 | BW26: 29 | BX26: 30 | CA26: 5 | CB26: 1 | CG26: 282 | CH26: 511 | CJ26: 511 | CK26: 226 | CL26: 37 | CM26: 1 | CQ26: 12 | CR26: 6 | CT26: 291 | CU26: 4 | CV26: 5 | CW26: 41 | CX26: 18 | CY26: 25 | DB26: 91 | DC26: 100 | DD26: 36 | DE26: 29 | DF26: 21 | DG26: 46 | DK26: 33 | DL26: 45 | DM26: 7 | DN26: 1 | DO26: 509 | DQ26: 1 | DR26: 1 | DS26: 1 | DX26: 8 | DY26: 2 | EB26: 58 | EC26: 12 | ED26: 198 | EE26: 3 | EG26: 24 | EI26: 8 | EJ26: 761
A27: 106070924 | B27: 070924 | C27: CONTRA COSTA | D27: CONTRA COSTA REGIONAL MEDICAL CENTER | E27: 2500 ALHAMBRA AVE | F27: MARTINEZ | G27: 94553 | H27: City or County | I27: Small/Rural | J27: 150-199 | K27: District 3 | L27: District 14 | M27: Crockett/Hercules/Martinez West/Pinole/Port Costa/Richmond Northeast/Rodeo | N27: Urban | O27: 7581 | Q27: 712 | U27: 3302 | V27: 4991 | X27: 1882 | Y27: 170 | Z27: 1447 | AA27: 1523 | AB27: 750 | AC27: 863 | AD27: 848 | AE27: 500 | AF27: 310 | AH27: 3604 | AI27: 4123 | AJ27: 566 | AK27: 21 | AL27: 743 | AM27: 99 | AN27: 1183 | AO27: 2010 | AP27: 119 | AQ27: 3946 | AR27: 172 | AS27: 5135 | AT27: 636 | AU27: 305 | AV27: 30 | AX27: 353 | AY27: 1 | BA27: 2 | BB27: 14 | BC27: 1817 | BE27: 5676 | BF27: 300 | BG27: 2317 | BI27: 40854 | BJ27: 131 | BK27: 5676 | BL27: 655 | BM27: 1817 | BO27: 14 | BP27: 7314 | BQ27: 428 | BS27: 3 | BT27: 313 | BU27: 55 | BV27: 3 | BW27: 58 | BX27: 15 | BZ27: 8 | CA27: 15 | CB27: 81 | CG27: 241 | CH27: 8052 | CJ27: 1175 | CK27: 6642 | CL27: 284 | CM27: 4 | CO27: 29 | CQ27: 159 | CT27: 427 | CU27: 143 | CV27: 58 | CW27: 310 | CX27: 1007 | CY27: 122 | CZ27: 10 | DA27: 5 | DB27: 635 | DC27: 271 | DD27: 697 | DE27: 150 | DF27: 88 | DG27: 242 | DH27: 1938 | DI27: 1881 | DJ27: 1 | DK27: 104 | DL27: 179 | DM27: 15 | DN27: 10 | DO27: 2133 | DP27: 1679 | DQ27: 80 | DR27: 572 | DS27: 4 | DT27: 6 | DU27: 2 | DV27: 193 | DW27: 20 | DX27: 100 | DY27: 204 | DZ27: 39 | EA27: 30 | EB27: 26 | EC27: 29 | ED27: 2976 | EE27: 200 | EF27: 3 | EG27: 393 | EI27: 24 | EJ27: 7873
A28: 106070934 | B28: 070934 | C28: CONTRA COSTA | D28: SUTTER DELTA MEDICAL CENTER | E28: 3901 LONE TREE WAY | F28: ANTIOCH | G28: 94509 | H28: Non-profit Corporation (incl. Church-related) | I28: Small/Rural | J28: 100-149 | K28: District 7 | L28: District 11 | M28: Brentwood Central and West/Oakley | N28: Urban | O28: 6405 | U28: 2995 | V28: 3410 | X28: 449 | Y28: 60 | Z28: 405 | AA28: 635 | AB28: 505 | AC28: 972 | AD28: 1222 | AE28: 1104 | AF28: 1053 | AH28: 1517 | AI28: 4825 | AJ28: 63 | AK28: 17 | AL28: 393 | AM28: 296 | AN28: 1419 | AO28: 3065 | AP28: 54 | AQ28: 1064 | AR28: 97 | AS28: 5688 | AT28: 50 | AU28: 62 | AV28: 158 | AW28: 5 | AY28: 1 | AZ28: 1 | BA28: 2 | BB28: 1 | BC28: 437 | BE28: 5392 | BF28: 13 | BG28: 1000 | BI28: 25435 | BJ28: 4184 | BK28: 1538 | BL28: 246 | BM28: 437 | BP28: 3434 | BQ28: 274 | BR28: 4 | BS28: 657 | BT28: 69 | BU28: 1 | BV28: 245 | BW28: 181 | BX28: 1410 | BZ28: 1 | CA28: 113 | CB28: 13 | CD28: 3 | CG28: 236 | CH28: 6169 | CJ28: 2676 | CK28: 2110 | CL28: 1313 | CM28: 3 | CO28: 204 | CQ28: 94 | CR28: 5 | CT28: 1201 | CU28: 68 | CV28: 92 | CW28: 421 | CX28: 105 | CY28: 179 | CZ28: 2 | DA28: 3 | DB28: 1289 | DC28: 478 | DD28: 705 | DE28: 91 | DF28: 87 | DG28: 307 | DH28: 468 | DI28: 449 | DJ28: 2 | DK28: 117 | DL28: 331 | DM28: 10 | DO28: 941 | DP28: 431 | DQ28: 779 | DR28: 579 | DS28: 3 | DV28: 50 | DW28: 8 | DX28: 86 | DY28: 194 | DZ28: 33 | EA28: 17 | EB28: 100 | EC28: 78 | ED28: 2837 | EE28: 269 | EF28: 17 | EG28: 244 | EH28: 4 | EI28: 49 | EJ28: 6091
A29: 106070988 | B29: 070988 | C29: CONTRA COSTA | D29: JOHN MUIR MEDICAL CENTER-WALNUT CREEK CAMPUS | E29: 1601 YGNACIO VALLEY RD | F29: WALNUT CREEK | G29: 94598 | H29: Non-profit Corporation (incl. Church-related) | I29: Small/Rural | J29: 500+ | K29: District 7 | L29: District 16 | M29: Clayton/Concord South/Walnut Creek Central and East | N29: Urban | O29: 21538 | S29: 420 | U29: 9187 | V29: 12771 | X29: 3824 | Y29: 424 | Z29: 1256 | AA29: 3049 | AB29: 1183 | AC29: 1717 | AD29: 2752 | AE29: 3626 | AF29: 4127 | AH29: 3500 | AI29: 17555 | AJ29: 903 | AK29: 63 | AL29: 2444 | AM29: 172 | AN29: 1388 | AO29: 13711 | AP29: 888 | AQ29: 2500 | AR29: 792 | AS29: 15808 | AT29: 415 | AU29: 1908 | AV29: 771 | AW29: 6 | AX29: 25 | AY29: 5 | AZ29: 1 | BB29: 31 | BC29: 2988 | BE29: 11730 | BF29: 616 | BG29: 9612 | BI29: 117891 | BJ29: 11081 | BK29: 1158 | BL29: 5513 | BM29: 2988 | BN29: 1200 | BO29: 18 | BP29: 11682 | BQ29: 537 | BR29: 266 | BS29: 2586 | BT29: 11 | BU29: 14 | BV29: 188 | BW29: 697 | BX29: 5451 | BZ29: 39 | CA29: 366 | CB29: 107 | CD29: 6 | CE29: 8 | CG29: 1253 | CH29: 20705 | CJ29: 8743 | CK29: 3271 | CL29: 8736 | CM29: 149 | CO29: 537 | CQ29: 507 | CR29: 15 | CT29: 1739 | CU29: 987 | CV29: 147 | CW29: 633 | CX29: 201 | CY29: 476 | CZ29: 14 | DA29: 7 | DB29: 2182 | DC29: 1240 | DD29: 1722 | DE29: 259 | DF29: 1681 | DG29: 816 | DH29: 3213 | DI29: 3150 | DJ29: 27 | DK29: 214 | DL29: 3007 | DM29: 242 | DN29: 1 | DO29: 846 | DP29: 2941 | DQ29: 1072 | DR29: 1844 | DS29: 12 | DT29: 22 | DU29: 12 | DV29: 790 | DW29: 171 | DX29: 527 | DY29: 2661 | DZ29: 507 | EA29: 119 | EB29: 564 | EC29: 179 | ED29: 9138 | EE29: 553 | EF29: 25 | EG29: 291 | EH29: 4 | EI29: 136 | EJ29: 21502
A30: 106070990 | B30: 070990 | C30: CONTRA COSTA | D30: KAISER FOUNDATION HOSPITAL - WALNUT CREEK | E30: 1425 S MAIN ST | F30: WALNUT CREEK | G30: 94596 | H30: Non-profit Corporation (incl. Church-related) | I30: Small/Rural | J30: 200-299 | K30: District 7 | L30: District 16 | M30: Clayton/Concord South/Walnut Creek Central and East | N30: Urban | O30: 14977 | U30: 6042 | V30: 8935 | X30: 3308 | Y30: 120 | Z30: 867 | AA30: 2574 | AB30: 773 | AC30: 896 | AD30: 1523 | AE30: 2021 | AF30: 2895 | AH30: 2051 | AI30: 12633 | AJ30: 293 | AK30: 34 | AL30: 2854 | AM30: 64 | AN30: 790 | AO30: 8570 | AP30: 237 | AQ30: 2201 | AR30: 227 | AS30: 10115 | AT30: 273 | AU30: 564 | AV30: 430 | AW30: 483 | AX30: 1 | AY30: 1 | BB30: 46 | BC30: 3064 | BE30: 7517 | BF30: 256 | BG30: 7204 | BI30: 57707 | BJ30: 1770 | BK30: 9263 | BL30: 867 | BM30: 3064 | BO30: 13 | BP30: 10256 | BQ30: 325 | BR30: 56 | BS30: 1373 | BT30: 5 | BV30: 88 | BW30: 361 | BX30: 2136 | CA30: 318 | CB30: 11 | CD30: 11 | CE30: 37 | CG30: 1934 | CH30: 13043 | CJ30: 5686 | CK30: 780 | CL30: 8402 | CM30: 5 | CO30: 11 | CQ30: 92 | CR30: 1 | CT30: 1843 | CU30: 326 | CV30: 95 | CW30: 345 | CX30: 147 | CY30: 230 | CZ30: 14 | DA30: 4 | DB30: 1776 | DC30: 701 | DD30: 1137 | DE30: 200 | DF30: 139 | DG30: 481 | DH30: 3244 | DI30: 3132 | DJ30: 6 | DK30: 244 | DL30: 853 | DM30: 60 | DO30: 3815 | DP30: 3077 | DQ30: 1114 | DR30: 1174 | DS30: 6 | DT30: 3 | DU30: 4 | DV30: 870 | DW30: 27 | DX30: 216 | DY30: 610 | DZ30: 83 | EA30: 90 | EB30: 212 | EC30: 279 | ED30: 3078 | EE30: 319 | EG30: 38 | EI30: 36 | EJ30: 14903
A31: 106071018 | B31: 071018 | C31: CONTRA COSTA | D31: JOHN MUIR MEDICAL CENTER-CONCORD CAMPUS | E31: 2540 EAST ST | F31: CONCORD | G31: 94520 | H31: Non-profit Corporation (incl. Church-related) | I31: Small/Rural | J31: 200-299 | K31: District 7 | L31: District 14 | M31: Avon/Clyde/Concord Central/Pittsburg Southwest | N31: Urban | O31: 10777 | U31: 5560 | V31: 5217 | Y31: 31 | Z31: 276 | AA31: 518 | AB31: 867 | AC31: 1485 | AD31: 2550 | AE31: 2684 | AF31: 2366 | AH31: 1926 | AI31: 8727 | AJ31: 124 | AK31: 34 | AL31: 923 | AM31: 120 | AN31: 1275 | AO31: 6708 | AP31: 131 | AQ31: 1442 | AR31: 144 | AS31: 9519 | AT31: 262 | AU31: 600 | AV31: 369 | AW31: 10 | AX31: 5 | AY31: 3 | AZ31: 1 | BA31: 3 | BB31: 5 | BE31: 8297 | BF31: 88 | BG31: 2392 | BI31: 60503 | BJ31: 8338 | BK31: 871 | BL31: 1565 | BN31: 1 | BO31: 2 | BP31: 4320 | BQ31: 243 | BR31: 50 | BS31: 1572 | BT31: 3 | BU31: 7 | BV31: 313 | BW31: 424 | BX31: 3575 | CA31: 209 | CB31: 55 | CE31: 6 | CG31: 695 | CH31: 10082 | CJ31: 5921 | CK31: 2260 | CL31: 1836 | CM31: 13 | CN31: 1 | CO31: 551 | CQ31: 179 | CR31: 16 | CT31: 1528 | CU31: 530 | CV31: 99 | CW31: 861 | CX31: 172 | CY31: 239 | CZ31: 9 | DA31: 12 | DB31: 2591 | DC31: 715 | DD31: 1326 | DE31: 174 | DF31: 651 | DG31: 826 | DH31: 12 | DJ31: 36 | DK31: 134 | DL31: 827 | DM31: 35 | DO31: 563 | DQ31: 2137 | DR31: 1445 | DS31: 3 | DT31: 4 | DV31: 88 | DW31: 72 | DX31: 190 | DY31: 1008 | DZ31: 51 | EA31: 16 | EB31: 427 | EC31: 316 | ED31: 3995 | EE31: 462 | EF31: 2 | EG31: 317 | EH31: 3 | EI31: 66 | EJ31: 10389
A32: 106074017 | B32: 074017 | C32: CONTRA COSTA | D32: SAN RAMON REGIONAL MEDICAL CENTER | E32: 6001 NORRIS CANYON RD | F32: SAN RAMON | G32: 94583 | H32: Investor - Corporation | I32: Small/Rural | J32: 100-149 | K32: District 7 | L32: District 16 | M32: Alamo/Danville/Diablo/San Ramon | N32: Urban | O32: 3842 | U32: 1683 | V32: 2159 | X32: 260 | Y32: 20 | Z32: 103 | AA32: 323 | AB32: 286 | AC32: 356 | AD32: 562 | AE32: 852 | AF32: 1080 | AH32: 207 | AI32: 3453 | AJ32: 182 | AL32: 598 | AM32: 28 | AN32: 170 | AO32: 2475 | AP32: 112 | AQ32: 443 | AR32: 16 | AS32: 3546 | AT32: 17 | AU32: 5 | AV32: 7 | AW32: 14 | AX32: 4 | AY32: 1 | AZ32: 1 | BC32: 247 | BE32: 2854 | BF32: 3 | BG32: 985 | BI32: 17484 | BJ32: 1342 | BK32: 1707 | BL32: 546 | BM32: 247 | BP32: 2222 | BQ32: 54 | BR32: 6 | BS32: 476 | BT32: 18 | BU32: 1 | BV32: 61 | BW32: 86 | BX32: 810 | BZ32: 3 | CA32: 102 | CB32: 3 | CG32: 466 | CH32: 3373 | CI32: 3 | CJ32: 1916 | CK32: 176 | CL32: 1379 | CM32: 81 | CO32: 13 | CP32: 2 | CQ32: 4 | CR32: 271 | CT32: 427 | CU32: 106 | CV32: 30 | CW32: 209 | CX32: 64 | CY32: 121 | CZ32: 2 | DA32: 8 | DB32: 609 | DC32: 258 | DD32: 516 | DE32: 65 | DF32: 337 | DG32: 162 | DH32: 259 | DI32: 251 | DJ32: 3 | DK32: 97 | DL32: 298 | DM32: 20 | DO32: 988 | DP32: 245 | DQ32: 286 | DR32: 454 | DS32: 2 | DV32: 22 | DW32: 4 | DX32: 49 | DY32: 432 | DZ32: 56 | EA32: 6 | EB32: 95 | EC32: 84 | ED32: 1011 | EE32: 108 | EF32: 8 | EG32: 1 | EI32: 52 | EJ32: 3781
A33: 106074039 | B33: 074039 | C33: CONTRA COSTA | D33: JOHN MUIR BEHAVIORAL HEALTH CENTER | E33: 2740 GRANT ST | F33: CONCORD | G33: 94520 | H33: Non-profit Corporation (incl. Church-related) | I33: Small/Rural | J33: 50-99 | K33: District 7 | L33: District 14 | M33: Concord West/Martinez East/Martinez Waterfront/Pacheco/Pleasant Hill East | N33: Urban | Q33: 3101 | U33: 1215 | V33: 1886 | X33: 46 | Y33: 1571 | Z33: 442 | AA33: 285 | AB33: 210 | AC33: 224 | AD33: 218 | AE33: 95 | AG33: 10 | AH33: 601 | AI33: 2353 | AJ33: 147 | AK33: 19 | AL33: 230 | AM33: 16 | AN33: 292 | AO33: 1559 | AP33: 149 | AQ33: 777 | AR33: 59 | AS33: 526 | AT33: 1 | AU33: 2573 | BB33: 1 | BF33: 2471 | BG33: 630 | BI33: 18300 | BJ33: 2692 | BK33: 404 | BL33: 3 | BO33: 2 | BP33: 2675 | BQ33: 48 | BR33: 24 | BS33: 3 | BU33: 2 | BV33: 335 | CB33: 10 | CD33: 1 | CE33: 3 | CH33: 3101 | CJ33: 412 | CK33: 751 | CL33: 1644 | CO33: 237 | CQ33: 57 | CX33: 3092 | CY33: 2 | DN33: 7 | ED33: 3099 | EE33: 2 | EF33: 2 | EG33: 91 | EI33: 28 | EJ33: 2980
A34: 106074097 | B34: 074097 | C34: CONTRA COSTA | D34: KAISER FOUNDATION HOSPITAL - ANTIOCH | E34: 4501 SAND CREEK ROAD | F34: ANTIOCH | G34: 94531 | H34: Non-profit Corporation (incl. Church-related) | I34: Small/Rural | J34: 150-199 | K34: District 7 | L34: District 11 | M34: Brentwood Central and West/Oakley | N34: Urban | O34: 10532 | U34: 4217 | V34: 6315 | X34: 1880 | Y34: 67 | Z34: 940 | AA34: 1432 | AB34: 643 | AC34: 998 | AD34: 1325 | AE34: 1722 | AF34: 1524 | AG34: 1 | AH34: 2414 | AI34: 8058 | AJ34: 60 | AK34: 28 | AL34: 1242 | AM34: 91 | AN34: 1716 | AO34: 4783 | AP34: 54 | AQ34: 2493 | AR34: 125 | AS34: 8093 | AT34: 116 | AU34: 252 | AV34: 69 | AW34: 156 | BB34: 12 | BC34: 1834 | BE34: 5920 | BF34: 29 | BG34: 4583 | BI34: 37175 | BJ34: 1388 | BK34: 6686 | BL34: 623 | BM34: 1834 | BO34: 1 | BP34: 6858 | BQ34: 358 | BR34: 30 | BS34: 648 | BV34: 98 | BW34: 239 | BX34: 2094 | CA34: 173 | CB34: 4 | CD34: 4 | CE34: 25 | CF34: 1 | CG34: 912 | CH34: 9620 | CJ34: 4126 | CK34: 1206 | CL34: 5078 | CM34: 11 | CO34: 7 | CQ34: 104 | CT34: 1895 | CU34: 266 | CV34: 88 | CW34: 247 | CX34: 74 | CY34: 173 | CZ34: 2 | DA34: 4 | DB34: 1231 | DC34: 466 | DD34: 972 | DE34: 111 | DF34: 146 | DG34: 330 | DH34: 1963 | DI34: 1878 | DJ34: 8 | DK34: 147 | DL34: 493 | DM34: 38 | DO34: 2732 | DP34: 1849 | DQ34: 390 | DR34: 992 | DS34: 6 | DT34: 1 | DV34: 538 | DW34: 18 | DX34: 168 | DY34: 418 | DZ34: 54 | EA34: 39 | EB34: 167 | EC34: 238 | ED34: 2624 | EE34: 298 | EF34: 3 | EG34: 61 | EI34: 15 | EJ34: 10453
A35: 106084001 | B35: 084001 | C35: DEL NORTE | D35: SUTTER COAST HOSPITAL | E35: 800 E WASHINGTON BLVD | F35: CRESCENT CITY | G35: 95531 | H35: Non-profit Corporation (incl. Church-related) | I35: Small/Rural | J35: 1-49 | K35: District 2 | L35: District 2 | M35: Crescent City/Gasquet/Klamath/Smith River | N35: Rural | O35: 2188 | S35: 139 | U35: 1025 | V35: 1302 | X35: 285 | Y35: 49 | Z35: 198 | AA35: 198 | AB35: 122 | AC35: 255 | AD35: 430 | AE35: 459 | AF35: 331 | AH35: 212 | AI35: 2067 | AJ35: 48 | AK35: 96 | AL35: 43 | AM35: 12 | AN35: 18 | AO35: 1931 | AP35: 22 | AQ35: 124 | AR35: 81 | AS35: 1848 | AT35: 16 | AU35: 87 | AV35: 45 | AW35: 1 | AX35: 64 | AY35: 1 | BA35: 20 | BC35: 245 | BE35: 1565 | BF35: 6 | BG35: 756 | BI35: 10163 | BJ35: 914 | BK35: 722 | BL35: 397 | BM35: 245 | BN35: 49 | BP35: 1517 | BQ35: 108 | BR35: 57 | BS35: 145 | BT35: 4 | BU35: 24 | BV35: 77 | BW35: 83 | BX35: 304 | CA35: 4 | CB35: 1 | CD35: 3 | CG35: 194 | CH35: 2133 | CJ35: 1035 | CK35: 697 | CL35: 305 | CM35: 10 | CO35: 214 | CQ35: 66 | CT35: 567 | CU35: 21 | CV35: 22 | CW35: 80 | CX35: 31 | CY35: 41 | DB35: 273 | DC35: 115 | DD35: 205 | DE35: 48 | DF35: 70 | DG35: 54 | DH35: 258 | DI35: 252 | DK35: 25 | DL35: 231 | DM35: 34 | DO35: 308 | DP35: 240 | DQ35: 23 | DR35: 151 | DV35: 43 | DW35: 3 | DX35: 60 | DY35: 219 | DZ35: 5 | EA35: 8 | EB35: 40 | EC35: 5 | ED35: 1170 | EE35: 52 | EF35: 6 | EG35: 46 | EI35: 326 | EJ35: 1949
A36: 106090793 | B36: 090793 | C36: EL DORADO | D36: BARTON MEMORIAL HOSPITAL | E36: 2170 SOUTH AVE | F36: SOUTH LAKE TAHOE | G36: 96150 | H36: Non-profit Corporation (incl. Church-related) | I36: Small/Rural | J36: 100-149 | K36: District 1 | L36: District 5 | M36: South Lake Tahoe | N36: Rural | O36: 1914 | P36: 6 | U36: 895 | V36: 1025 | X36: 367 | Y36: 29 | Z36: 140 | AA36: 271 | AB36: 139 | AC36: 185 | AD36: 312 | AE36: 295 | AF36: 182 | AH36: 306 | AI36: 1507 | AJ36: 107 | AL36: 46 | AN36: 21 | AO36: 1633 | AP36: 116 | AQ36: 80 | AR36: 24 | AS36: 1200 | AT36: 405 | AU36: 10 | AV36: 5 | AX36: 6 | BA36: 4 | BB36: 1 | BC36: 289 | BE36: 1174 | BG36: 746 | BI36: 7089 | BJ36: 1090 | BK36: 48 | BL36: 418 | BM36: 289 | BN36: 75 | BP36: 1576 | BQ36: 57 | BR36: 12 | BS36: 102 | BT36: 3 | BU36: 2 | BV36: 19 | BW36: 43 | BX36: 70 | BZ36: 10 | CA36: 8 | CB36: 10 | CC36: 8 | CG36: 136 | CH36: 1784 | CJ36: 635 | CK36: 512 | CL36: 600 | CM36: 5 | CO36: 91 | CQ36: 67 | CR36: 10 | CT36: 180 | CU36: 26 | CV36: 10 | CW36: 52 | CX36: 61 | CY36: 17 | DA36: 1 | DB36: 116 | DC36: 183 | DD36: 227 | DE36: 40 | DF36: 112 | DG36: 40 | DH36: 302 | DI36: 307 | DK36: 19 | DL36: 217 | DM36: 10 | DO36: 375 | DP36: 286 | DQ36: 24 | DR36: 152 | DS36: 1 | DT36: 1 | DV36: 23 | DX36: 35 | DY36: 218 | DZ36: 13 | EA36: 8 | EB36: 28 | EC36: 7 | ED36: 722 | EE36: 27 | EF36: 1 | EG36: 24 | EH36: 4 | EI36: 341 | EJ36: 1550
A37: 106090933 | B37: 090933 | C37: EL DORADO | D37: MARSHALL MEDICAL CENTER | E37: 1100 MARSHALL WAY | F37: PLACERVILLE | G37: 95667 | H37: Non-profit Corporation (incl. Church-related) | I37: Small/Rural | J37: 100-149 | K37: District 1 | L37: District 5 | M37: Cool/Diamond Springs/Latrobe/Pilot Hill/Placerville | N37: Rural | O37: 4691 | U37: 2199 | V37: 2492 | X37: 366 | Y37: 26 | Z37: 297 | AA37: 364 | AB37: 280 | AC37: 460 | AD37: 867 | AE37: 1007 | AF37: 1023 | AG37: 1 | AH37: 353 | AI37: 4279 | AJ37: 59 | AK37: 32 | AL37: 24 | AN37: 25 | AO37: 4118 | AP37: 72 | AQ37: 394 | AR37: 26 | AS37: 3714 | AT37: 547 | AU37: 13 | AV37: 42 | AW37: 10 | BA37: 2 | BB37: 15 | BC37: 348 | BE37: 3741 | BF37: 2 | BG37: 941 | BH37: 7 | BI37: 18143 | BJ37: 2451 | BK37: 1328 | BL37: 429 | BM37: 348 | BN37: 134 | BO37: 1 | BP37: 3025 | BQ37: 174 | BR37: 5 | BS37: 574 | BT37: 10 | BU37: 14 | BV37: 77 | BW37: 131 | BX37: 507 | CA37: 162 | CB37: 4 | CC37: 1 | CD37: 7 | CG37: 435 | CH37: 4256 | CJ37: 1856 | CK37: 1234 | CL37: 1375 | CM37: 10 | CO37: 163 | CQ37: 32 | CR37: 7 | CS37: 14 | CT37: 701 | CU37: 95 | CV37: 14 | CW37: 193 | CX37: 153 | CY37: 74 | CZ37: 3 | DA37: 4 | DB37: 663 | DC37: 462 | DD37: 606 | DE37: 102 | DF37: 177 | DG37: 211 | DH37: 385 | DI37: 366 | DJ37: 1 | DK37: 48 | DL37: 423 | DM37: 8 | DN37: 2 | DO37: 953 | DP37: 344 | DQ37: 217 | DR37: 418 | DS37: 1 | DU37: 1 | DV37: 21 | DW37: 2 | DX37: 100 | DY37: 306 | DZ37: 21 | EA37: 8 | EB37: 85 | EC37: 276 | ED37: 1876 | EE37: 62 | EG37: 123 | EH37: 1 | EI37: 19 | EJ37: 4548
A38: 106094002 | B38: 094002 | C38: EL DORADO | D38: TELECARE EL DORADO COUNTY P.H.F. | E38: 935B SPRING ST | F38: PLACERVILLE | G38: 95667 | H38: Investor - Corporation | I38: Small/Rural | J38: 1-49 | K38: District 1 | L38: District 5 | M38: Cool/Diamond Springs/Latrobe/Pilot Hill/Placerville | N38: Rural | Q38: 299 | U38: 162 | V38: 137 | Z38: 100 | AA38: 103 | AB38: 36 | AC38: 30 | AD38: 20 | AG38: 10 | AH38: 25 | AI38: 272 | AJ38: 2 | AN38: 17 | AO38: 237 | AP38: 14 | AQ38: 31 | AS38: 2 | AU38: 297 | BG38: 299 | BI38: 3856 | BK38: 299 | BP38: 281 | BQ38: 5 | BT38: 1 | BU38: 2 | BV38: 9 | CA38: 1 | CH38: 299 | CK38: 265 | CN38: 32 | CR38: 2 | CX38: 299 | ED38: 299 | EF38: 2 | EI38: 4 | EJ38: 293
A39: 106100005 | B39: 100005 | C39: FRESNO | D39: CLOVIS COMMUNITY MEDICAL CENTER | E39: 2755 HERNDON AVE | F39: CLOVIS | G39: 93611 | H39: Non-profit Corporation (incl. Church-related) | I39: Small/Rural | J39: 300-499 | K39: District 8 | L39: District 23 | M39: Auberry/Calwa/Centerville/Clovis East/Del Rey/Fowler/Friant/Sanger/Shaver Lake | N39: Rural | O39: 22533 | U39: 8432 | V39: 14101 | X39: 4633 | Y39: 178 | Z39: 2826 | AA39: 3261 | AB39: 1486 | AC39: 1896 | AD39: 2821 | AE39: 2806 | AF39: 2626 | AH39: 8392 | AI39: 14054 | AJ39: 87 | AK39: 279 | AL39: 1985 | AM39: 74 | AN39: 955 | AO39: 17944 | AP39: 49 | AQ39: 1036 | AR39: 211 | AS39: 17648 | AT39: 26 | AU39: 28 | AV39: 174 | AW39: 25 | AX39: 3 | BA39: 1 | BB39: 3 | BC39: 4625 | BE39: 12096 | BF39: 3 | BG39: 10434 | BI39: 96978 | BJ39: 12151 | BK39: 4400 | BL39: 1314 | BM39: 4625 | BN39: 2 | BO39: 41 | BP39: 15031 | BQ39: 480 | BR39: 401 | BS39: 1548 | BT39: 102 | BU39: 1 | BV39: 370 | BW39: 584 | BX39: 3544 | BZ39: 4 | CA39: 420 | CB39: 39 | CD39: 3 | CE39: 6 | CG39: 653 | CH39: 21880 | CJ39: 7230 | CK39: 6720 | CL39: 7782 | CM39: 37 | CO39: 329 | CQ39: 435 | CT39: 1753 | CU39: 621 | CV39: 164 | CW39: 1065 | CX39: 163 | CY39: 332 | CZ39: 13 | DA39: 19 | DB39: 1916 | DC39: 1175 | DD39: 2240 | DE39: 325 | DF39: 381 | DG39: 1204 | DH39: 4921 | DI39: 4632 | DJ39: 10 | DK39: 253 | DL39: 1208 | DM39: 137 | DN39: 1 | DO39: 1796 | DP39: 4534 | DQ39: 1165 | DR39: 2103 | DS39: 6 | DT39: 10 | DU39: 1 | DV39: 180 | DW39: 114 | DX39: 383 | DY39: 1121 | DZ39: 131 | EA39: 23 | EB39: 437 | EC39: 296 | ED39: 9783 | EE39: 450 | EG39: 167 | EH39: 1 | EI39: 60 | EJ39: 22305
A40: 106100697 | B40: 100697 | C40: FRESNO | D40: COALINGA REGIONAL MEDICAL CENTER | E40: 1191 PHELPS AVE | F40: COALINGA | G40: 93210 | H40: Investor - Limited Liability Company | I40: Small/Rural | J40: 100-149 | K40: District 12 | L40: District 31 | M40: Coalinga | N40: Rural | O40: 637 | P40: 92 | U40: 352 | V40: 377 | Z40: 48 | AA40: 97 | AB40: 119 | AC40: 112 | AD40: 167 | AE40: 109 | AF40: 71 | AG40: 6 | AH40: 420 | AI40: 306 | AJ40: 3 | AN40: 22 | AO40: 695 | AP40: 12 | AS40: 714 | AU40: 2 | AV40: 7 | AX40: 6 | BE40: 10 | BG40: 719 | BI40: 9971 | BJ40: 23 | BK40: 694 | BL40: 12 | BP40: 509 | BQ40: 34 | BR40: 2 | BS40: 43 | BT40: 25 | BU40: 24 | BV40: 51 | BW40: 2 | BX40: 8 | CA40: 2 | CC40: 10 | CD40: 19 | CG40: 133 | CH40: 595 | CI40: 1 | CJ40: 74 | CK40: 208 | CL40: 200 | CM40: 5 | CO40: 1 | CQ40: 15 | CR40: 222 | CS40: 4 | CT40: 98 | CU40: 5 | CV40: 14 | CW40: 59 | CX40: 27 | CY40: 23 | CZ40: 1 | DA40: 1 | DB40: 81 | DC40: 75 | DD40: 80 | DE40: 52 | DF40: 23 | DG40: 102 | DK40: 40 | DL40: 41 | DM40: 5 | DN40: 2 | DO40: 466 | DP40: 1 | DX40: 4 | DY40: 1 | EA40: 1 | EB40: 12 | ED40: 239 | EE40: 5 | EG40: 2 | EI40: 5 | EJ40: 722
A41: 106100717 | B41: 100717 | C41: FRESNO | D41: COMMUNITY REGIONAL MEDICAL CENTER-FRESNO | E41: 2823 FRESNO ST | F41: FRESNO | G41: 93721 | H41: Non-profit Corporation (incl. Church-related) | I41: Teaching | J41: 500+ | K41: District 14 | L41: District 31 | M41: Fresno West Central | N41: Urban | O41: 41220 | P41: 88 | Q41: 2155 | S41: 713 | U41: 20977 | V41: 23198 | W41: 1 | X41: 4905 | Y41: 1155 | Z41: 5198 | AA41: 5968 | AB41: 4995 | AC41: 6250 | AD41: 7290 | AE41: 5180 | AF41: 3235 | AH41: 21815 | AI41: 22235 | AJ41: 126 | AK41: 404 | AL41: 2934 | AM41: 124 | AN41: 4110 | AO41: 33589 | AP41: 80 | AQ41: 2341 | AR41: 594 | AS41: 32819 | AT41: 214 | AU41: 3322 | AV41: 1109 | AW41: 710 | AX41: 1577 | AY41: 1 | BA41: 346 | BB41: 41 | BC41: 4037 | BE41: 26774 | BF41: 875 | BG41: 16527 | BI41: 296985 | BJ41: 22810 | BK41: 8257 | BL41: 5802 | BM41: 4037 | BN41: 3132 | BO41: 138 | BP41: 27153 | BQ41: 637 | BR41: 945 | BS41: 3258 | BT41: 152 | BU41: 439 | BV41: 2113 | BW41: 1280 | BX41: 7303 | BZ41: 10 | CA41: 571 | CB41: 246 | CD41: 39 | CE41: 30 | CG41: 1218 | CH41: 42958 | CJ41: 12796 | CK41: 22158 | CL41: 5763 | CM41: 222 | CN41: 131 | CO41: 1942 | CQ41: 1164 | CT41: 3278 | CU41: 1365 | CV41: 214 | CW41: 3172 | CX41: 3356 | CY41: 1267 | CZ41: 56 | DA41: 65 | DB41: 6009 | DC41: 2028 | DD41: 3577 | DE41: 659 | DF41: 1188 | DG41: 1839 | DH41: 5097 | DI41: 4246 | DJ41: 76 | DK41: 798 | DL41: 5366 | DM41: 517 | DN41: 3 | DO41: 4633 | DP41: 3951 | DQ41: 4266 | DR41: 4974 | DS41: 27 | DT41: 52 | DU41: 19 | DV41: 471 | DW41: 174 | DX41: 1212 | DY41: 2608 | DZ41: 983 | EA41: 137 | EB41: 931 | EC41: 496 | ED41: 18469 | EE41: 773 | EF41: 59 | EG41: 2347 | EH41: 12 | EI41: 163 | EJ41: 41595
A42: 106100797 | B42: 100797 | C42: FRESNO | D42: ADVENTIST HEALTH REEDLEY | E42: 372 W CYPRESS AVE | F42: REEDLEY | G42: 93654 | H42: Non-profit Corporation (incl. Church-related) | I42: Small/Rural | J42: 1-49 | K42: District 14 | L42: District 31 | M42: Orange Cove/Parlier/Reedley/Squaw Valley/Tivy Valley/Wonder Valley | N42: Rural | O42: 2843 | P42: 203 | U42: 879 | V42: 2167 | X42: 1263 | Y42: 81 | Z42: 728 | AA42: 502 | AB42: 98 | AC42: 92 | AD42: 92 | AE42: 90 | AF42: 100 | AH42: 2567 | AI42: 399 | AJ42: 80 | AL42: 25 | AN42: 12 | AO42: 2208 | AP42: 86 | AQ42: 715 | AS42: 1531 | AT42: 25 | AU42: 188 | AV42: 8 | AX42: 33 | BC42: 1261 | BE42: 252 | BF42: 71 | BG42: 2718 | BH42: 5 | BI42: 10829 | BJ42: 234 | BK42: 360 | BL42: 1191 | BM42: 1261 | BP42: 2647 | BQ42: 79 | BR42: 1 | BS42: 71 | BT42: 1 | BV42: 27 | BW42: 8 | BX42: 182 | BZ42: 22 | CA42: 6 | CE42: 2 | CG42: 72 | CH42: 2974 | CJ42: 225 | CK42: 2307 | CL42: 456 | CO42: 13 | CQ42: 43 | CS42: 2 | CT42: 40 | CU42: 13 | CW42: 32 | CX42: 10 | CY42: 11 | CZ42: 1 | DA42: 1 | DB42: 67 | DC42: 69 | DD42: 34 | DE42: 8 | DF42: 21 | DG42: 63 | DH42: 1308 | DI42: 1263 | DK42: 44 | DL42: 34 | DM42: 26 | DN42: 1 | DO42: 1313 | DP42: 1284 | DQ42: 21 | DR42: 2 | DV42: 38 | DX42: 7 | DY42: 1 | DZ42: 4 | EB42: 4 | EC42: 1 | ED42: 362 | EE42: 9 | EF42: 1 | EG42: 18 | EJ42: 3027
A43: 106100899 | B43: 100899 | C43: FRESNO | D43: ST. AGNES MEDICAL CENTER | E43: 1303 E HERNDON AVE | F43: FRESNO | G43: 93720 | H43: Non-profit Corporation (incl. Church-related) | I43: Small/Rural | J43: 300-499 | K43: District 8 | L43: District 23 | M43: Fresno North Central | N43: Urban | O43: 26402 | U43: 10759 | V43: 15643 | X43: 3974 | Y43: 258 | Z43: 2858 | AA43: 3057 | AB43: 1939 | AC43: 2566 | AD43: 3865 | AE43: 3875 | AF43: 4010 | AH43: 11085 | AI43: 15182 | AJ43: 135 | AK43: 119 | AL43: 1730 | AM43: 14 | AN43: 1720 | AO43: 20713 | AP43: 268 | AQ43: 1789 | AR43: 49 | AS43: 19574 | AT43: 2363 | AU43: 203 | AV43: 253 | AW43: 28 | BA43: 1 | BB43: 6 | BC43: 3974 | BE43: 18733 | BF43: 33 | BG43: 7636 | BI43: 118627 | BJ43: 18760 | BK43: 644 | BL43: 3024 | BM43: 3974 | BP43: 17539 | BQ43: 290 | BR43: 226 | BS43: 1759 | BT43: 168 | BU43: 2 | BV43: 838 | BW43: 747 | BX43: 4020 | BZ43: 353 | CA43: 425 | CB43: 22 | CD43: 6 | CE43: 7 | CG43: 2402 | CH43: 24000 | CJ43: 10678 | CK43: 10667 | CL43: 4536 | CM43: 7 | CO43: 214 | CQ43: 174 | CR43: 126 | CT43: 2160 | CU43: 801 | CV43: 131 | CW43: 1397 | CX43: 379 | CY43: 527 | CZ43: 18 | DA43: 16 | DB43: 3833 | DC43: 1583 | DD43: 2580 | DE43: 426 | DF43: 522 | DG43: 1665 | DH43: 4318 | DI43: 3974 | DJ43: 18 | DK43: 489 | DL43: 1480 | DM43: 84 | DN43: 1 | DO43: 3070 | DP43: 3964 | DQ43: 2393 | DR43: 2587 | DS43: 6 | DT43: 12 | DU43: 2 | DV43: 344 | DW43: 70 | DX43: 543 | DY43: 1184 | DZ43: 108 | EA43: 81 | EB43: 466 | EC43: 412 | ED43: 10788 | EE43: 372 | EF43: 9 | EG43: 475 | EH43: 4 | EI43: 119 | EJ43: 25795
A44: 106104023 | B44: 104023 | C44: FRESNO | D44: SAN JOAQUIN VALLEY REHABILITATION HOSPITAL | E44: 7173 N SHARON AVE | F44: FRESNO | G44: 93720 | H44: Investor - Limited Liability Company | I44: Small/Rural | J44: 50-99 | K44: District 8 | L44: District 23 | M44: Fresno Northwest | N44: Urban | O44: 1393 | U44: 623 | V44: 770 | Z44: 14 | AA44: 26 | AB44: 46 | AC44: 121 | AD44: 293 | AE44: 457 | AF44: 436 | AH44: 243 | AI44: 1128 | AJ44: 22 | AL44: 70 | AN44: 56 | AO44: 1237 | AP44: 30 | AS44: 11 | AU44: 1368 | AV44: 14 | BF44: 657 | BG44: 736 | BI44: 17127 | BJ44: 1 | BL44: 1392 | BP44: 645 | BQ44: 177 | BS44: 96 | BT44: 1 | BW44: 4 | BX44: 466 | CA44: 3 | CE44: 1 | CG44: 13 | CH44: 1380 | CJ44: 1006 | CK44: 134 | CL44: 200 | CM44: 19 | CO44: 7 | CQ44: 2 | CR44: 25 | CT44: 1 | CU44: 11 | CW44: 8 | CY44: 333 | DA44: 2 | DB44: 218 | DC44: 3 | DD44: 4 | DE44: 3 | DF44: 155 | DG44: 3 | DJ44: 1 | DK44: 51 | DL44: 364 | DM44: 236 | DO44: 11 | DQ44: 44 | DR44: 3 | ED44: 1335 | EF44: 1 | EI44: 9 | EJ44: 1383
A45: 106104047 | B45: 104047 | C45: FRESNO | D45: FRESNO SURGICAL HOSPITAL | E45: 6125 N FRESNO ST | F45: FRESNO | G45: 93710 | H45: Investor - Partnership | I45: Small/Rural | J45: 1-49 | K45: District 8 | L45: District 23 | M45: Fresno North Central | N45: Urban | O45: 921 | U45: 429 | V45: 492 | AA45: 31 | AB45: 67 | AC45: 143 | AD45: 302 | AE45: 308 | AF45: 65 | AG45: 5 | AH45: 246 | AI45: 675 | AL45: 15 | AN45: 28 | AO45: 845 | AP45: 3 | AQ45: 30 | AS45: 915 | AU45: 3 | AV45: 1 | BB45: 2 | BG45: 921 | BI45: 1839 | BK45: 4 | BL45: 917 | BP45: 815 | BQ45: 7 | BR45: 46 | BS45: 21 | BX45: 32 | CG45: 57 | CH45: 864 | CJ45: 525 | CK45: 51 | CL45: 177 | CM45: 143 | CO45: 23 | CQ45: 2 | CU45: 5 | DF45: 722 | DG45: 24 | DL45: 169 | DM45: 1 | DV45: 11 | DX45: 10 | DY45: 881 | DZ45: 2 | EC45: 15 | ED45: 2 | EI45: 3 | EJ45: 918
A46: 106104062 | B46: 104062 | C46: FRESNO | D46: KAISER FOUNDATION HOSPITAL - FRESNO | E46: 7300 N FRESNO ST | F46: FRESNO | G46: 93720 | H46: Non-profit Corporation (incl. Church-related) | I46: Small/Rural | J46: 150-199 | K46: District 8 | L46: District 23 | M46: Fresno North Central | N46: Urban | O46: 10025 | U46: 3807 | V46: 6218 | X46: 1842 | Y46: 50 | Z46: 947 | AA46: 1332 | AB46: 549 | AC46: 668 | AD46: 1289 | AE46: 1603 | AF46: 1745 | AH46: 3753 | AI46: 6242 | AJ46: 30 | AK46: 63 | AL46: 998 | AM46: 16 | AN46: 618 | AO46: 4609 | AP46: 85 | AQ46: 3557 | AR46: 79 | AS46: 7686 | AT46: 135 | AU46: 161 | AV46: 207 | AW46: 53 | AX46: 1 | BB46: 6 | BC46: 1776 | BE46: 5634 | BF46: 36 | BG46: 4355 | BI46: 35419 | BJ46: 366 | BK46: 7254 | BL46: 626 | BM46: 1776 | BO46: 3 | BP46: 6573 | BQ46: 160 | BR46: 28 | BS46: 634 | BV46: 53 | BW46: 295 | BX46: 1973 | BZ46: 11 | CA46: 265 | CB46: 19 | CD46: 4 | CE46: 10 | CG46: 918 | CH46: 9107 | CJ46: 4228 | CK46: 171 | CL46: 5551 | CM46: 10 | CO46: 4 | CQ46: 61 | CT46: 1447 | CU46: 147 | CV46: 68 | CW46: 506 | CX46: 57 | CY46: 185 | CZ46: 1 | DA46: 2 | DB46: 1158 | DC46: 514 | DD46: 897 | DE46: 65 | DF46: 173 | DG46: 390 | DH46: 1866 | DI46: 1841 | DJ46: 1 | DK46: 204 | DL46: 487 | DM46: 16 | DO46: 3626 | DP46: 1768 | DQ46: 487 | DR46: 970 | DS46: 10 | DT46: 2 | DV46: 179 | DW46: 8 | DX46: 144 | DY46: 469 | DZ46: 139 | EA46: 25 | EB46: 224 | EC46: 287 | ED46: 1518 | EE46: 169 | EF46: 2 | EG46: 21 | EI46: 18 | EJ46: 9984
A47: 106104089 | B47: 104089 | C47: FRESNO | D47: EXODUS PSYCHIATRIC HEALTH FACILITY FRESNO | E47: 4411 E KINGS CANYON RD | F47: FRESNO | G47: 93702 | H47: Investor - Corporation | I47: Small/Rural | J47: 1-49 | K47: District 14 | L47: District 31 | M47: Fresno East Central | N47: Urban | Q47: 210 | U47: 139 | V47: 71 | Z47: 63 | AA47: 68 | AB47: 42 | AC47: 24 | AG47: 13 | AH47: 87 | AI47: 104 | AJ47: 19 | AN47: 42 | AO47: 129 | AP47: 19 | AQ47: 20 | AU47: 20 | AW47: 170 | BA47: 20 | BF47: 20 | BG47: 190 | BI47: 5645 | BK47: 210 | BP47: 190 | BQ47: 4 | BU47: 10 | CD47: 6 | CH47: 210 | CK47: 187 | CN47: 23 | CX47: 210 | ED47: 210 | EG47: 22 | EJ47: 188
A48: 106105125 | B48: 105125 | C48: FRESNO | D48: CENTRAL STAR PSYCHIATRIC HEALTH FACILITY | E48: 4411 E KINGS CANYON RD | F48: FRESNO | G48: 93702 | H48: Investor - Corporation | I48: Small/Rural | J48: 1-49 | K48: District 14 | L48: District 31 | M48: Fresno East Central | N48: Urban | Q48: 426 | U48: 144 | V48: 282 | Y48: 426 | AH48: 230 | AI48: 186 | AJ48: 10 | AL48: 12 | AN48: 30 | AO48: 134 | AP48: 9 | AQ48: 190 | AR48: 51 | AU48: 237 | AW48: 189 | BF48: 117 | BG48: 309 | BI48: 3830 | BK48: 426 | BP48: 422 | BQ48: 4 | CH48: 426 | CK48: 337 | CL48: 87 | CR48: 2 | CX48: 237 | DM48: 188 | DN48: 1 | DO48: 426 | EF48: 1 | EG48: 1 | EJ48: 424
A49: 106110889 | B49: 110889 | C49: GLENN | D49: GLENN MEDICAL CENTER | E49: 1133 W SYCAMORE ST | F49: WILLOWS | G49: 95988 | H49: Investor - Limited Liability Company | I49: Small/Rural | J49: 1-49 | K49: District 4 | L49: District 3 | M49: Artois/Elk Creek/Glenn/Grindstone Indian Rancheria/Willows | N49: Frontier | O49: 220 | P49: 246 | U49: 213 | V49: 253 | AB49: 11 | AC49: 24 | AD49: 99 | AE49: 174 | AF49: 145 | AG49: 13 | AH49: 34 | AI49: 431 | AJ49: 1 | AM49: 11 | AO49: 407 | AP49: 16 | AQ49: 32 | AS49: 216 | AU49: 162 | AX49: 88 | BE49: 220 | BG49: 246 | BI49: 7397 | BJ49: 220 | BL49: 246 | BP49: 208 | BQ49: 36 | BS49: 133 | BT49: 9 | BV49: 28 | BW49: 43 | BX49: 3 | CB49: 1 | CC49: 1 | CD49: 3 | CE49: 1 | CG49: 57 | CH49: 409 | CJ49: 341 | CK49: 98 | CL49: 27 | CT49: 107 | CU49: 4 | CV49: 5 | CW49: 12 | CX49: 3 | CY49: 11 | DB49: 38 | DC49: 62 | DD49: 22 | DE49: 27 | DF49: 5 | DG49: 38 | DK49: 71 | DL49: 23 | DM49: 38 | DO49: 3 | DR49: 1 | DX49: 2 | ED49: 460 | EG49: 16 | EI49: 3 | EJ49: 447
A50: 106121002 | B50: 121002 | C50: HUMBOLDT | D50: MAD RIVER COMMUNITY HOSPITAL | E50: 3800 JANES RD | F50: ARCATA | G50: 95521 | H50: Investor - Corporation | I50: Small/Rural | J50: 50-99 | K50: District 2 | L50: District 2 | M50: Arcata/Eureka | N50: Rural | O50: 1636 | P50: 11 | U50: 607 | V50: 1040 | X50: 415 | Y50: 28 | Z50: 176 | AA50: 276 | AB50: 112 | AC50: 93 | AD50: 176 | AE50: 191 | AF50: 180 | AH50: 201 | AI50: 1410 | AJ50: 36 | AK50: 208 | AL50: 21 | AN50: 23 | AO50: 1263 | AP50: 8 | AQ50: 68 | AR50: 56 | AS50: 1219 | AT50: 1 | AU50: 3 | AV50: 1 | AW50: 1 | AX50: 11 | BA50: 1 | BB50: 12 | BC50: 398 | BE50: 1181 | BG50: 466 | BI50: 5750 | BJ50: 775 | BK50: 3 | BL50: 471 | BM50: 398 | BP50: 1395 | BQ50: 40 | BR50: 11 | BS50: 68 | BT50: 14 | BV50: 38 | BW50: 45 | BX50: 21 | BZ50: 1 | CA50: 10 | CC50: 3 | CD50: 1 | CG50: 132 | CH50: 1515 | CJ50: 500 | CK50: 727 | CL50: 364 | CM50: 1 | CO50: 42 | CQ50: 8 | CS50: 5 | CT50: 159 | CU50: 19 | CV50: 9 | CW50: 63 | CX50: 38 | CY50: 24 | DB50: 83 | DC50: 116 | DD50: 119 | DE50: 29 | DF50: 26 | DG50: 35 | DH50: 405 | DI50: 405 | DK50: 9 | DL50: 103 | DM50: 5 | DO50: 74 | DP50: 397 | DQ50: 24 | DR50: 82 | DV50: 19 | DX50: 26 | DY50: 111 | DZ50: 2 | EA50: 13 | EB50: 15 | EC50: 1 | ED50: 851 | EE50: 32 | EG50: 27 | EI50: 16 | EJ50: 1604
A51: 106121031 | B51: 121031 | C51: HUMBOLDT | D51: JEROLD PHELPS COMMUNITY HOSPITAL | E51: 733 CEDAR ST | F51: GARBERVILLE | G51: 95542 | H51: District | I51: Small/Rural | J51: 1-49 | K51: District 2 | L51: District 2 | M51: Garberville/Redway | N51: Frontier | O51: 35 | P51: 38 | U51: 47 | V51: 26 | AD51: 20 | AE51: 29 | AF51: 19 | AG51: 5 | AI51: 61 | AJ51: 12 | AO51: 63 | AP51: 10 | AS51: 31 | AT51: 2 | AU51: 16 | AV51: 1 | AW51: 2 | AX51: 21 | BE51: 33 | BF51: 2 | BG51: 38 | BI51: 1043 | BJ51: 36 | BL51: 37 | BP51: 28 | BQ51: 15 | BS51: 24 | BV51: 3 | BW51: 3 | CG51: 26 | CH51: 47 | CJ51: 54 | CK51: 17 | CL51: 1 | CO51: 1 | CT51: 7 | CU51: 1 | CV51: 1 | CW51: 1 | CX51: 2 | CY51: 3 | DB51: 6 | DC51: 8 | DD51: 8 | DE51: 6 | DF51: 3 | DG51: 3 | DK51: 7 | DL51: 13 | DM51: 4 | DO51: 1 | ED51: 72 | EG51: 5 | EJ51: 68
A52: 106121051 | B52: 121051 | C52: HUMBOLDT | D52: PROVIDENCE REDWOOD MEMORIAL HOSPITAL | E52: 3300 RENNER DR | F52: FORTUNA | G52: 95540 | H52: Investor - Limited Liability Company | I52: Small/Rural | J52: 1-49 | K52: District 2 | L52: District 2 | M52: Ferndale/Fortuna/Rio Dell/Scotia | N52: Rural | O52: 697 | P52: 38 | U52: 348 | V52: 387 | Z52: 20 | AA52: 49 | AB52: 66 | AC52: 89 | AD52: 148 | AE52: 156 | AF52: 202 | AG52: 5 | AH52: 22 | AI52: 688 | AJ52: 25 | AK52: 17 | AO52: 670 | AP52: 21 | AQ52: 27 | AS52: 588 | AT52: 4 | AU52: 93 | AV52: 7 | AW52: 1 | AX52: 42 | BE52: 580 | BF52: 59 | BG52: 96 | BI52: 4354 | BJ52: 571 | BK52: 115 | BL52: 48 | BO52: 1 | BP52: 435 | BQ52: 53 | BR52: 11 | BS52: 120 | BT52: 2 | BV52: 27 | BW52: 35 | BX52: 32 | CA52: 17 | CB52: 1 | CC52: 2 | CG52: 225 | CH52: 510 | CJ52: 475 | CK52: 153 | CL52: 76 | CO52: 23 | CQ52: 8 | CT52: 190 | CU52: 12 | CV52: 4 | CW52: 70 | CX52: 17 | CY52: 13 | DA52: 1 | DB52: 68 | DC52: 69 | DD52: 142 | DE52: 36 | DF52: 16 | DG52: 27 | DK52: 19 | DL52: 32 | DM52: 18 | DN52: 1 | DO52: 107 | DQ52: 26 | DR52: 113 | DS52: 1 | DT52: 1 | DX52: 19 | DY52: 15 | DZ52: 2 | EA52: 3 | EB52: 9 | EC52: 1 | ED52: 372 | EE52: 66 | EG52: 44 | EI52: 8 | EJ52: 683
A53: 106121080 | B53: 121080 | C53: HUMBOLDT | D53: PROVIDENCE ST. JOSEPH HOSPITAL - EUREKA | E53: 2700 DOLBEER ST | F53: EUREKA | G53: 95501 | H53: Investor - Limited Liability Company | I53: Small/Rural | J53: 100-149 | K53: District 2 | L53: District 2 | M53: Arcata/Eureka | N53: Rural | O53: 6951 | S53: 257 | U53: 3430 | V53: 3778 | X53: 784 | Y53: 68 | Z53: 573 | AA53: 732 | AB53: 532 | AC53: 760 | AD53: 1358 | AE53: 1378 | AF53: 1023 | AH53: 452 | AI53: 6136 | AJ53: 620 | AK53: 363 | AL53: 132 | AM53: 25 | AN53: 100 | AO53: 5470 | AP53: 527 | AQ53: 490 | AR53: 101 | AS53: 5765 | AT53: 84 | AU53: 369 | AV53: 49 | AW53: 72 | AX53: 125 | AY53: 2 | BA53: 6 | BB53: 1 | BC53: 735 | BE53: 4545 | BF53: 127 | BG53: 2536 | BI53: 38415 | BJ53: 4422 | BK53: 539 | BL53: 1367 | BM53: 735 | BN53: 124 | BO53: 21 | BP53: 5022 | BQ53: 242 | BR53: 238 | BS53: 463 | BT53: 24 | BU53: 18 | BV53: 270 | BW53: 238 | BX53: 452 | BZ53: 15 | CA53: 184 | CB53: 30 | CC53: 4 | CD53: 7 | CF53: 1 | CG53: 900 | CH53: 6308 | CJ53: 3282 | CK53: 2309 | CL53: 1259 | CM53: 21 | CO53: 263 | CQ53: 74 | CT53: 935 | CU53: 198 | CV53: 29 | CW53: 200 | CX53: 129 | CY53: 118 | CZ53: 2 | DA53: 4 | DB53: 1200 | DC53: 361 | DD53: 668 | DE53: 154 | DF53: 325 | DG53: 289 | DH53: 807 | DI53: 762 | DJ53: 4 | DK53: 95 | DL53: 846 | DM53: 82 | DO53: 1549 | DP53: 729 | DQ53: 818 | DR53: 595 | DS53: 1 | DT53: 7 | DV53: 64 | DW53: 14 | DX53: 182 | DY53: 629 | DZ53: 89 | EA53: 18 | EB53: 137 | EC53: 102 | ED53: 2112 | EE53: 162 | EG53: 400 | EI53: 62 | EJ53: 6746
A54: 106124004 | B54: 124004 | C54: HUMBOLDT | D54: SEMPERVIRENS P.H.F. | E54: 720 WOOD ST | F54: EUREKA | G54: 95501 | H54: City or County | I54: Small/Rural | J54: 1-49 | K54: District 2 | L54: District 2 | M54: Arcata/Eureka | N54: Rural | Q54: 299 | U54: 164 | V54: 135 | Y54: 13 | Z54: 81 | AA54: 94 | AB54: 49 | AC54: 20 | AD54: 35 | AG54: 7 | AH54: 39 | AI54: 214 | AJ54: 46 | AK54: 25 | AO54: 188 | AP54: 18 | AR54: 68 | AS54: 20 | AU54: 232 | AV54: 9 | AW54: 1 | BA54: 37 | BF54: 232 | BG54: 67 | BI54: 4311 | BJ54: 295 | BK54: 4 | BP54: 214 | BQ54: 10 | BT54: 42 | BU54: 10 | BV54: 23 | CH54: 299 | CJ54: 91 | CK54: 164 | CL54: 25 | CN54: 7 | CO54: 2 | CQ54: 10 | CX54: 298 | DN54: 1 | DO54: 299 | EG54: 83 | EI54: 3 | EJ54: 213
A55: 106130699 | B55: 130699 | C55: IMPERIAL | D55: EL CENTRO REGIONAL MEDICAL CENTER | E55: 1415 ROSS AVE | F55: EL CENTRO | G55: 92243 | H55: City or County | I55: Small/Rural | J55: 150-199 | K55: District 40 | L55: District 56 | M55: El Centro/Heber/Holtville/Imperial/Seeley | N55: Rural | O55: 5121 | U55: 2390 | V55: 2731 | X55: 795 | Y55: 68 | Z55: 514 | AA55: 537 | AB55: 317 | AC55: 419 | AD55: 888 | AE55: 742 | AF55: 841 | AH55: 4536 | AI55: 566 | AJ55: 19 | AL55: 38 | AN55: 67 | AO55: 2937 | AP55: 45 | AQ55: 1963 | AR55: 71 | AS55: 3682 | AT55: 554 | AU55: 20 | AV55: 85 | BA55: 16 | BC55: 764 | BE55: 3483 | BG55: 1638 | BI55: 24947 | BJ55: 1173 | BK55: 2308 | BL55: 876 | BM55: 764 | BP55: 3160 | BQ55: 176 | BR55: 6 | BS55: 422 | BT55: 15 | BU55: 40 | BV55: 148 | BW55: 277 | BX55: 771 | BZ55: 29 | CA55: 76 | CB55: 1 | CG55: 217 | CH55: 4904 | CJ55: 2225 | CK55: 1693 | CL55: 662 | CM55: 11 | CN55: 1 | CO55: 72 | CP55: 32 | CQ55: 425 | CT55: 694 | CU55: 109 | CV55: 54 | CW55: 287 | CX55: 34 | CY55: 84 | CZ55: 3 | DA55: 1 | DB55: 527 | DC55: 376 | DD55: 699 | DE55: 110 | DF55: 65 | DG55: 346 | DH55: 808 | DI55: 771 | DJ55: 2 | DK55: 29 | DL55: 110 | DM55: 12 | DO55: 221 | DP55: 757 | DQ55: 255 | DR55: 603 | DS55: 1 | DT55: 2 | DV55: 22 | DW55: 12 | DX55: 62 | DY55: 132 | DZ55: 28 | EA55: 15 | EB55: 102 | EC55: 83 | ED55: 2737 | EE55: 89 | EF55: 3 | EG55: 124 | EH55: 98 | EI55: 129 | EJ55: 4767
A56: 106130760 | B56: 130760 | C56: IMPERIAL | D56: PIONEERS MEMORIAL HEALTHCARE DISTRICT | E56: 207 W LEGION RD | F56: BRAWLEY | G56: 92227 | H56: District | I56: Small/Rural | J56: 100-149 | K56: District 40 | L56: District 56 | M56: Brawley/Westmorland | N56: Rural | O56: 5965 | U56: 2139 | V56: 3826 | X56: 1980 | Y56: 103 | Z56: 1091 | AA56: 929 | AB56: 235 | AC56: 339 | AD56: 476 | AE56: 398 | AF56: 414 | AH56: 5233 | AI56: 717 | AJ56: 15 | AL56: 14 | AN56: 56 | AO56: 5823 | AP56: 17 | AQ56: 55 | AS56: 4128 | AT56: 1 | AU56: 9 | AV56: 15 | BA56: 25 | BC56: 1787 | BE56: 3904 | BG56: 2061 | BI56: 19259 | BJ56: 1513 | BK56: 1847 | BL56: 818 | BM56: 1787 | BP56: 4993 | BQ56: 170 | BR56: 15 | BS56: 226 | BT56: 5 | BU56: 41 | BV56: 134 | BW56: 120 | BX56: 204 | BZ56: 5 | CA56: 43 | CB56: 2 | CC56: 1 | CD56: 5 | CE56: 1 | CG56: 91 | CH56: 5874 | CJ56: 1144 | CK56: 2965 | CL56: 1168 | CM56: 5 | CN56: 2 | CO56: 90 | CP56: 3 | CQ56: 588 | CT56: 486 | CU56: 25 | CV56: 8 | CW56: 171 | CX56: 10 | CY56: 57 | CZ56: 2 | DA56: 2 | DB56: 306 | DC56: 311 | DD56: 338 | DE56: 94 | DF56: 102 | DG56: 187 | DH56: 1877 | DI56: 1826 | DK56: 19 | DL56: 140 | DM56: 3 | DN56: 1 | DO56: 440 | DP56: 1774 | DQ56: 145 | DR56: 227 | DV56: 23 | DW56: 1 | DX56: 64 | DY56: 129 | DZ56: 32 | EA56: 16 | EB56: 41 | EC56: 46 | ED56: 2947 | EE56: 80 | EF56: 4 | EG56: 40 | EH56: 383 | EI56: 51 | EJ56: 5487
A57: 106141273 | B57: 141273 | C57: INYO | D57: NORTHERN INYO HOSPITAL | E57: 150 PIONEER LN | F57: BISHOP | G57: 93514 | H57: District | I57: Small/Rural | J57: 1-49 | K57: District 8 | L57: District 26 | M57: Bishop/Bishop Paiute Tribe/Mustang Mesa/Round Valley/West Bishop/Wilkerson | N57: Rural | O57: 1001 | P57: 8 | U57: 436 | V57: 573 | X57: 254 | Y57: 18 | Z57: 105 | AA57: 139 | AB57: 45 | AC57: 48 | AD57: 112 | AE57: 130 | AF57: 158 | AH57: 173 | AI57: 738 | AJ57: 98 | AK57: 118 | AO57: 709 | AP57: 80 | AQ57: 81 | AR57: 21 | AS57: 662 | AT57: 103 | AU57: 16 | AV57: 1 | AW57: 4 | BB57: 13 | BC57: 210 | BE57: 561 | BG57: 448 | BI57: 2919 | BJ57: 72 | BK57: 487 | BL57: 239 | BM57: 210 | BN57: 1 | BP57: 800 | BQ57: 54 | BR57: 5 | BS57: 83 | BV57: 6 | BW57: 27 | BX57: 26 | CA57: 7 | CB57: 1 | CG57: 135 | CH57: 874 | CJ57: 325 | CK57: 339 | CL57: 317 | CM57: 4 | CO57: 2 | CQ57: 21 | CR57: 1 | CT57: 109 | CU57: 11 | CV57: 3 | CW57: 52 | CX57: 14 | CY57: 9 | CZ57: 1 | DA57: 2 | DB57: 55 | DC57: 59 | DD57: 99 | DE57: 19 | DF57: 23 | DG57: 22 | DH57: 213 | DI57: 221 | DK57: 30 | DL57: 65 | DM57: 2 | DO57: 220 | DP57: 182 | DQ57: 5 | DR57: 64 | DV57: 8 | DX57: 27 | DY57: 65 | DZ57: 3 | EA57: 8 | EB57: 3 | EC57: 1 | ED57: 418 | EE57: 5 | EG57: 8 | EI57: 44 | EJ57: 957
A58: 106141338 | B58: 141338 | C58: INYO | D58: SOUTHERN INYO HOSPITAL | E58: 501 E LOCUST ST | F58: LONE PINE | G58: 93545 | H58: District | I58: Small/Rural | J58: 1-49 | K58: District 8 | L58: District 26 | M58: Alabama Hills/Cartago/Darwin/Keeler/Lone Pine/Lone Pine Paiute Shoshone Tribe/Olancha/Pearsonville | N58: Frontier | P58: 10 | U58: 4 | V58: 6 | AG58: 10 | AJ58: 10 | AP58: 10 | AT58: 3 | AU58: 5 | AX58: 2 | BE58: 2 | BG58: 8 | BI58: 422 | BJ58: 1 | BK58: 1 | BL58: 8 | BP58: 6 | BS58: 3 | BW58: 1 | CG58: 6 | CH58: 4 | CJ58: 8 | CK58: 1 | CL58: 1 | CU58: 1 | CX58: 1 | DB58: 1 | DF58: 3 | DG58: 1 | DL58: 3 | DO58: 10 | EJ58: 10
A59: 106150706 | B59: 150706 | C59: KERN | D59: ADVENTIST HEALTH DELANO | E59: 1401 GARCES HWY | F59: DELANO | G59: 93215 | H59: Non-profit Corporation (incl. Church-related) | I59: Small/Rural | J59: 150-199 | K59: District 14 | L59: District 32 | M59: Delano/McFarland | N59: Urban | O59: 2704 | P59: 20 | U59: 1038 | V59: 1686 | X59: 632 | Y59: 64 | Z59: 459 | AA59: 373 | AB59: 192 | AC59: 233 | AD59: 305 | AE59: 224 | AF59: 242 | AH59: 2139 | AI59: 552 | AJ59: 33 | AL59: 187 | AN59: 45 | AO59: 1072 | AP59: 57 | AQ59: 1318 | AR59: 45 | AS59: 2030 | AT59: 3 | AU59: 15 | AV59: 17 | AX59: 12 | BA59: 32 | BB59: 4 | BC59: 611 | BE59: 1293 | BG59: 1428 | BH59: 3 | BI59: 24759 | BJ59: 1220 | BK59: 255 | BL59: 633 | BM59: 611 | BO59: 5 | BP59: 2259 | BQ59: 87 | BR59: 13 | BS59: 154 | BT59: 11 | BU59: 36 | BV59: 53 | BW59: 68 | BX59: 16 | BZ59: 2 | CA59: 20 | CB59: 1 | CD59: 1 | CF59: 3 | CG59: 1407 | CH59: 1317 | CJ59: 552 | CK59: 1862 | CL59: 220 | CM59: 1 | CO59: 42 | CQ59: 40 | CR59: 7 | CT59: 365 | CU59: 34 | CV59: 13 | CW59: 173 | CX59: 21 | CY59: 21 | DB59: 142 | DC59: 141 | DD59: 234 | DE59: 34 | DF59: 64 | DG59: 99 | DH59: 648 | DI59: 618 | DJ59: 1 | DK59: 24 | DL59: 89 | DM59: 3 | DO59: 1278 | DP59: 610 | DQ59: 119 | DR59: 169 | DV59: 35 | DX59: 32 | DY59: 106 | DZ59: 9 | EA59: 2 | EB59: 26 | ED59: 325 | EE59: 13 | EF59: 2 | EG59: 17 | EI59: 9 | EJ59: 2696
A60: 106150722 | B60: 150722 | C60: KERN | D60: BAKERSFIELD MEMORIAL HOSPITAL | E60: 420 34TH ST | F60: BAKERSFIELD | G60: 93301 | H60: Non-profit Corporation (incl. Church-related) | I60: Small/Rural | J60: 300-499 | K60: District 16 | L60: District 34 | M60: Bakersfield Northeast/Oildale | N60: Urban | O60: 19545 | U60: 8077 | V60: 11468 | X60: 4820 | Y60: 685 | Z60: 2582 | AA60: 2084 | AB60: 1170 | AC60: 1844 | AD60: 2560 | AE60: 2190 | AF60: 1610 | AH60: 10242 | AI60: 9200 | AJ60: 103 | AK60: 130 | AL60: 496 | AM60: 29 | AN60: 1214 | AO60: 14386 | AP60: 431 | AQ60: 2844 | AR60: 15 | AS60: 11574 | AT60: 3033 | AU60: 1016 | AV60: 213 | AW60: 11 | AX60: 1 | BA60: 2 | BC60: 3695 | BE60: 11557 | BF60: 55 | BG60: 7933 | BI60: 77549 | BJ60: 9856 | BK60: 3357 | BL60: 2616 | BM60: 3695 | BN60: 21 | BP60: 15155 | BQ60: 211 | BR60: 327 | BS60: 1230 | BT60: 118 | BU60: 14 | BV60: 360 | BW60: 541 | BX60: 1261 | BZ60: 41 | CA60: 270 | CB60: 7 | CD60: 10 | CG60: 339 | CH60: 19206 | CJ60: 5516 | CK60: 10446 | CL60: 3240 | CM60: 99 | CO60: 122 | CQ60: 117 | CR60: 5 | CT60: 2311 | CU60: 330 | CV60: 71 | CW60: 775 | CX60: 82 | CY60: 450 | CZ60: 9 | DA60: 4 | DB60: 2502 | DC60: 972 | DD60: 1447 | DE60: 159 | DF60: 604 | DG60: 676 | DH60: 3869 | DI60: 3912 | DJ60: 15 | DK60: 167 | DL60: 1158 | DM60: 32 | DO60: 2451 | DP60: 3605 | DQ60: 2028 | DR60: 1385 | DT60: 14 | DU60: 1 | DV60: 206 | DW60: 7 | DX60: 409 | DY60: 989 | DZ60: 425 | EA60: 6 | EB60: 207 | EC60: 195 | ED60: 7393 | EE60: 224 | EF60: 5 | EG60: 351 | EH60: 3 | EI60: 53 | EJ60: 19133
A61: 106150736 | B61: 150736 | C61: KERN | D61: KERN MEDICAL CENTER | E61: 1700 MOUNT VERNON AVENUE | F61: BAKERSFIELD | G61: 93306 | H61: City or County | I61: Teaching | J61: 200-299 | K61: District 16 | L61: District 32 | M61: Bakersfield Northeast/Oildale | N61: Urban | O61: 11861 | Q61: 670 | U61: 5699 | V61: 6831 | W61: 1 | X61: 2754 | Y61: 485 | Z61: 2233 | AA61: 2176 | AB61: 1270 | AC61: 1419 | AD61: 1290 | AE61: 617 | AF61: 287 | AH61: 7985 | AI61: 4478 | AJ61: 68 | AK61: 27 | AL61: 230 | AM61: 22 | AN61: 1068 | AO61: 10980 | AP61: 44 | AQ61: 113 | AR61: 47 | AS61: 8105 | AT61: 1648 | AU61: 189 | AV61: 8 | AW61: 30 | AY61: 1 | BA61: 120 | BC61: 2430 | BE61: 8038 | BG61: 4493 | BI61: 64176 | BJ61: 5317 | BK61: 2396 | BL61: 1482 | BM61: 2430 | BN61: 904 | BO61: 2 | BP61: 9718 | BQ61: 189 | BR61: 385 | BS61: 452 | BU61: 205 | BV61: 606 | BW61: 213 | BX61: 412 | BY61: 1 | BZ61: 52 | CA61: 119 | CB61: 169 | CD61: 6 | CE61: 4 | CG61: 10386 | CH61: 2145 | CJ61: 1645 | CK61: 9361 | CL61: 987 | CM61: 37 | CO61: 81 | CQ61: 338 | CR61: 82 | CT61: 561 | CU61: 300 | CV61: 105 | CW61: 388 | CX61: 899 | CY61: 355 | CZ61: 8 | DA61: 14 | DB61: 690 | DC61: 337 | DD61: 756 | DE61: 231 | DF61: 292 | DG61: 430 | DH61: 2619 | DI61: 2567 | DJ61: 13 | DK61: 137 | DL61: 1795 | DM61: 32 | DN61: 2 | DO61: 3970 | DP61: 2499 | DQ61: 419 | DR61: 613 | DS61: 9 | DT61: 6 | DU61: 3 | DV61: 205 | DW61: 25 | DX61: 292 | DY61: 946 | DZ61: 236 | EA61: 48 | EB61: 231 | EC61: 179 | ED61: 2738 | EE61: 112 | EF61: 1 | EG61: 268 | EI61: 46 | EJ61: 12216
A62: 106150737 | B62: 150737 | C62: KERN | D62: KERN VALLEY HEALTHCARE DISTRICT | E62: 6412 LAUREL AVE | F62: LAKE ISABELLA | G62: 93240 | H62: District | I62: Small/Rural | J62: 100-149 | K62: District 16 | L62: District 26 | M62: Alta Sierra/Bodfish/Glennville/Kernville/Lake Isabella/Weldon/Wofford Heights | N62: Frontier | O62: 300 | P62: 64 | U62: 173 | V62: 191 | AA62: 18 | AB62: 18 | AC62: 44 | AD62: 85 | AE62: 63 | AF62: 130 | AG62: 6 | AH62: 22 | AI62: 330 | AJ62: 12 | AO62: 335 | AP62: 17 | AQ62: 12 | AS62: 333 | AU62: 1 | AX62: 30 | BE62: 291 | BG62: 73 | BI62: 11060 | BJ62: 307 | BK62: 17 | BL62: 40 | BP62: 227 | BQ62: 17 | BR62: 1 | BS62: 51 | BV62: 28 | BW62: 27 | BX62: 2 | CA62: 9 | CC62: 1 | CF62: 1 | CG62: 122 | CH62: 242 | CJ62: 210 | CK62: 102 | CL62: 30 | CO62: 2 | CQ62: 20 | CT62: 47 | CU62: 8 | CV62: 3 | CW62: 25 | CX62: 6 | CY62: 11 | DB62: 36 | DC62: 115 | DD62: 39 | DE62: 22 | DF62: 7 | DG62: 28 | DK62: 4 | DL62: 13 | DO62: 285 | DR62: 1 | DY62: 1 | EB62: 7 | ED62: 41 | EE62: 29 | EI62: 3 | EJ62: 361
A63: 106150761 | B63: 150761 | C63: KERN | D63: MERCY HOSPITAL - BAKERSFIELD | E63: 2215 TRUXTUN AVE | F63: BAKERSFIELD | G63: 93301 | H63: Non-profit Corporation (incl. Church-related) | I63: Small/Rural | J63: 100-149 | K63: District 16 | L63: District 34 | M63: Bakersfield Northwest/Rosedale | N63: Urban | O63: 12975 | U63: 5073 | V63: 7900 | W63: 2 | X63: 2359 | Y63: 172 | Z63: 1671 | AA63: 2024 | AB63: 1207 | AC63: 1376 | AD63: 1741 | AE63: 1336 | AF63: 1089 | AH63: 5770 | AI63: 7163 | AJ63: 42 | AK63: 47 | AL63: 510 | AM63: 17 | AN63: 802 | AO63: 8426 | AP63: 258 | AQ63: 2892 | AR63: 23 | AS63: 8714 | AT63: 1685 | AU63: 183 | AV63: 21 | AW63: 5 | BA63: 2 | BB63: 7 | BC63: 2358 | BE63: 6384 | BF63: 12 | BG63: 6579 | BI63: 47509 | BJ63: 5203 | BK63: 3970 | BL63: 1408 | BM63: 2358 | BN63: 36 | BP63: 9910 | BQ63: 251 | BR63: 158 | BS63: 729 | BT63: 18 | BU63: 16 | BV63: 358 | BW63: 304 | BX63: 1022 | BZ63: 6 | CA63: 173 | CB63: 9 | CD63: 21 | CG63: 280 | CH63: 12695 | CJ63: 3457 | CK63: 4623 | CL63: 4583 | CM63: 19 | CO63: 154 | CQ63: 138 | CR63: 1 | CT63: 1583 | CU63: 341 | CV63: 42 | CW63: 843 | CX63: 100 | CY63: 217 | CZ63: 3 | DA63: 6 | DB63: 859 | DC63: 662 | DD63: 1470 | DE63: 154 | DF63: 346 | DG63: 707 | DH63: 2542 | DI63: 2359 | DJ63: 3 | DK63: 95 | DL63: 623 | DM63: 20 | DO63: 1692 | DP63: 2254 | DQ63: 693 | DR63: 1465 | DT63: 2 | DV63: 202 | DW63: 18 | DX63: 161 | DY63: 607 | DZ63: 131 | EA63: 3 | EB63: 136 | EC63: 240 | ED63: 5212 | EE63: 159 | EF63: 4 | EG63: 321 | EI63: 60 | EJ63: 12590
A64: 106150775 | B64: 150775 | C64: KERN | D64: GOOD SAMARITAN HOSPITAL-BAKERSFIELD | E64: 901 OLIVE DR | F64: BAKERSFIELD | G64: 93308 | H64: Investor - Partnership | I64: Small/Rural | J64: 50-99 | K64: District 16 | L64: District 34 | M64: Bakersfield Northeast/Oildale | N64: Urban | O64: 597 | Q64: 1828 | U64: 1602 | V64: 823 | Y64: 53 | Z64: 433 | AA64: 585 | AB64: 387 | AC64: 455 | AD64: 342 | AE64: 111 | AF64: 59 | AH64: 603 | AI64: 1813 | AJ64: 9 | AL64: 36 | AN64: 167 | AO64: 2166 | AP64: 16 | AQ64: 40 | AS64: 4 | AT64: 2238 | AU64: 7 | AW64: 174 | BA64: 1 | BB64: 1 | BG64: 2425 | BI64: 11058 | BJ64: 7 | BK64: 2415 | BL64: 3 | BP64: 1938 | BQ64: 38 | BR64: 7 | BS64: 172 | BU64: 7 | BV64: 195 | BW64: 6 | BZ64: 8 | CA64: 3 | CD64: 51 | CG64: 58 | CH64: 2367 | CJ64: 521 | CK64: 1761 | CL64: 137 | CO64: 6 | CT64: 87 | CU64: 4 | CV64: 10 | CW64: 77 | CX64: 1825 | CY64: 43 | DB64: 53 | DC64: 75 | DD64: 42 | DE64: 124 | DF64: 14 | DG64: 40 | DK64: 20 | DL64: 11 | DO64: 16 | DQ64: 113 | DR64: 43 | DV64: 1 | DX64: 76 | DY64: 33 | DZ64: 3 | EA64: 1 | EB64: 8 | ED64: 2131 | EF64: 16 | EG64: 430 | EI64: 2 | EJ64: 1977
A65: 106150782 | B65: 150782 | C65: KERN | D65: RIDGECREST REGIONAL HOSPITAL | E65: 1081 N CHINA LAKE BLVD | F65: RIDGECREST | G65: 93555 | H65: Non-profit Corporation (incl. Church-related) | I65: Small/Rural | J65: 50-99 | K65: District 16 | L65: District 34 | M65: Inyokern/Ridgecrest | N65: Rural | O65: 2004 | P65: 113 | U65: 801 | V65: 1316 | X65: 445 | Y65: 32 | Z65: 284 | AA65: 237 | AB65: 116 | AC65: 174 | AD65: 259 | AE65: 260 | AF65: 310 | AH65: 310 | AI65: 1739 | AJ65: 68 | AK65: 22 | AL65: 49 | AM65: 13 | AN65: 141 | AO65: 1542 | AP65: 44 | AQ65: 306 | AS65: 1561 | AT65: 12 | AU65: 2 | AV65: 6 | AW65: 5 | AX65: 107 | AZ65: 1 | BB65: 4 | BC65: 419 | BE65: 1151 | BF65: 2 | BG65: 964 | BI65: 20912 | BJ65: 1079 | BK65: 326 | BL65: 293 | BM65: 419 | BP65: 1667 | BQ65: 95 | BR65: 10 | BS65: 102 | BT65: 10 | BV65: 56 | BW65: 83 | BX65: 80 | CA65: 11 | CB65: 1 | CC65: 2 | CG65: 336 | CH65: 1781 | CJ65: 712 | CK65: 708 | CL65: 546 | CM65: 2 | CO65: 122 | CQ65: 27 | CT65: 132 | CU65: 26 | CV65: 15 | CW65: 77 | CX65: 24 | CY65: 32 | DB65: 173 | DC65: 196 | DD65: 207 | DE65: 62 | DF65: 44 | DG65: 104 | DH65: 456 | DI65: 423 | DK65: 61 | DL65: 75 | DM65: 8 | DN65: 2 | DO65: 496 | DP65: 430 | DQ65: 19 | DR65: 143 | DS65: 1 | DV65: 20 | DW65: 1 | DX65: 20 | DY65: 162 | DZ65: 4 | EA65: 4 | EB65: 162 | EC65: 1 | ED65: 648 | EE65: 6 | EF65: 1 | EG65: 2 | EH65: 1 | EI65: 10 | EJ65: 2103
A66: 106150788 | B66: 150788 | C66: KERN | D66: ADVENTIST HEALTH BAKERSFIELD | E66: 2615 CHESTER AVE | F66: BAKERSFIELD | G66: 93301 | H66: Non-profit Corporation (incl. Church-related) | I66: Small/Rural | J66: 200-299 | K66: District 16 | L66: District 34 | M66: Bakersfield Northeast/Oildale | N66: Urban | O66: 17802 | U66: 8026 | V66: 9768 | W66: 8 | X66: 2220 | Y66: 207 | Z66: 1767 | AA66: 2186 | AB66: 1663 | AC66: 2208 | AD66: 2780 | AE66: 2729 | AF66: 2042 | AH66: 7577 | AI66: 9962 | AJ66: 263 | AK66: 74 | AL66: 411 | AM66: 30 | AN66: 1415 | AO66: 14119 | AP66: 309 | AQ66: 1444 | AS66: 12411 | AT66: 553 | AU66: 1625 | AV66: 211 | AW66: 34 | AX66: 3 | AY66: 9 | AZ66: 2 | BA66: 817 | BC66: 2137 | BE66: 10870 | BF66: 684 | BG66: 6143 | BH66: 105 | BI66: 74571 | BJ66: 9769 | BK66: 4008 | BL66: 1865 | BM66: 2137 | BN66: 19 | BO66: 4 | BP66: 11676 | BQ66: 298 | BR66: 290 | BS66: 1420 | BT66: 55 | BU66: 850 | BV66: 398 | BW66: 583 | BX66: 1727 | BZ66: 3 | CA66: 482 | CB66: 9 | CD66: 2 | CE66: 9 | CG66: 1853 | CH66: 15949 | CJ66: 6647 | CK66: 4797 | CL66: 4962 | CM66: 33 | CO66: 1092 | CQ66: 203 | CR66: 2 | CS66: 66 | CT66: 2482 | CU66: 443 | CV66: 81 | CW66: 1181 | CX66: 101 | CY66: 463 | CZ66: 9 | DA66: 6 | DB66: 2579 | DC66: 911 | DD66: 2059 | DE66: 328 | DF66: 425 | DG66: 757 | DH66: 2300 | DI66: 2163 | DJ66: 5 | DK66: 244 | DL66: 1159 | DM66: 106 | DO66: 3524 | DP66: 2213 | DQ66: 1975 | DR66: 2479 | DS66: 8 | DT66: 6 | DU66: 1 | DV66: 122 | DW66: 49 | DX66: 321 | DY66: 986 | DZ66: 307 | EA66: 70 | EB66: 407 | EC66: 249 | ED66: 4827 | EE66: 258 | EF66: 75 | EG66: 220 | EI66: 69 | EJ66: 17438
A67: 106150820 | B67: 150820 | C67: KERN | D67: BAKERSFIELD REHABILITATION HOSPITAL | E67: 4400 KIRKCALDY DR | F67: BAKERSFIELD | G67: 93306 | H67: Investor - Limited Liability Company | I67: Small/Rural | J67: 50-99 | K67: District 16 | L67: District 34 | M67: Bakersfield Northeast/Oildale | N67: Urban | S67: 298 | U67: 128 | V67: 170 | AC67: 17 | AD67: 68 | AE67: 117 | AF67: 82 | AG67: 14 | AH67: 54 | AI67: 147 | AJ67: 97 | AN67: 19 | AO67: 203 | AP67: 76 | AS67: 1 | AT67: 3 | AU67: 280 | AV67: 1 | AW67: 13 | BG67: 298 | BI67: 3327 | BL67: 298 | BP67: 56 | BQ67: 31 | BS67: 42 | BT67: 1 | BV67: 11 | BX67: 150 | CA67: 6 | CC67: 1 | CH67: 298 | CJ67: 277 | CK67: 11 | CL67: 7 | CM67: 1 | CO67: 1 | CQ67: 1 | CT67: 3 | CW67: 4 | CX67: 2 | CY67: 31 | DA67: 1 | DB67: 51 | DC67: 10 | DD67: 4 | DE67: 1 | DF67: 15 | DK67: 66 | DL67: 75 | DM67: 35 | DO67: 10 | DQ67: 5 | DY67: 1 | EB67: 14 | EC67: 1 | ED67: 267 | EI67: 2 | EJ67: 296
A68: 106154022 | B68: 154022 | C68: KERN | D68: ENCOMPASS HEALTH REHABILITATION HOSPITAL OF BAKERSFIELD | E68: 5001 COMMERCE DR | F68: BAKERSFIELD | G68: 93309 | H68: Investor - Limited Liability Company | I68: Small/Rural | J68: 50-99 | K68: District 16 | L68: District 34 | M68: Bakersfield Northwest/Rosedale | N68: Urban | S68: 1711 | U68: 882 | V68: 829 | Z68: 55 | AA68: 97 | AB68: 115 | AC68: 227 | AD68: 384 | AE68: 469 | AF68: 358 | AG68: 6 | AH68: 320 | AI68: 1387 | AJ68: 4 | AL68: 30 | AN68: 90 | AO68: 1478 | AP68: 43 | AQ68: 58 | AR68: 12 | AS68: 3 | AT68: 29 | AU68: 1662 | AV68: 10 | BB68: 7 | BG68: 1711 | BI68: 22254 | BJ68: 6 | BL68: 1705 | BP68: 413 | BQ68: 166 | BR68: 2 | BS68: 125 | BT68: 1 | BV68: 20 | BW68: 5 | BX68: 959 | CA68: 18 | CD68: 2 | CH68: 1711 | CJ68: 1102 | CK68: 340 | CL68: 254 | CM68: 14 | CQ68: 1 | CT68: 36 | CU68: 5 | CV68: 1 | CW68: 4 | CX68: 4 | CY68: 282 | DB68: 349 | DC68: 24 | DD68: 7 | DE68: 1 | DF68: 110 | DK68: 159 | DL68: 466 | DM68: 259 | DN68: 4 | DO68: 69 | DQ68: 100 | DR68: 13 | DY68: 3 | ED68: 1526 | EI68: 11 | EJ68: 1700
A69: 106154044 | B69: 154044 | C69: KERN | D69: BAKERSFIELD BEHAVORIAL HEALTHCARE HOSPITAL, LLC | E69: 5201 WHITE LN | F69: BAKERSFIELD | G69: 93309 | H69: Investor - Limited Liability Company | I69: Small/Rural | J69: 50-99 | K69: District 16 | L69: District 34 | M69: Bakersfield Southwest | N69: Urban | Q69: 2775 | R69: 48 | U69: 1201 | V69: 1622 | X69: 53 | Y69: 1623 | Z69: 367 | AA69: 316 | AB69: 202 | AC69: 153 | AD69: 82 | AE69: 26 | AG69: 1 | AH69: 1071 | AI69: 1683 | AJ69: 69 | AK69: 14 | AL69: 44 | AN69: 234 | AO69: 2232 | AP69: 83 | AQ69: 216 | AS69: 1255 | AT69: 77 | AU69: 1077 | AV69: 5 | AW69: 407 | BB69: 2 | BF69: 1022 | BG69: 1801 | BI69: 18574 | BJ69: 19 | BK69: 2798 | BL69: 6 | BP69: 2726 | BQ69: 8 | BR69: 2 | BT69: 9 | BU69: 2 | BV69: 68 | BX69: 5 | CC69: 1 | CD69: 2 | CH69: 2823 | CJ69: 224 | CK69: 1198 | CL69: 762 | CN69: 592 | CO69: 43 | CP69: 1 | CQ69: 1 | CR69: 2 | CX69: 2823 | DO69: 105 | ED69: 2718 | EF69: 2 | EG69: 83 | EI69: 7 | EJ69: 2731
A70: 106154101 | B70: 154101 | C70: KERN | D70: BAKERSFIELD HEART HOSPITAL | E70: 3001 SILLECT AVE | F70: BAKERSFIELD | G70: 93308 | H70: Investor - Corporation | I70: Small/Rural | J70: 1-49 | K70: District 16 | L70: District 34 | M70: Bakersfield Northwest/Rosedale | N70: Urban | O70: 2095 | U70: 1185 | V70: 910 | Z70: 30 | AA70: 53 | AB70: 156 | AC70: 335 | AD70: 529 | AE70: 556 | AF70: 435 | AG70: 1 | AH70: 571 | AI70: 1510 | AJ70: 14 | AK70: 12 | AL70: 94 | AN70: 132 | AO70: 1273 | AP70: 1 | AQ70: 583 | AS70: 2073 | AU70: 21 | BD70: 1 | BE70: 1851 | BF70: 1 | BG70: 241 | BH70: 2 | BI70: 9765 | BJ70: 1846 | BK70: 20 | BL70: 229 | BP70: 1409 | BQ70: 42 | BR70: 24 | BS70: 175 | BT70: 1 | BV70: 130 | BW70: 70 | BX70: 188 | CA70: 56 | CG70: 70 | CH70: 2025 | CJ70: 1421 | CK70: 411 | CL70: 237 | CM70: 5 | CO70: 6 | CQ70: 15 | CT70: 269 | CU70: 31 | CV70: 15 | CW70: 89 | CX70: 3 | CY70: 29 | DA70: 1 | DB70: 1039 | DC70: 173 | DD70: 107 | DE70: 57 | DF70: 24 | DG70: 162 | DJ70: 1 | DK70: 32 | DL70: 59 | DM70: 4 | DO70: 267 | DQ70: 750 | DR70: 111 | DS70: 1 | DT70: 1 | DX70: 24 | DY70: 33 | DZ70: 8 | EB70: 63 | EC70: 3 | ED70: 830 | EE70: 4 | EG70: 44 | EI70: 7 | EJ70: 2044
A71: 106154160 | B71: 154160 | C71: KERN | D71: CRESTWOOD PSYCHIATRIC HEALTH FACILITY BAKERSFIELD | E71: 6700 EUCALYPTUS DR | F71: BAKERSFIELD | G71: 93306 | H71: Investor - Corporation | I71: Small/Rural | J71: 1-49 | K71: District 16 | L71: District 32 | M71: Bakersfield East/Lakeview/La Loma | N71: Urban | Q71: 308 | U71: 153 | V71: 155 | Y71: 29 | Z71: 112 | AA71: 88 | AB71: 46 | AC71: 24 | AG71: 9 | AH71: 146 | AI71: 161 | AJ71: 1 | AN71: 41 | AO71: 106 | AP71: 16 | AQ71: 145 | AT71: 17 | AW71: 291 | BG71: 308 | BI71: 5137 | BJ71: 1 | BK71: 307 | BP71: 263 | BR71: 15 | BT71: 28 | BV71: 2 | CH71: 308 | CK71: 251 | CL71: 6 | CN71: 21 | CQ71: 30 | CX71: 276 | DM71: 19 | DN71: 13 | ED71: 308 | EG71: 56 | EI71: 1 | EJ71: 251
A72: 106154168 | B72: 154168 | C72: KERN | D72: ADVENTIST HEALTH TEHACHAPI VALLEY | E72: MAGELLAN DR | F72: TEHACHAPI | G72: 93561 | H72: Non-profit Corporation (incl. Church-related) | I72: Small/Rural | J72: 1-49 | K72: District 16 | L72: District 34 | M72: Bear Valley Springs/Keene/Stallion Springs/Tehachapi | N72: Rural | O72: 972 | P72: 11 | U72: 504 | V72: 479 | Z72: 55 | AA72: 78 | AB72: 112 | AC72: 157 | AD72: 213 | AE72: 210 | AF72: 152 | AG72: 6 | AH72: 162 | AI72: 813 | AJ72: 8 | AN72: 109 | AO72: 773 | AP72: 25 | AQ72: 76 | AS72: 947 | AT72: 3 | AU72: 5 | AX72: 4 | BA72: 24 | BE72: 961 | BF72: 6 | BG72: 11 | BH72: 5 | BI72: 3586 | BJ72: 946 | BK72: 18 | BL72: 19 | BP72: 578 | BQ72: 81 | BR72: 16 | BS72: 69 | BU72: 18 | BV72: 33 | BW72: 37 | BX72: 113 | CA72: 34 | CB72: 4 | CG72: 121 | CH72: 862 | CJ72: 502 | CK72: 300 | CL72: 100 | CM72: 6 | CO72: 54 | CQ72: 20 | CS72: 1 | CT72: 285 | CU72: 4 | CV72: 3 | CW72: 72 | CX72: 42 | CY72: 6 | DB72: 130 | DC72: 119 | DD72: 147 | DE72: 32 | DF72: 9 | DG72: 75 | DJ72: 2 | DK72: 5 | DL72: 49 | DN72: 3 | DO72: 469 | DQ72: 30 | DR72: 94 | DV72: 1 | DX72: 12 | DY72: 9 | EA72: 1 | EB72: 89 | ED72: 217 | EE72: 61 | EF72: 3 | EG72: 11 | EI72: 6 | EJ72: 963
A73: 106164029 | B73: 164029 | C73: KINGS | D73: ADVENTIST HEALTH HANFORD | E73: 115 MALL DR | F73: HANFORD | G73: 93230 | H73: Non-profit Corporation (incl. Church-related) | I73: Small/Rural | J73: 150-199 | K73: District 14 | L73: District 32 | M73: Armona/Hanford/Lemoore | N73: Urban | O73: 11643 | U73: 4710 | V73: 6932 | W73: 1 | X73: 2272 | Y73: 190 | Z73: 1679 | AA73: 1498 | AB73: 840 | AC73: 1140 | AD73: 1477 | AE73: 1369 | AF73: 1178 | AH73: 6655 | AI73: 4690 | AJ73: 298 | AK73: 54 | AL73: 190 | AM73: 19 | AN73: 507 | AO73: 9979 | AP73: 310 | AQ73: 572 | AR73: 12 | AS73: 8006 | AT73: 324 | AU73: 714 | AV73: 211 | AX73: 37 | AY73: 9 | BA73: 82 | BC73: 2260 | BE73: 5965 | BF73: 359 | BG73: 5297 | BH73: 22 | BI73: 50484 | BJ73: 5629 | BK73: 1036 | BL73: 2703 | BM73: 2260 | BN73: 15 | BP73: 7460 | BQ73: 266 | BR73: 54 | BS73: 939 | BT73: 7 | BU73: 82 | BV73: 253 | BW73: 313 | BX73: 1946 | BZ73: 90 | CA73: 216 | CB73: 3 | CD73: 3 | CE73: 6 | CF73: 5 | CG73: 967 | CH73: 10676 | CJ73: 3016 | CK73: 4926 | CL73: 2673 | CM73: 10 | CO73: 860 | CQ73: 156 | CS73: 2 | CT73: 1469 | CU73: 126 | CV73: 37 | CW73: 785 | CX73: 104 | CY73: 219 | CZ73: 4 | DA73: 3 | DB73: 1022 | DC73: 620 | DD73: 1066 | DE73: 99 | DF73: 176 | DG73: 546 | DH73: 2413 | DI73: 2272 | DJ73: 2 | DK73: 104 | DL73: 528 | DM73: 46 | DN73: 2 | DO73: 3327 | DP73: 2312 | DQ73: 612 | DR73: 923 | DS73: 1 | DT73: 30 | DU73: 1 | DV73: 83 | DW73: 13 | DX73: 237 | DY73: 508 | DZ73: 77 | EA73: 125 | EB73: 240 | EC73: 55 | ED73: 2852 | EE73: 247 | EF73: 9 | EG73: 110 | EI73: 47 | EJ73: 11477
A74: 106171049 | B74: 171049 | C74: LAKE | D74: ADVENTIST HEALTH CLEARLAKE | E74: 15630 18TH AVE | F74: CLEARLAKE | G74: 95422 | H74: Non-profit Corporation (incl. Church-related) | I74: Small/Rural | J74: 1-49 | K74: District 2 | L74: District 4 | M74: Clearlake/Clearlake Oaks | N74: Rural | O74: 1280 | P74: 58 | U74: 610 | V74: 728 | X74: 161 | Y74: 17 | Z74: 122 | AA74: 106 | AB74: 87 | AC74: 129 | AD74: 268 | AE74: 229 | AF74: 219 | AH74: 226 | AI74: 1089 | AJ74: 23 | AK74: 18 | AN74: 50 | AO74: 953 | AP74: 127 | AQ74: 190 | AS74: 1067 | AT74: 28 | AU74: 10 | AV74: 25 | AX74: 52 | BB74: 2 | BC74: 154 | BE74: 931 | BF74: 2 | BG74: 405 | BI74: 6389 | BJ74: 676 | BK74: 360 | BL74: 143 | BM74: 154 | BN74: 3 | BO74: 2 | BP74: 784 | BQ74: 70 | BR74: 2 | BS74: 190 | BT74: 2 | BV74: 65 | BW74: 37 | BX74: 173 | CA74: 13 | CB74: 2 | CG74: 147 | CH74: 1191 | CJ74: 553 | CK74: 492 | CL74: 226 | CO74: 55 | CQ74: 12 | CT74: 231 | CU74: 16 | CV74: 4 | CW74: 63 | CX74: 14 | CY74: 30 | CZ74: 1 | DB74: 149 | DC74: 144 | DD74: 133 | DE74: 57 | DF74: 14 | DG74: 59 | DH74: 169 | DI74: 161 | DK74: 10 | DL74: 69 | DM74: 13 | DN74: 1 | DO74: 487 | DP74: 163 | DQ74: 16 | DR74: 81 | DV74: 5 | DW74: 1 | DX74: 25 | DY74: 21 | DZ74: 2 | EA74: 5 | EB74: 63 | EC74: 1 | ED74: 433 | EE74: 35 | EF74: 4 | EG74: 38 | EI74: 5 | EJ74: 1291
A75: 106171395 | B75: 171395 | C75: LAKE | D75: SUTTER LAKESIDE HOSPITAL | E75: 5176 HILL RD E | F75: LAKEPORT | G75: 95453 | H75: Non-profit Corporation (incl. Church-related) | I75: Small/Rural | J75: 1-49 | K75: District 2 | L75: District 4 | M75: Kelseyville/Lakeport | N75: Rural | O75: 1773 | P75: 83 | U75: 747 | V75: 1109 | X75: 261 | Y75: 29 | Z75: 172 | AA75: 182 | AB75: 123 | AC75: 144 | AD75: 310 | AE75: 337 | AF75: 298 | AH75: 281 | AI75: 1546 | AJ75: 29 | AK75: 108 | AL75: 16 | AN75: 23 | AO75: 1467 | AP75: 8 | AQ75: 179 | AR75: 55 | AS75: 1462 | AT75: 17 | AU75: 72 | AV75: 25 | AW75: 1 | AX75: 28 | AY75: 1 | BA75: 1 | BC75: 249 | BE75: 1156 | BF75: 8 | BG75: 692 | BI75: 6971 | BJ75: 658 | BK75: 511 | BL75: 330 | BM75: 249 | BN75: 108 | BP75: 1070 | BQ75: 154 | BR75: 3 | BS75: 241 | BT75: 3 | BU75: 1 | BV75: 42 | BW75: 51 | BX75: 248 | CA75: 37 | CD75: 6 | CG75: 195 | CH75: 1661 | CJ75: 831 | CK75: 682 | CL75: 237 | CM75: 2 | CO75: 61 | CQ75: 43 | CT75: 264 | CU75: 41 | CV75: 16 | CW75: 93 | CX75: 13 | CY75: 32 | CZ75: 1 | DB75: 177 | DC75: 119 | DD75: 215 | DE75: 55 | DF75: 59 | DG75: 65 | DH75: 268 | DI75: 260 | DJ75: 1 | DK75: 18 | DL75: 151 | DM75: 8 | DO75: 216 | DP75: 245 | DQ75: 19 | DR75: 140 | DS75: 1 | DU75: 1 | DV75: 10 | DW75: 3 | DX75: 35 | DY75: 137 | DZ75: 6 | EA75: 4 | EB75: 19 | EC75: 4 | ED75: 971 | EE75: 45 | EG75: 23 | EI75: 9 | EJ75: 1824
A76: 106184008 | B76: 184008 | C76: LASSEN | D76: BANNER LASSEN MEDICAL CENTER | E76: 1800 SPRING RIDGE DR | F76: SUSANVILLE | G76: 96130 | H76: Non-profit Corporation (incl. Church-related) | I76: Small/Rural | J76: 1-49 | K76: District 1 | L76: District 1 | M76: Susanville | N76: Rural | O76: 1020 | U76: 410 | V76: 610 | X76: 219 | Y76: 19 | Z76: 159 | AA76: 99 | AB76: 49 | AC76: 76 | AD76: 114 | AE76: 134 | AF76: 151 | AH76: 87 | AI76: 933 | AK76: 18 | AN76: 13 | AO76: 902 | AP76: 21 | AQ76: 66 | AS76: 608 | AT76: 203 | BA76: 11 | BC76: 198 | BE76: 604 | BG76: 416 | BI76: 3581 | BJ76: 579 | BK76: 73 | BL76: 170 | BM76: 198 | BP76: 779 | BQ76: 4 | BR76: 4 | BS76: 1 | BU76: 30 | BV76: 117 | BW76: 37 | BX76: 6 | BZ76: 40 | CA76: 2 | CG76: 161 | CH76: 859 | CJ76: 356 | CK76: 351 | CL76: 241 | CM76: 7 | CO76: 52 | CQ76: 13 | CT76: 88 | CU76: 5 | CV76: 6 | CW76: 41 | CX76: 4 | CY76: 13 | DA76: 1 | DB76: 79 | DC76: 103 | DD76: 108 | DE76: 37 | DF76: 18 | DG76: 40 | DH76: 212 | DI76: 203 | DK76: 8 | DL76: 48 | DM76: 6 | DO76: 30 | DP76: 195 | DQ76: 9 | DR76: 49 | DV76: 8 | DX76: 10 | DY76: 33 | DZ76: 2 | EA76: 4 | EB76: 12 | ED76: 667 | EE76: 1 | EF76: 1 | EG76: 10 | EI76: 10 | EJ76: 999
A77: 106190017 | B77: 190017 | C77: LOS ANGELES | D77: ALHAMBRA HOSPITAL MEDICAL CENTER | E77: 100 S RAYMOND AVE | F77: ALHAMBRA | G77: 91801 | H77: Investor - Partnership | I77: Small/Rural | J77: 100-149 | K77: District 22 | L77: District 49 | M77: Alhambra/El Sereno South/San Gabriel Central | N77: Urban | O77: 3774 | P77: 21 | S77: 207 | U77: 1963 | V77: 2039 | Y77: 22 | Z77: 144 | AA77: 210 | AB77: 294 | AC77: 540 | AD77: 711 | AE77: 788 | AF77: 1293 | AH77: 1487 | AI77: 2495 | AJ77: 20 | AK77: 18 | AL77: 1822 | AN77: 201 | AO77: 926 | AP77: 38 | AQ77: 997 | AS77: 2639 | AT77: 46 | AU77: 699 | AV77: 380 | AW77: 62 | AX77: 133 | AY77: 1 | BA77: 1 | BB77: 41 | BE77: 2995 | BF77: 461 | BG77: 546 | BI77: 26639 | BJ77: 3394 | BK77: 467 | BL77: 141 | BP77: 1690 | BQ77: 242 | BR77: 96 | BS77: 763 | BT77: 38 | BU77: 2 | BV77: 151 | BW77: 193 | BX77: 743 | CA77: 76 | CB77: 8 | CG77: 254 | CH77: 3748 | CJ77: 2293 | CK77: 1301 | CL77: 379 | CM77: 4 | CO77: 3 | CQ77: 21 | CR77: 1 | CT77: 916 | CU77: 192 | CV77: 50 | CW77: 197 | CX77: 29 | CY77: 122 | CZ77: 7 | DA77: 5 | DB77: 546 | DC77: 264 | DD77: 603 | DE77: 85 | DF77: 157 | DG77: 282 | DJ77: 4 | DK77: 228 | DL77: 281 | DM77: 27 | DN77: 7 | DO77: 641 | DP77: 1 | DQ77: 187 | DR77: 623 | DS77: 2 | DT77: 2 | DU77: 2 | DV77: 10 | DW77: 11 | DX77: 93 | DY77: 202 | DZ77: 37 | EA77: 1 | EB77: 69 | EC77: 34 | ED77: 1975 | EE77: 112 | EG77: 50 | EH77: 1 | EI77: 12 | EJ77: 3939
A78: 106190020 | B78: 190020 | C78: LOS ANGELES | D78: BHC ALHAMBRA HOSPITAL | E78: 4619 ROSEMEAD BLVD | F78: ROSEMEAD | G78: 91770 | H78: Investor - Corporation | I78: Small/Rural | J78: 50-99 | K78: District 22 | L78: District 49 | M78: Rosemead/San Gabriel South/South El Monte West/Temple City West | N78: Urban | Q78: 5224 | U78: 2508 | V78: 2716 | Y78: 1546 | Z78: 1312 | AA78: 1044 | AB78: 609 | AC78: 464 | AD78: 236 | AE78: 13 | AH78: 1841 | AI78: 3301 | AJ78: 82 | AL78: 340 | AN78: 859 | AO78: 1929 | AP78: 8 | AQ78: 2088 | AS78: 556 | AT78: 4527 | AU78: 140 | BA78: 1 | BF78: 90 | BG78: 5134 | BI78: 36697 | BJ78: 1 | BK78: 5223 | BP78: 4871 | BQ78: 29 | BS78: 71 | BT78: 127 | BV78: 109 | CB78: 16 | CD78: 1 | CH78: 5224 | CJ78: 435 | CK78: 927 | CL78: 3819 | CN78: 26 | CO78: 9 | CQ78: 8 | CU78: 1 | CX78: 5216 | CY78: 1 | DN78: 6 | DO78: 107 | ED78: 5117 | EF78: 25 | EG78: 1275 | EH78: 2 | EI78: 142 | EJ78: 3780
A79: 106190034 | B79: 190034 | C79: LOS ANGELES | D79: ANTELOPE VALLEY HOSPITAL | E79: 1600 W AVE J | F79: LANCASTER | G79: 93534 | H79: District | I79: Small/Rural | J79: 300-499 | K79: District 21 | L79: District 36 | M79: Desert View Highlands/Lancaster West/Palmdale Northwest/Quartz Hill | N79: Urban | O79: 20227 | Q79: 466 | U79: 8867 | V79: 11826 | X79: 3756 | Y79: 443 | Z79: 2550 | AA79: 2735 | AB79: 1514 | AC79: 2107 | AD79: 3140 | AE79: 2488 | AF79: 1960 | AH79: 8579 | AI79: 12007 | AJ79: 107 | AK79: 84 | AL79: 473 | AM79: 41 | AN79: 4397 | AO79: 7930 | AP79: 72 | AQ79: 7346 | AR79: 350 | AS79: 14960 | AT79: 1254 | AU79: 272 | AV79: 857 | AW79: 6 | AX79: 2 | AY79: 6 | BA79: 106 | BC79: 3230 | BE79: 13354 | BF79: 8 | BG79: 7331 | BI79: 89016 | BJ79: 198 | BK79: 15257 | BL79: 1026 | BM79: 3230 | BN79: 982 | BP79: 14021 | BQ79: 206 | BR79: 294 | BS79: 1558 | BT79: 166 | BU79: 99 | BV79: 535 | BW79: 744 | BX79: 2642 | BZ79: 30 | CA79: 379 | CB79: 8 | CD79: 11 | CG79: 285 | CH79: 20408 | CJ79: 6431 | CK79: 8052 | CL79: 5559 | CM79: 41 | CO79: 517 | CQ79: 93 | CT79: 2448 | CU79: 399 | CV79: 127 | CW79: 773 | CX79: 623 | CY79: 498 | CZ79: 9 | DA79: 9 | DB79: 2298 | DC79: 1144 | DD79: 1938 | DE79: 194 | DF79: 374 | DG79: 825 | DH79: 3446 | DI79: 3349 | DJ79: 8 | DK79: 273 | DL79: 1923 | DM79: 34 | DN79: 1 | DO79: 1369 | DP79: 3189 | DQ79: 1362 | DR79: 2114 | DS79: 6 | DT79: 15 | DU79: 2 | DV79: 188 | DW79: 45 | DX79: 465 | DY79: 1202 | DZ79: 337 | EA79: 34 | EB79: 398 | EC79: 269 | ED79: 9264 | EE79: 434 | EF79: 1 | EG79: 262 | EI79: 122 | EJ79: 20308
A80: 106190045 | B80: 190045 | C80: LOS ANGELES | D80: CATALINA ISLAND MEDICAL CENTER | E80: 100 FALLS CANYON RD | F80: AVALON | G80: 90704 | H80: Non-profit Corporation (incl. Church-related) | I80: Small/Rural | J80: 1-49 | K80: District 26 | L80: District 70 | M80: Avalon | N80: Frontier | O80: 19 | P80: 1 | U80: 6 | V80: 14 | AF80: 15 | AG80: 5 | AI80: 12 | AJ80: 8 | AO80: 12 | AP80: 8 | AS80: 3 | AT80: 5 | AU80: 6 | AV80: 1 | AX80: 5 | BE80: 4 | BG80: 16 | BI80: 441 | BJ80: 4 | BL80: 16 | BP80: 11 | BQ80: 3 | BS80: 2 | BV80: 1 | BW80: 2 | CD80: 1 | CG80: 14 | CH80: 6 | CJ80: 18 | CK80: 2 | CT80: 2 | CU80: 1 | CW80: 2 | CY80: 1 | DB80: 1 | DC80: 3 | DE80: 1 | DF80: 3 | DK80: 5 | DL80: 1 | ED80: 20 | EJ80: 20
A81: 106190049 | B81: 190049 | C81: LOS ANGELES | D81: KINDRED HOSPITAL - BALDWIN PARK | E81: 14148 FRANCISQUITO AVE | F81: BALDWIN PARK | G81: 91706 | H81: Investor - Limited Liability Company | I81: Small/Rural | J81: 50-99 | K81: District 22 | L81: District 48 | M81: Bassett/Industry West/La Puente | N81: Urban | O81: 703 | U81: 380 | V81: 323 | AA81: 17 | AB81: 31 | AC81: 85 | AD81: 157 | AE81: 199 | AF81: 204 | AG81: 10 | AH81: 131 | AI81: 508 | AJ81: 64 | AL81: 144 | AN81: 44 | AO81: 310 | AP81: 3 | AQ81: 202 | AT81: 1 | AU81: 698 | AW81: 4 | BG81: 703 | BI81: 26905 | BL81: 703 | BP81: 17 | BQ81: 44 | BR81: 12 | BS81: 320 | BV81: 14 | BW81: 201 | BX81: 76 | CA81: 19 | CG81: 3 | CH81: 700 | CJ81: 432 | CK81: 84 | CL81: 169 | CM81: 1 | CO81: 17 | CT81: 56 | CU81: 5 | CW81: 29 | CY81: 9 | DB81: 25 | DC81: 391 | DD81: 37 | DE81: 25 | DF81: 9 | DG81: 56 | DK81: 3 | DL81: 49 | DM81: 9 | DO81: 224 | DQ81: 83 | DR81: 58 | DX81: 11 | DY81: 8 | EB81: 17 | ED81: 290 | EE81: 12 | EF81: 1 | EG81: 7 | EI81: 3 | EJ81: 692
A82: 106190052 | B82: 190052 | C82: LOS ANGELES | D82: BARLOW RESPIRATORY HOSPITAL | E82: 2000 STADIUM WAY | F82: LOS ANGELES | G82: 90026 | H82: Non-profit Corporation (incl. Church-related) | I82: Small/Rural | J82: 100-149 | K82: District 24 | L82: District 51 | M82: Glassell Park/Glendale Southeast/Silverlake North | N82: Urban | O82: 673 | U82: 367 | V82: 306 | Z82: 12 | AA82: 27 | AB82: 39 | AC82: 73 | AD82: 134 | AE82: 206 | AF82: 181 | AG82: 1 | AH82: 136 | AI82: 534 | AJ82: 3 | AL82: 68 | AN82: 46 | AO82: 533 | AP82: 13 | AQ82: 13 | AU82: 673 | BF82: 3 | BG82: 670 | BI82: 22927 | BK82: 1 | BL82: 672 | BP82: 7 | BQ82: 134 | BR82: 76 | BS82: 298 | BU82: 2 | BV82: 3 | BW82: 76 | BX82: 59 | CA82: 10 | CD82: 6 | CE82: 1 | CF82: 1 | CG82: 58 | CH82: 614 | CI82: 1 | CJ82: 503 | CK82: 6 | CL82: 155 | CM82: 8 | CS82: 1 | CT82: 88 | CW82: 10 | CY82: 5 | DB82: 10 | DC82: 501 | DD82: 7 | DE82: 10 | DF82: 10 | DG82: 9 | DK82: 3 | DL82: 15 | DM82: 5 | DO82: 428 | DQ82: 90 | DR82: 13 | DU82: 1 | DX82: 4 | DY82: 5 | DZ82: 1 | EA82: 1 | EB82: 42 | EC82: 8 | ED82: 55 | EE82: 25 | EI82: 8 | EJ82: 665
A83: 106190053 | B83: 190053 | C83: LOS ANGELES | D83: ST. MARY MEDICAL CENTER - LONG BEACH | E83: 1050 LINDEN AVE | F83: LONG BEACH | G83: 90813 | H83: Non-profit Corporation (incl. Church-related) | I83: Small/Rural | J83: 300-499 | K83: District 33 | L83: District 70 | M83: Belmont Shore/Long Beach East/Long Beach Shoreline/Los Altos/Naples | N83: Urban | O83: 10551 | S83: 267 | U83: 4801 | V83: 6017 | X83: 1427 | Y83: 185 | Z83: 1262 | AA83: 1415 | AB83: 1017 | AC83: 1496 | AD83: 1716 | AE83: 1369 | AF83: 931 | AH83: 4775 | AI83: 5961 | AJ83: 82 | AK83: 33 | AL83: 703 | AM83: 159 | AN83: 1841 | AO83: 6645 | AP83: 324 | AQ83: 887 | AR83: 226 | AS83: 8539 | AT83: 143 | AU83: 247 | AV83: 284 | AW83: 16 | AX83: 240 | AY83: 3 | BA83: 1 | BC83: 1345 | BE83: 6781 | BF83: 44 | BG83: 3989 | BH83: 4 | BI83: 66386 | BJ83: 5631 | BK83: 1540 | BL83: 1888 | BM83: 1345 | BN83: 414 | BP83: 7627 | BQ83: 280 | BR83: 213 | BS83: 769 | BT83: 70 | BU83: 10 | BV83: 528 | BW83: 336 | BX83: 819 | BZ83: 3 | CA83: 113 | CB83: 8 | CD83: 42 | CG83: 229 | CH83: 10589 | CJ83: 3321 | CK83: 6177 | CL83: 967 | CM83: 49 | CN83: 4 | CO83: 96 | CQ83: 126 | CS83: 78 | CT83: 1545 | CU83: 218 | CV83: 88 | CW83: 657 | CX83: 120 | CY83: 279 | CZ83: 3 | DA83: 7 | DB83: 1549 | DC83: 439 | DD83: 843 | DE83: 156 | DF83: 183 | DG83: 487 | DH83: 1496 | DI83: 1382 | DJ83: 3 | DK83: 211 | DL83: 1095 | DM83: 57 | DO83: 2050 | DP83: 1368 | DQ83: 913 | DR83: 1013 | DS83: 6 | DT83: 7 | DU83: 3 | DV83: 160 | DW83: 31 | DX83: 226 | DY83: 477 | DZ83: 108 | EA83: 30 | EB83: 143 | EC83: 162 | ED83: 3966 | EE83: 155 | EF83: 26 | EG83: 639 | EH83: 10 | EI83: 84 | EJ83: 10059
A84: 106190066 | B84: 190066 | C84: LOS ANGELES | D84: LOS ANGELES COMMUNITY HOSPITAL AT BELLFLOWER | E84: 9542 ARTESIA BLVD | F84: BELLFLOWER | G84: 90706 | H84: Investor - Corporation | I84: Small/Rural | J84: 100-149 | K84: District 32 | L84: District 58 | M84: Bellflower/Paramount South | N84: Urban | Q84: 1359 | U84: 931 | V84: 428 | Y84: 16 | Z84: 233 | AA84: 338 | AB84: 270 | AC84: 284 | AD84: 176 | AE84: 39 | AG84: 3 | AH84: 397 | AI84: 819 | AJ84: 143 | AL84: 68 | AN84: 373 | AO84: 588 | AP84: 12 | AQ84: 290 | AR84: 28 | AS84: 28 | AU84: 1299 | AV84: 2 | AW84: 28 | AX84: 2 | BF84: 685 | BG84: 674 | BI84: 9871 | BJ84: 213 | BL84: 1146 | BP84: 904 | BQ84: 38 | BR84: 27 | BS84: 155 | BT84: 70 | BU84: 2 | BV84: 9 | CB84: 7 | CD84: 147 | CG84: 1 | CH84: 1358 | CJ84: 326 | CK84: 985 | CL84: 43 | CQ84: 5 | CX84: 1354 | DM84: 5 | DO84: 1347 | ED84: 12 | EF84: 19 | EG84: 185 | EI84: 6 | EJ84: 1149
A85: 106190081 | B85: 190081 | C85: LOS ANGELES | D85: BEVERLY HOSPITAL | E85: 309 W BEVERLY BLVD | F85: MONTEBELLO | G85: 90640 | H85: Non-profit Corporation (incl. Church-related) | I85: Small/Rural | J85: 200-299 | K85: District 32 | L85: District 58 | M85: Pico Rivera/Santa Fe Springs Northwest | N85: Urban | O85: 7873 | U85: 3727 | V85: 4146 | X85: 560 | Y85: 107 | Z85: 533 | AA85: 735 | AB85: 745 | AC85: 1128 | AD85: 1499 | AE85: 1222 | AF85: 1344 | AH85: 6506 | AI85: 1317 | AJ85: 50 | AL85: 338 | AN85: 207 | AO85: 7136 | AP85: 28 | AQ85: 152 | AR85: 12 | AS85: 6670 | AT85: 1 | AU85: 294 | AV85: 489 | AX85: 3 | AY85: 2 | BB85: 5 | BC85: 409 | BE85: 6092 | BF85: 268 | BG85: 1513 | BI85: 33713 | BJ85: 254 | BK85: 6173 | BL85: 1030 | BM85: 409 | BO85: 7 | BP85: 4671 | BQ85: 195 | BR85: 7 | BS85: 1176 | BT85: 5 | BU85: 2 | BV85: 260 | BW85: 242 | BX85: 1174 | BZ85: 2 | CA85: 105 | CB85: 23 | CD85: 11 | CG85: 105 | CH85: 7768 | CJ85: 3316 | CK85: 3515 | CL85: 923 | CM85: 11 | CN85: 2 | CQ85: 106 | CT85: 1081 | CU85: 218 | CV85: 69 | CW85: 448 | CX85: 101 | CY85: 219 | CZ85: 9 | DA85: 33 | DB85: 1021 | DC85: 422 | DD85: 1206 | DE85: 175 | DF85: 460 | DG85: 661 | DH85: 498 | DI85: 420 | DJ85: 9 | DK85: 194 | DL85: 590 | DM85: 38 | DN85: 1 | DO85: 949 | DP85: 428 | DQ85: 613 | DR85: 1076 | DT85: 3 | DU85: 1 | DV85: 197 | DW85: 15 | DX85: 233 | DY85: 708 | DZ85: 60 | EA85: 4 | EB85: 90 | EC85: 104 | ED85: 3322 | EE85: 70 | EF85: 7 | EG85: 195 | EI85: 35 | EJ85: 7636
A86: 106190110 | B86: 190110 | C86: LOS ANGELES | D86: SOUTHERN CALIFORNIA HOSPITAL AT CULVER CITY | E86: 3828 DELMAS TER | F86: CULVER CITY | G86: 90232 | H86: Investor - Corporation | I86: Small/Rural | J86: 300-499 | K86: District 30 | L86: District 54 | M86: Culver City North/Palms | N86: Urban | O86: 7510 | P86: 20 | Q86: 3455 | R86: 982 | S86: 334 | U86: 7348 | V86: 4948 | W86: 5 | Y86: 79 | Z86: 1035 | AA86: 1885 | AB86: 1854 | AC86: 2493 | AD86: 2435 | AE86: 1424 | AF86: 1096 | AH86: 2558 | AI86: 9443 | AJ86: 300 | AK86: 15 | AL86: 353 | AN86: 4600 | AO86: 5377 | AP86: 384 | AQ86: 1269 | AR86: 303 | AS86: 7054 | AT86: 17 | AU86: 3322 | AV86: 1439 | AW86: 259 | AX86: 120 | BA86: 2 | BB86: 88 | BE86: 6024 | BF86: 165 | BG86: 6112 | BI86: 77009 | BJ86: 6164 | BK86: 3392 | BL86: 2744 | BO86: 1 | BP86: 7040 | BQ86: 324 | BR86: 249 | BS86: 2177 | BT86: 93 | BU86: 15 | BV86: 863 | BW86: 211 | BX86: 730 | CA86: 71 | CB86: 112 | CC86: 2 | CD86: 413 | CF86: 1 | CG86: 181 | CH86: 12120 | CJ86: 4292 | CK86: 3256 | CL86: 4553 | CM86: 14 | CO86: 10 | CQ86: 176 | CT86: 1883 | CU86: 162 | CV86: 70 | CW86: 745 | CX86: 4808 | CY86: 457 | CZ86: 3 | DA86: 22 | DB86: 1164 | DC86: 354 | DD86: 782 | DE86: 191 | DF86: 342 | DG86: 433 | DH86: 14 | DK86: 160 | DL86: 639 | DM86: 70 | DN86: 2 | DO86: 5629 | DP86: 1 | DQ86: 858 | DR86: 1198 | DS86: 1 | DT86: 4 | DU86: 1 | DV86: 62 | DW86: 10 | DX86: 175 | DY86: 436 | DZ86: 60 | EA86: 16 | EB86: 89 | EC86: 84 | ED86: 3653 | EE86: 24 | EF86: 5 | EG86: 572 | EI86: 218 | EJ86: 11506
A87: 106190125 | B87: 190125 | C87: LOS ANGELES | D87: CALIFORNIA HOSPITAL MEDICAL CENTER - LOS ANGELES | E87: 1401 S GRAND AVE | F87: LOS ANGELES | G87: 90015 | H87: Non-profit Corporation (incl. Church-related) | I87: Small/Rural | J87: 300-499 | K87: District 30 | L87: District 53 | M87: Boyle Heights Northwest/Chinatown/Downtown Northwest/Little Tokyo/Westlake | N87: Urban | O87: 17067 | U87: 7678 | V87: 9389 | X87: 2810 | Y87: 458 | Z87: 2660 | AA87: 2647 | AB87: 1814 | AC87: 2364 | AD87: 2379 | AE87: 1185 | AF87: 750 | AH87: 10862 | AI87: 6169 | AJ87: 36 | AK87: 17 | AL87: 477 | AM87: 12 | AN87: 4121 | AO87: 8958 | AP87: 306 | AQ87: 3176 | AS87: 12133 | AT87: 461 | AU87: 1729 | AV87: 121 | AW87: 9 | AX87: 13 | BA87: 3 | BC87: 2598 | BE87: 9377 | BF87: 1641 | BG87: 6047 | BH87: 2 | BI87: 79030 | BJ87: 8360 | BK87: 3767 | BL87: 1348 | BM87: 2598 | BN87: 994 | BP87: 13476 | BQ87: 184 | BR87: 62 | BS87: 664 | BT87: 54 | BU87: 10 | BV87: 969 | BW87: 276 | BX87: 1163 | BY87: 1 | BZ87: 1 | CA87: 180 | CB87: 19 | CC87: 2 | CD87: 5 | CE87: 1 | CG87: 7 | CH87: 17060 | CJ87: 2624 | CK87: 13049 | CL87: 715 | CM87: 24 | CO87: 125 | CP87: 87 | CQ87: 238 | CR87: 205 | CT87: 1583 | CU87: 493 | CV87: 161 | CW87: 761 | CX87: 252 | CY87: 350 | CZ87: 19 | DA87: 28 | DB87: 1717 | DC87: 584 | DD87: 1696 | DE87: 328 | DF87: 461 | DG87: 779 | DH87: 3009 | DI87: 2648 | DJ87: 3 | DK87: 278 | DL87: 1904 | DM87: 13 | DO87: 3440 | DP87: 2738 | DQ87: 1067 | DR87: 1445 | DS87: 9 | DT87: 13 | DU87: 23 | DV87: 358 | DW87: 54 | DX87: 503 | DY87: 925 | DZ87: 156 | EA87: 37 | EB87: 274 | EC87: 128 | ED87: 5839 | EE87: 58 | EF87: 107 | EG87: 1713 | EH87: 4 | EI87: 58 | EJ87: 15185
A88: 106190137 | B88: 190137 | C88: LOS ANGELES | D88: CASA COLINA HOSPITAL | E88: 255 E BONITA AVE | F88: POMONA | G88: 91767 | H88: Non-profit Corporation (incl. Church-related) | I88: Small/Rural | J88: 50-99 | K88: District 20 | L88: District 52 | M88: Pomona East and South | N88: Urban | O88: 973 | S88: 1136 | U88: 1123 | V88: 986 | Y88: 21 | Z88: 96 | AA88: 152 | AB88: 152 | AC88: 309 | AD88: 530 | AE88: 495 | AF88: 354 | AH88: 652 | AI88: 1425 | AJ88: 32 | AK88: 16 | AM88: 135 | AN88: 155 | AO88: 1481 | AP88: 36 | AQ88: 270 | AR88: 16 | AS88: 556 | AT88: 39 | AU88: 1248 | AV88: 64 | AW88: 28 | AX88: 173 | AZ88: 1 | BE88: 2 | BF88: 294 | BG88: 1813 | BI88: 26536 | BK88: 525 | BL88: 1584 | BP88: 1077 | BQ88: 126 | BR88: 124 | BS88: 192 | BV88: 24 | BW88: 19 | BX88: 508 | CA88: 18 | CD88: 20 | CE88: 1 | CG88: 107 | CH88: 2002 | CJ88: 1086 | CK88: 184 | CL88: 756 | CM88: 59 | CO88: 7 | CP88: 1 | CQ88: 1 | CR88: 15 | CT88: 116 | CU88: 77 | CV88: 5 | CW88: 54 | CX88: 10 | CY88: 220 | DA88: 1 | DB88: 396 | DC88: 94 | DD88: 159 | DE88: 28 | DF88: 334 | DG88: 76 | DK88: 26 | DL88: 416 | DM88: 95 | DN88: 2 | DO88: 34 | DQ88: 104 | DR88: 189 | DS88: 1 | DT88: 9 | DV88: 8 | DW88: 1 | DX88: 20 | DY88: 230 | DZ88: 139 | EB88: 20 | EC88: 13 | ED88: 1337 | EE88: 4 | EF88: 3 | EG88: 14 | EI88: 27 | EJ88: 2065
A89: 106190148 | B89: 190148 | C89: LOS ANGELES | D89: CENTINELA HOSPITAL MEDICAL CENTER | E89: 555 E HARDY ST | F89: INGLEWOOD | G89: 90301 | H89: Investor - Limited Liability Company | I89: Small/Rural | J89: 300-499 | K89: District 35 | L89: District 62 | M89: Del Aire/Inglewood West/Los Angeles International Airport | N89: Urban | O89: 13205 | S89: 92 | U89: 6205 | V89: 7092 | X89: 763 | Y89: 113 | Z89: 863 | AA89: 1126 | AB89: 1166 | AC89: 2042 | AD89: 3046 | AE89: 2203 | AF89: 1975 | AH89: 3863 | AI89: 9352 | AJ89: 82 | AK89: 27 | AL89: 188 | AN89: 7718 | AO89: 4593 | AQ89: 684 | AR89: 87 | AS89: 12409 | AT89: 11 | AU89: 83 | AV89: 5 | AW89: 21 | BA89: 3 | BB89: 12 | BC89: 753 | BE89: 12275 | BF89: 32 | BG89: 990 | BI89: 67354 | BJ89: 11824 | BK89: 118 | BL89: 602 | BM89: 753 | BP89: 7885 | BQ89: 530 | BR89: 244 | BS89: 1419 | BT89: 2 | BU89: 5 | BV89: 938 | BW89: 518 | BX89: 1624 | CA89: 104 | CB89: 27 | CC89: 1 | CG89: 286 | CH89: 13011 | CJ89: 5800 | CK89: 6682 | CL89: 612 | CQ89: 201 | CR89: 1 | CS89: 1 | CT89: 2513 | CU89: 158 | CV89: 135 | CW89: 620 | CX89: 69 | CY89: 1217 | CZ89: 14 | DA89: 12 | DB89: 2392 | DC89: 786 | DD89: 1294 | DE89: 138 | DF89: 772 | DG89: 563 | DH89: 858 | DI89: 762 | DJ89: 3 | DK89: 180 | DL89: 805 | DM89: 6 | DO89: 3019 | DP89: 731 | DQ89: 1650 | DR89: 611 | DT89: 3 | DU89: 13 | DV89: 46 | DW89: 10 | DX89: 273 | DY89: 395 | DZ89: 85 | EA89: 2 | EB89: 101 | EC89: 56 | ED89: 6275 | EE89: 27 | EF89: 15 | EG89: 496 | EH89: 7 | EI89: 131 | EJ89: 12648
A90: 106190150 | B90: 190150 | C90: LOS ANGELES | D90: KEDREN COMMUNITY MENTAL HEALTH CENTER | E90: 4211 AVALON BLVD | F90: LOS ANGELES | G90: 90011 | H90: Non-profit Corporation (incl. Church-related) | I90: Small/Rural | J90: 50-99 | K90: District 30 | L90: District 59 | M90: South Central Northeast | N90: Urban | Q90: 840 | U90: 553 | V90: 287 | Y90: 24 | Z90: 295 | AA90: 269 | AB90: 154 | AC90: 75 | AD90: 23 | AH90: 242 | AI90: 563 | AJ90: 35 | AK90: 31 | AL90: 37 | AN90: 228 | AO90: 199 | AP90: 59 | AQ90: 286 | AS90: 49 | AT90: 151 | AU90: 542 | AW90: 98 | BF90: 542 | BG90: 298 | BI90: 15972 | BJ90: 66 | BK90: 774 | BP90: 695 | BQ90: 6 | BS90: 121 | BT90: 12 | BU90: 2 | CB90: 2 | CE90: 2 | CH90: 840 | CJ90: 2 | CO90: 838 | CX90: 840 | ED90: 840 | EI90: 10 | EJ90: 830
A91: 106190155 | B91: 190155 | C91: LOS ANGELES | D91: CALIFORNIA REHABILITATION INSTITUTE, LLC | E91: 2070 CENTURY PARK E | F91: LOS ANGELES | G91: 90067 | H91: Investor - Limited Liability Company | I91: Small/Rural | J91: 100-149 | K91: District 30 | L91: District 54 | M91: Century City/Cheviot Hills/Rancho Park/West Los Angeles/Westwood | N91: Urban | S91: 3362 | U91: 1759 | V91: 1603 | Z91: 48 | AA91: 86 | AB91: 123 | AC91: 294 | AD91: 649 | AE91: 1080 | AF91: 1074 | AG91: 8 | AH91: 242 | AI91: 3010 | AJ91: 110 | AL91: 211 | AN91: 370 | AO91: 2649 | AP91: 132 | AS91: 28 | AT91: 9 | AU91: 3310 | AV91: 14 | AW91: 1 | BF91: 9 | BG91: 3353 | BI91: 48087 | BK91: 1 | BL91: 3361 | BP91: 700 | BQ91: 408 | BR91: 2 | BS91: 320 | BT91: 10 | BV91: 25 | BW91: 4 | BX91: 1887 | CA91: 6 | CH91: 3362 | CJ91: 2565 | CL91: 738 | CM91: 42 | CN91: 2 | CO91: 7 | CQ91: 8 | CT91: 2 | CU91: 21 | CW91: 1 | CX91: 4 | CY91: 606 | DB91: 558 | DC91: 4 | DD91: 9 | DF91: 112 | DJ91: 1 | DK91: 645 | DL91: 664 | DM91: 735 | DO91: 1 | DQ91: 23 | ED91: 3338 | EF91: 2 | EH91: 4 | EI91: 128 | EJ91: 3228
A92: 106190163 | B92: 190163 | C92: LOS ANGELES | D92: AURORA CHARTER OAK | E92: 1161 E COVINA BLVD | F92: COVINA | G92: 91724 | H92: Investor - Limited Liability Company | I92: Small/Rural | J92: 100-149 | K92: District 22 | L92: District 48 | M92: Asuza/Charter Oak/Covina | N92: Urban | Q92: 6514 | U92: 3684 | V92: 2829 | W92: 1 | Y92: 1221 | Z92: 1719 | AA92: 1405 | AB92: 1055 | AC92: 681 | AD92: 374 | AE92: 52 | AG92: 7 | AH92: 3209 | AI92: 3297 | AJ92: 8 | AK92: 42 | AL92: 366 | AM92: 19 | AN92: 818 | AO92: 5112 | AP92: 33 | AQ92: 104 | AR92: 20 | AS92: 4387 | AT92: 68 | AU92: 1840 | AV92: 1 | AW92: 34 | BA92: 184 | BF92: 1712 | BG92: 4802 | BI92: 47147 | BJ92: 175 | BK92: 6087 | BL92: 252 | BP92: 6014 | BQ92: 25 | BR92: 133 | BS92: 25 | BT92: 3 | BU92: 38 | BV92: 270 | CA92: 3 | CB92: 3 | CH92: 6514 | CJ92: 1054 | CK92: 906 | CL92: 1394 | CN92: 3071 | CO92: 44 | CP92: 2 | CQ92: 43 | CX92: 6513 | CY92: 1 | DO92: 783 | ED92: 5731 | EG92: 2115 | EI92: 29 | EJ92: 4370
A93: 106190170 | B93: 190170 | C93: LOS ANGELES | D93: CHILDREN'S HOSPITAL OF LOS ANGELES | E93: 4650 W SUNSET BLVD | F93: LOS ANGELES | G93: 90027 | H93: Non-profit Corporation (incl. Church-related) | I93: Teaching | J93: 300-499 | K93: District 24 | L93: District 43 | M93: Hollywood South Central/Inner Sunset | N93: Urban | O93: 16893 | S93: 160 | U93: 9528 | V93: 7524 | W93: 1 | X93: 10568 | Y93: 5946 | Z93: 538 | AG93: 1 | AH93: 10458 | AI93: 5737 | AJ93: 858 | AL93: 1031 | AM93: 26 | AN93: 1293 | AO93: 3984 | AP93: 1038 | AQ93: 9055 | AR93: 626 | AS93: 13057 | AT93: 508 | AU93: 2646 | AV93: 1 | AW93: 29 | AX93: 127 | AY93: 597 | BB93: 68 | BC93: 20 | BE93: 9309 | BF93: 1183 | BG93: 6545 | BH93: 16 | BI93: 107362 | BJ93: 8389 | BK93: 4485 | BL93: 3922 | BM93: 20 | BN93: 237 | BP93: 16660 | BQ93: 195 | BS93: 11 | BT93: 26 | BV93: 23 | BW93: 116 | BX93: 10 | BZ93: 9 | CF93: 3 | CG93: 33 | CH93: 16996 | CI93: 24 | CJ93: 38 | CK93: 12438 | CL93: 4152 | CO93: 164 | CQ93: 195 | CR93: 50 | CS93: 16 | CT93: 1158 | CU93: 737 | CV93: 558 | CW93: 626 | CX93: 223 | CY93: 1355 | CZ93: 159 | DA93: 89 | DB93: 317 | DC93: 2961 | DD93: 2248 | DE93: 271 | DF93: 687 | DG93: 608 | DI93: 445 | DJ93: 1452 | DK93: 511 | DL93: 1706 | DM93: 932 | DN93: 10 | DO93: 2256 | DQ93: 947 | DR93: 1488 | DS93: 95 | DT93: 32 | DU93: 137 | DV93: 172 | DW93: 122 | DX93: 320 | DY93: 1298 | DZ93: 646 | EA93: 518 | EB93: 221 | EC93: 225 | ED93: 8418 | EE93: 158 | EF93: 20 | EI93: 214 | EJ93: 16819
A94: 106190176 | B94: 190176 | C94: LOS ANGELES | D94: CITY OF HOPE HELFORD CLINICAL RESEARCH HOSPITAL | E94: 1500 DUARTE RD | F94: DUARTE | G94: 91010 | H94: Non-profit Corporation (incl. Church-related) | I94: Teaching | J94: 200-299 | K94: District 25 | L94: District 48 | M94: Baldwin Park/Irwindale | N94: Urban | O94: 7387 | U94: 3821 | V94: 3566 | X94: 40 | Y94: 151 | Z94: 485 | AA94: 530 | AB94: 869 | AC94: 1498 | AD94: 2107 | AE94: 1330 | AF94: 377 | AH94: 2491 | AI94: 4828 | AJ94: 68 | AK94: 26 | AL94: 1204 | AM94: 29 | AN94: 311 | AO94: 5394 | AP94: 192 | AQ94: 116 | AR94: 115 | AS94: 2361 | AT94: 4554 | AU94: 469 | AV94: 1 | AW94: 2 | BG94: 7387 | BI94: 75518 | BJ94: 1 | BK94: 4254 | BL94: 3132 | BP94: 4275 | BQ94: 35 | BR94: 77 | BS94: 181 | BU94: 1 | BW94: 309 | BX94: 2223 | BZ94: 2 | CA94: 280 | CD94: 4 | CG94: 456 | CH94: 6931 | CJ94: 2712 | CK94: 1217 | CL94: 3304 | CM94: 22 | CO94: 8 | CP94: 29 | CQ94: 90 | CR94: 5 | CT94: 649 | CU94: 3382 | CV94: 145 | CW94: 114 | CX94: 5 | CY94: 123 | CZ94: 7 | DA94: 2 | DB94: 147 | DC94: 309 | DD94: 574 | DE94: 71 | DF94: 143 | DG94: 178 | DJ94: 1 | DK94: 95 | DL94: 613 | DM94: 820 | DN94: 9 | DO94: 1530 | DQ94: 342 | DR94: 1329 | DS94: 15 | DT94: 36 | DV94: 134 | DW94: 790 | DX94: 263 | DY94: 253 | DZ94: 271 | EA94: 49 | EB94: 586 | EC94: 238 | ED94: 1124 | EE94: 427 | EG94: 15 | EI94: 282 | EJ94: 7090
A95: 106190184 | B95: 190184 | C95: LOS ANGELES | D95: COLLEGE HOSPITAL | E95: 10802 COLLEGE PL | F95: CERRITOS | G95: 90703 | H95: Investor - Corporation | I95: Teaching | J95: 150-199 | K95: District 32 | L95: District 58 | M95: Cerritos/Hawaiian Gardens | N95: Urban | Q95: 3560 | U95: 2003 | V95: 1557 | Y95: 734 | Z95: 902 | AA95: 744 | AB95: 504 | AC95: 358 | AD95: 261 | AE95: 54 | AG95: 3 | AH95: 1504 | AI95: 2038 | AJ95: 18 | AK95: 12 | AL95: 238 | AN95: 514 | AO95: 1284 | AP95: 12 | AQ95: 1450 | AR95: 50 | AS95: 3129 | AT95: 13 | AU95: 150 | AV95: 4 | BA95: 264 | BG95: 3560 | BI95: 60077 | BJ95: 329 | BK95: 3231 | BP95: 2808 | BQ95: 168 | BS95: 110 | BT95: 285 | BV95: 141 | BW95: 1 | BZ95: 29 | CB95: 17 | CF95: 1 | CH95: 3560 | CJ95: 425 | CK95: 1017 | CL95: 1852 | CM95: 5 | CN95: 1 | CO95: 113 | CP95: 41 | CQ95: 6 | CR95: 99 | CS95: 1 | CX95: 3560 | DO95: 3559 | ED95: 1 | EF95: 32 | EG95: 322 | EI95: 50 | EJ95: 3156
A96: 106190196 | B96: 190196 | C96: LOS ANGELES | D96: KINDRED HOSPITAL - SOUTH BAY | E96: 1246 W 155TH ST | F96: GARDENA | G96: 90247 | H96: Investor - Limited Liability Company | I96: Teaching | J96: 50-99 | K96: District 35 | L96: District 66 | M96: Gardena Southeast/Harbor Gateway Central/Lawndale South/Moneta/Redondo Beach North/Torrance North | N96: Urban | O96: 422 | U96: 234 | V96: 188 | AB96: 19 | AC96: 40 | AD96: 105 | AE96: 119 | AF96: 127 | AG96: 12 | AH96: 73 | AI96: 343 | AJ96: 6 | AL96: 41 | AN96: 150 | AO96: 140 | AP96: 11 | AQ96: 80 | AT96: 1 | AU96: 406 | AW96: 15 | BG96: 422 | BI96: 16831 | BL96: 422 | BP96: 14 | BQ96: 24 | BR96: 12 | BS96: 185 | BV96: 6 | BW96: 120 | BX96: 45 | CA96: 16 | CG96: 72 | CH96: 350 | CJ96: 297 | CK96: 38 | CL96: 77 | CM96: 2 | CO96: 8 | CT96: 30 | CU96: 6 | CV96: 4 | CW96: 5 | CX96: 2 | CY96: 11 | DB96: 20 | DC96: 201 | DD96: 21 | DE96: 20 | DF96: 10 | DG96: 47 | DK96: 6 | DL96: 21 | DM96: 18 | DO96: 146 | DQ96: 123 | DR96: 25 | DX96: 7 | DY96: 14 | EB96: 9 | EC96: 3 | ED96: 95 | EG96: 7 | EI96: 4 | EJ96: 411
A97: 106190197 | B97: 190197 | C97: LOS ANGELES | D97: COMMUNITY HOSPITAL OF HUNTINGTON PARK | E97: 2623 E SLAUSON AVE | F97: HUNTINGTON PARK | G97: 90255 | H97: Investor - Corporation | I97: Teaching | J97: 50-99 | K97: District 33 | L97: District 53 | M97: Huntington Park/South Gate West/Walnut Park | N97: Urban | O97: 3296 | U97: 1837 | V97: 1459 | Y97: 20 | Z97: 180 | AA97: 283 | AB97: 451 | AC97: 635 | AD97: 695 | AE97: 562 | AF97: 469 | AG97: 1 | AH97: 2666 | AI97: 627 | AJ97: 3 | AL97: 35 | AN97: 397 | AO97: 186 | AP97: 9 | AQ97: 2669 | AS97: 3109 | AT97: 6 | AU97: 72 | AV97: 108 | BB97: 1 | BE97: 3161 | BG97: 135 | BI97: 15199 | BJ97: 3190 | BL97: 104 | BO97: 2 | BP97: 1997 | BQ97: 133 | BR97: 1 | BS97: 331 | BT97: 23 | BV97: 367 | BW97: 132 | BX97: 288 | CA97: 21 | CB97: 3 | CG97: 14 | CH97: 3282 | CJ97: 1186 | CK97: 1912 | CL97: 170 | CM97: 2 | CO97: 4 | CQ97: 19 | CR97: 3 | CT97: 676 | CU97: 35 | CV97: 45 | CW97: 277 | CX97: 68 | CY97: 87 | CZ97: 4 | DA97: 4 | DB97: 701 | DC97: 173 | DD97: 655 | DE97: 78 | DF97: 23 | DG97: 184 | DH97: 21 | DK97: 73 | DL97: 190 | DM97: 1 | DN97: 1 | DO97: 347 | DP97: 7 | DQ97: 353 | DR97: 349 | DV97: 28 | DW97: 1 | DX97: 69 | DY97: 124 | DZ97: 8 | EB97: 31 | EC97: 12 | ED97: 1952 | EE97: 15 | EF97: 22 | EG97: 47 | EI97: 7 | EJ97: 3220
A98: 106190198 | B98: 190198 | C98: LOS ANGELES | D98: LOS ANGELES COMMUNITY HOSPITAL | E98: 4081 E OLYMPIC BLVD | F98: LOS ANGELES | G98: 90023 | H98: Investor - Corporation | I98: Teaching | J98: 100-149 | K98: District 24 | L98: District 51 | M98: City Terrace East/East Los Angeles | N98: Urban | O98: 5635 | P98: 60 | U98: 3220 | V98: 2472 | W98: 3 | Y98: 38 | Z98: 334 | AA98: 544 | AB98: 674 | AC98: 1331 | AD98: 1559 | AE98: 704 | AF98: 511 | AH98: 2646 | AI98: 2834 | AJ98: 215 | AL98: 221 | AM98: 19 | AN98: 1496 | AO98: 1420 | AP98: 263 | AQ98: 2276 | AS98: 645 | AT98: 10 | AU98: 3449 | AV98: 1400 | AW98: 11 | AX98: 179 | BB98: 1 | BE98: 1886 | BF98: 3367 | BG98: 442 | BI98: 34202 | BJ98: 3507 | BK98: 6 | BL98: 2182 | BP98: 2966 | BQ98: 123 | BR98: 6 | BS98: 1576 | BT98: 260 | BU98: 1 | BV98: 284 | BW98: 96 | BX98: 323 | CA98: 26 | CB98: 31 | CD98: 3 | CG98: 108 | CH98: 5587 | CJ98: 1666 | CK98: 3916 | CL98: 93 | CM98: 2 | CO98: 5 | CQ98: 13 | CT98: 1240 | CU98: 63 | CV98: 73 | CW98: 390 | CX98: 138 | CY98: 286 | CZ98: 8 | DA98: 12 | DB98: 627 | DC98: 371 | DD98: 826 | DE98: 250 | DF98: 220 | DG98: 477 | DH98: 14 | DJ98: 1 | DK98: 192 | DL98: 484 | DM98: 23 | DO98: 365 | DP98: 1 | DQ98: 479 | DR98: 550 | DS98: 2 | DU98: 1 | DV98: 29 | DW98: 4 | DX98: 113 | DY98: 278 | DZ98: 10 | EA98: 2 | EB98: 61 | EC98: 25 | ED98: 3750 | EE98: 25 | EF98: 13 | EG98: 184 | EI98: 6 | EJ98: 5492
A99: 106190200 | B99: 190200 | C99: LOS ANGELES | D99: SAN GABRIEL VALLEY MEDICAL CENTER | E99: 438 W LAS TUNAS DR | F99: SAN GABRIEL | G99: 91776 | H99: Investor - Partnership | I99: Teaching | J99: 200-299 | K99: District 22 | L99: District 49 | M99: Alhambra/El Sereno South/San Gabriel Central | N99: Urban | O99: 7654 | P99: 50 | Q99: 430 | T99: 1 | U99: 3293 | V99: 4842 | X99: 981 | Y99: 47 | Z99: 509 | AA99: 962 | AB99: 532 | AC99: 837 | AD99: 1238 | AE99: 1251 | AF99: 1778 | AH99: 2104 | AI99: 6000 | AJ99: 31 | AL99: 4441 | AN99: 242 | AO99: 2979 | AP99: 33 | AQ99: 427 | AR99: 13 | AS99: 6025 | AT99: 20 | AU99: 531 | AV99: 521 | AX99: 48 | AZ99: 1 | BA99: 17 | BC99: 972 | BE99: 4341 | BF99: 214 | BG99: 3580 | BI99: 56832 | BJ99: 4925 | BK99: 1590 | BL99: 648 | BM99: 972 | BP99: 4748 | BQ99: 363 | BR99: 82 | BS99: 1479 | BT99: 66 | BU99: 2 | BV99: 178 | BW99: 279 | BX99: 838 | BZ99: 2 | CA99: 53 | CB99: 34 | CC99: 8 | CD99: 1 | CF99: 2 | CG99: 201 | CH99: 7934 | CJ99: 3823 | CK99: 2772 | CL99: 1336 | CM99: 3 | CO99: 9 | CP99: 10 | CQ99: 182 | CT99: 1066 | CU99: 427 | CV99: 78 | CW99: 387 | CX99: 367 | CY99: 324 | CZ99: 12 | DA99: 22 | DB99: 715 | DC99: 442 | DD99: 728 | DE99: 104 | DF99: 329 | DG99: 398 | DH99: 1101 | DI99: 981 | DJ99: 2 | DK99: 137 | DL99: 486 | DM99: 29 | DO99: 1456 | DP99: 1009 | DQ99: 393 | DR99: 820 | DS99: 4 | DT99: 8 | DU99: 4 | DV99: 298 | DW99: 24 | DX99: 167 | DY99: 566 | DZ99: 46 | EA99: 8 | EB99: 159 | EC99: 62 | ED99: 2975 | EE99: 136 | EF99: 22 | EG99: 28 | EI99: 34 | EJ99: 8051
A100: 106190232 | B100: 190232 | C100: LOS ANGELES | D100: DEL AMO BEHAVIORAL HEALTH SYSTEM | E100: 23700 CAMINO DEL SOL | F100: TORRANCE | G100: 90505 | H100: Investor - Corporation | I100: Teaching | J100: 150-199 | K100: District 26 | L100: District 66 | M100: Harbor Gateway South/Lomita/Torrance East Central | N100: Urban | Q100: 7022 | U100: 2662 | V100: 4359 | W100: 1 | X100: 124 | Y100: 4136 | Z100: 821 | AA100: 658 | AB100: 462 | AC100: 359 | AD100: 328 | AE100: 117 | AF100: 17 | AH100: 2946 | AI100: 3389 | AJ100: 687 | AL100: 188 | AN100: 603 | AO100: 2335 | AP100: 7 | AQ100: 3875 | AR100: 14 | AS100: 474 | AT100: 67 | AU100: 6084 | BA100: 397 | BF100: 6042 | BG100: 980 | BI100: 49887 | BJ100: 200 | BK100: 6815 | BL100: 7 | BP100: 6701 | BQ100: 73 | BS100: 91 | BT100: 11 | BU100: 12 | BV100: 126 | BW100: 1 | CB100: 5 | CE100: 2 | CH100: 7022 | CJ100: 638 | CK100: 3146 | CL100: 2992 | CO100: 227 | CP100: 8 | CQ100: 11 | CW100: 1 | CX100: 7011 | CY100: 3 | DB100: 1 | DM100: 1 | DN100: 5 | DO100: 324 | ED100: 6698 | EF100: 12 | EG100: 677 | EI100: 53 | EJ100: 6280
...

Sheet INSTRUCTIONS & FOOTNOTES
A1: State of California
A2: Department of Health Care Access and Information
A3: ="Patient Discharge Data Pivot Profile, January-December "&MID(Profile!A1,1,4)&" Discharges" -> Patient Discharge Data Pivot Profile, January-December 2022 Discharges
A4: July 2023
A6: NOTE: The Patient Discharge Data Pivot Profile uses the data from all hospitals reporting during the discharge year. No adjustments have been made to the data for any hospitals with reporting modifications, non-compliances, data anomalies, or shortened report periods due to facility openings, closures, or consolidations. The data is aggregated at the facility level. Therefore, it does not contain individually identifiable health information.
A7: INSTRUCTIONS FOR USING THE PIVOT PROFILE:
A9: 1. Make your subsetting selections from the pulldown arrows on the "PIVOT" worksheet. Note: Selecting incompatible parameters (e.g. incorrect county for a facility) may yield errors on the "PROFILE". To get Statewide totals, select "All."
A10: 2. Click on the "PROFILE" worksheet tab to view your results.
A11: 3. Database: The background data that is necessary to run the pivot table is located in the "DATA" worksheet. DO NOT MAKE ANY CHANGES TO THIS WORKSHEET, AS IT CONTAINS MANY LINKS, FORMULAS AND CUSTOM FORMATS THAT CAN EASILY BE CORRUPTED. If you would like to use the data in the "DATA" worksheet, make a copy of it and use the copy (in Excel, 'Copy Sheet' function).
A15: DATA REFERENCES/NOTES:
A16: The purpose of the following notes is to help the data user understand the categorization of selected profile tables. Detailed information regarding the individual data elements can be found in the California Inpatient Data Reporting Manual on the OSHPD web site (www.oshpd.ca.gov).
A19: Disposition | B19: Description
A20: Acute Care | B20: 02=Discharged/transferred to a short term general hospital for inpatient care 82=Discharged/Transferred to a Short Term General Hospital for Inpatient Care with a Planned Acute Care Hospital Inpatient Readmission 63=Discharged/transferred to a Medicare certified long term care hospital (LTCH) 91=Discharged/Transferred to a Medicare certified Long Term Care Hospital (LTCH) with a Planned Acute Care Hospital Inpatient Readmission 43=Discharged/transferred to a federal health care facility 88=Discharged/Transferred to a Federal Health Care Facility with a Planned Acute Care Hospital Inpatient Readmission
A21: Against Medical Advice | B21: 07=Left against medical advice or discontinued care
A22: Children's Hospital or Cancer Center | B22: 05=Discharged/transferred to a designated cancer center or children’s hospital 85=Discharged/Transferred to a designated Cancer Center or Children's Hospital with a Planned Acute Care Hospital Inpatient Readmission
A23: Court/Law Enforcement | B23: 21=Discharged/transferred to court/law enforcement 87=Discharged/Transferred to Court/Law Enforcement with a Planned Acute Care Hospital Inpatient Readmission
A24: Critical Access Hospital | B24: 66=Discharged/transferred to a Critical Access Hospital (CAH) 94=Discharged/Transferred to a Critical Access Hospital (CAH) with a Planned Acute Care Hospital Inpatient Readmission
A25: Died | B25: 20=Expired
A26: Disaster Care Site | B26: 69=Discharged/Transferred to a designated Disaster Alternative Care Site
A27: Home Health Services | B27: 06=Discharged/transferred to home under care of organized home health service organization in anticipation of covered skilled care 86=Discharged/Transferred to home under care of organized home health service organization with a Planned Acute Care Hospital Inpatient Readmission
A28: Hospice Care | B28: 50=Discharged home with hospice care 51=Discharged to a medical facility with hospice care
A29: Inpatient Rehabilitation | B29: 62=Discharged/transferred to an inpatient rehabilitation facility (IRF) including a rehabilitation distinct part unit of a hospital 90=Discharged/Transferred to an Inpatient Rehabilitation Facility (IRF) including Rehabilitation Distinct Part Unit of a Hospital with a Planned Acute Care Hospital Inpatient Readmission
A30: Invalid/Blank | B30: 99=Invalid/Missing
... A70: Not Valid as Principal Diagnosis | B70: The supplied principal diagnosis is not considered valid in that position.
A72: * Clinical Classifications Software Refined (CCSR). For more information:https://www.hcup-us.ahrq.gov/toolssoftware/ccsr/ccs_refined.jsp
A75: Principal Procedure Group (based on CCS Grouping), | B75: Principal Procedure (ICD-10-PCS) Code Range** These ranges reflect the majority of codes in this grouping, not the entirety of codes.
A77: Miscellaneous diagnostic and therapeutic procedures | B77: F0, 2W, B5, 3E, B3
A78: Obstetrical procedures | B78: 10
A79: Operations on the cardiovascular system | B79: 02, 03, 04, 05, 06
A80: Operations on the digestive system | B80: 0D, 0F, 0W
A81: Operations on the ear | B81: 09
A82: Operations on the endocrine system | B82: 0G
A83: Operations on the female genital organs | B83: 0U
A84: Operations on the hemic and lymphatic system | B84: 07
A85: Operations on the integumentary system | B85: 0J, 0H
A86: Operations on the male genital organs | B86: 0V
A87: Operations on the musculoskeletal system | B87: 0P-0S, 0K-0N, 0X, 0Y
A88: Operations on the nervous system | B88: 00, 01
A89: Operations on the nose; mouth; and pharynx | B89: 0C, 0W
A90: Operations on the respiratory system | B90: 0B, 0W
... A92: No Principal Procedure Reported | B92: -
A94: * Clinical Classifications Software Refined (CCSR). For more information:https: //www.hcup-us.ahrq.gov/toolssoftware/ccsr/ccs_refined.jsp
A96: ** The first two digits of the code groupings are shown. These ranges reflect the majority of codes in this grouping, not the entirety of codes.
A99: Newborn Admit Type
A100: This count includes 'Born in this Hospital', 'Born outside of this hospital' and those records with an 'illogical source of admission'. These are records where the Admit Type is 'Newborn' but the Site of Admission indicattes something other than the expected categories listed above.
A102: Homeless
A103: Hospitals are instructed to report a patient zip code of 'ZZZZZ' for patients who lack a residence. The counts of 'Homeless' patients are based solely on reported patient zip code.
A106: Data De-identification and Masking
A108: Variables requiring masking: | B108: Age Group, Race Group, Ethnicity, Principal Diagnosis Group*, Preferred Language Spoken, Point of Origin, Admission Type
A109: *Only conditions originating in the perinatal period and diagnoses related to pregnancy and childbirth were masked for cells < 11.
A111: Other', 'Blank/Invalid', and 'Unknown' variabls were not masked unless needed for complementary masking.
A113: For variables requiring masking, cells with < 11 were combined with Other_Unknown.
A115: The data de-identification guidelines can be found here: | B115: https://chhsdata.github.io/dataplaybook/documents/CHHS-DDG-V1.0-092316.pdf
